Workbook
Name _Hlk149905875: 'Гидравл. расчет'!$A$22
Name DN_подвод_патрубка: Таблица9[DN подвод патрубка]
Name DN_подвод_патрубка: Таблица9[DN подвод патрубка]
Name Асбестцемент: Таблица9[DN подвод патрубка]
Name Асбестцемент: Таблица9[DN подвод патрубка]
Name Асбестцемент: Таблица9[DN подвод патрубка]
Name Валюта: Таблица72[Валюта]
Name Валюта: Таблица72[Валюта]
Name Группа: Таблица301715[Группа]
Name Давление: Таблица11[Давление]
Name Давление: Таблица11[Давление]
Name Давление: Таблица11[Давление]
Name Давление_для_проч_эл: Таблица44[Давление_для_проч_эл]
Name Давление_для_проч_эл: Таблица44[Давление_для_проч_эл]
Name Давление_для_фланцев: Таблица43[Давление_для_фланцев]
Name Давление_для_фланцев: Таблица43[Давление_для_фланцев]
Name Диаметр: Таблица8[Диаметр]
Name Диаметр: Таблица8[Диаметр]
Name Диаметр: Таблица8[Диаметр]
Name ЕИ: Таблица2[ЕИ]
Name ЕИ: Таблица2[ЕИ]
Name ЕИ: Таблица2[ЕИ]
Name Жесткость: Таблица13[Жесткость]
Name Жесткость: Таблица13[Жесткость]
Name Жесткость: Таблица13[Жесткость]
Name Изделие: Таблица6[Наименование изделия]
Name Изделие: Таблица6[Наименование изделия]
Name Изделие: Таблица6[Наименование изделия]
Name Категории: Списки!$AF$2:$AF$18
Name Категории: Списки!$AF$2:$AF$18
Name Категории: Списки!$AF$2:$AF$18
Name Категории: Списки!$AG$2:$AG$17
Name Материал: Таблица4[Материал]
Name Материал: Таблица4[Материал]
Name Материал: Таблица4[Материал]
Name Материал_трубы: Таблица3[Материал трубы]
Name Метизы: #REF!
Name Отвод: Таблица45[Отвод]
Name Отвод: Таблица45[Отвод]
Name ПВХ: Таблица9[DN подвод патрубка]
Name ПВХ: Таблица9[DN подвод патрубка]
Name ПВХ: Таблица9[DN подвод патрубка]
Name ПНД: Таблица9[DN подвод патрубка]
Name ПНД: Таблица9[DN подвод патрубка]
Name ПНД: Таблица9[DN подвод патрубка]
Name ПП: Таблица9[DN подвод патрубка]
Name ПП: Таблица9[DN подвод патрубка]
Name ПП: Таблица9[DN подвод патрубка]
Name ПЭ: 'Вес трубы, ПЭ трубы'!$U$2:$U$27
Name Среда: Таблица5[Среда]
Name Среда: Таблица5[Среда]
Name Среда: Таблица5[Среда]
Name Тип_емкости: Таблица37[Тип емкости]
Name Тип_емкости: Таблица37[Тип емкости]
Name Тип_ОЛ: Таблица42[Тип_ОЛ]
Name Тип_ОЛ: Таблица42[Тип_ОЛ]
Name Тип_патрубка: Таблица40[Тип патрубка]
Name Тип_патрубка: Таблица40[Тип патрубка]
Name Тройник: Таблица48[Тройник]
Name Тройник: Таблица48[Тройник]

Sheet Инструкции
C1: Инструкции | D1: к содержанию
B3: Что запрещается?
B4: 1. | C4: Изменять названия листов, категорий
B5: 2. | C5: Изменять навзания шапки таблиц во вкладках с Категоряими
B6: 3. | C6: Вставлять в ячейку скопированное из другого файла (можно только через правую кнопку мыши "Вставить значения")
B7: 4. | C7: Менять цвета (если добавляете какие-то цвета в процессе работы, то когда закончите свою раюоту - верните, пожалуйста, исходные цвета
B8: 5. | C8: В наименовании номенклатуры использовать знак "~" (тильда).
B10: Как пользоваться Опросным Листом?
B12: 1. | C12: Заполните поля, выделенные рамкой
B13: 2. | C13: В некоторых полях требуется выбрать из выпадающего списка (например, диаметр, давление, да/нет, и т.д.) в некоторых заполнить произвольным текстом (например, заказчик, объект, комментарии и пр.)
B28: 3. | C28: Распечатайте опросный лист
B30: Как пользоваться Калькулятором?
B32: 1. | C32: Заполняйте ячейки только на белом фоне (они без формул). Ячейки в бежевом цвете НЕ ЗАПОЛНЯТЬ (они содержат формулы).
B52: 2. | C52: В шапке таблицы с вводными данными есть "белые" ячейки, не требующие обязательного заполнения, т.к. значения для расчета уже подставлены автоматически либо по формуле, либо из таблиц, либо из ОЛ. Однако, если требуется иное значение, то в таких случаях предусмотрена возможность ручного ввода. Рядом (слева от значения по умолчанию) стоят "белые" поля, где можете подставить свое значение. Калькулятор будет брать для расчета "ручное" значение. Если в "белом" поле будет пусто, то калькулятор возьмет для расчета уже подставленное значние из "бежевого" поля.
C53: Вставить: форматы.
B69: 3. | C69: В самом калькуляторе многие значения уже подсчитываются по формуле или транслируются из введеных ранее данных или встроенных таблиц, Если же таких автоматически заполненных данных нет, то "открывается" белое окошечко, в которое необходимо подставить значения вручную.
B87: Как заполнять поля?
B89: 1. | C89: Прежде чем выбрать номенклатуру (из выпадающего списка или, если не нашли подходящую, вписать вручную), необходимо выбрать из выпадающего списка категорию номенклатуры
B101: 2. | C101: Заполнить все "белые" ячейки в строке (иногда это количество, цена, иногда ничего заполнять не надо, т.к. все подтянется автоматически, тогда "белых"ячеек не будет)
B102: 3. | C102: В блоке Фальшпол необходимо выбрать ДА/НЕТ (в зависимости от того, что требуется в исходных данных). А вот такие блоки как Теплоизоляция, Корзина, Дробилка - будут атоматически "утопать" белым цветом, что означает "не участвуют в расчете", или будут обычным черным шрифтом, т.е. "участвуют в расчете", в зависимости от того, что выбрано в ОЛ.
B117: Как добавлять/удалять строки
B119: 1. | C119: Выделите ВСЮ строку, НАД которой будете вставлять строку → на верхней панели инструментов вкладка Главная → Вставить
B147: 2. | C147: Выделите любую заполненную строку → Скопируйте (Ctrl+C или правкой кнопкой мыши Копировать) → выделите ВСЮ пустую строку и вставьте то, что скопировали в буфер (Ctrl+V или правой кнопкой мыши Вставить)
C157: Или выбеделите ВСЮ заполненную строку и просто потяните за уголок вниз (или вверх)
B167: 3. | C167: Если необзодимо УДАЛИТЬ, то выделите ВСЮ строку, предназначенную для уделения → на верхней панели инструментов вкладка Главная → Удалить
B170: Как добавлять номенклатуру, цены, скидки и пр. во вкладки Категории
B172: 1. | C172: Важный момент - шапки заголовков и наименования самих вкладов менять НЕЛЬЗЯ.
B174: 2. | C174: Чтобы добавить номенклатуру, необходимо либо вручную внести в пустую строку (формат и формулы подтянуться автоматически) либо скопировать из другого файла, но!!! Через правую кнопку мыши "Вставить значения"
B196: 3. | C196: В графах ЕИ и Валюта выбрать из выпадающего списка необходимую ЕИ и валюту. Или вставить скопированную как описано в п.1. ВНИМАНИЕ! ВСЕ ЕИ и валюта должны быть точно такие же как в выпадающем списке!
B198: 4. | C198: Указать цену, процент скидки. Если необходимо, написать комментарий. Все цены вписывать с НДС.
B200: 5. | C200: Можно исправить курс ЕВРО и ДОЛЛАРА при необходимости
B202: 6. | C202: ячейки с бежевым фоном не исправлять
B205: Как распечатывать лист?
B207: 1. | C207: Откройте Лист, который необходимо распечатать. Проверьте все ли правльно. Можете что-то подредактировать, например, отфильтроввать пустые строки.
B224: 2. | C224: Далее на верхней панеле инструментов Файл → Печать → В разделе Настройки сделать следущие манипуляции:
B226: 2.1. | C226: Если у Вас печать листа, то выбор должен стоять на Напечатать активные листы. Если определенный диапазон (выделить необходимые ячейки), то Напечатать выделенный фрагмент.
B252: 2.2. | C252: Чтобы уместить печать листа на одну страницу необходимо выбрать Вписать лист на одну страницу. В этом случае все, что на листе, будет размещено на одной странице. Посмотрите на образец размещения после печати справа.
C253: Если необзодимо уместить лист только по ширине в пределах одной страницы, а в "длину" можно на нескольких страницах, то выберете Вписать все столбцы на одну страницу. Посмотрите на образоц справа.
B285: 2.3. | C285: Внизу будет показано количество страниц после печати. Если все устраивает,то нажмите Печать.

Sheet Содержание
C1: Содержание | E1: =MID(CELL("имяфайла"),SEARCH("[",CELL("имяфайла"))+1,SEARCH("]",CELL("имяфайла"))-SEARCH("[",CELL("имяфайла"))-1) -> Шаблон 3.0.xlsx
C3: Выберите тип опросного листа | D3: ОЛ емкости | E3: =IF(D3=Списки!BB2,HYPERLINK("["&E1&"]ОЛ_Емкости!A1","Нажмите ссылку, чтобы перейти на ОЛ"),HYPERLINK("["&E1&"]ОЛ_НАСОСНАЯ_СТАНЦИЯ!A1","Нажмите ссылку, чтобы перейти на ОЛ")) -> Нажмите ссылку, чтобы перейти на ОЛ
B6: № | C6: Содержание | D6: Описание
B7: 1 | C7: Инструкции
B8: 2 | C8: Опросный лист
B9: 3 | C9: Калькулятор
B10: 4 | C10: Заявка на закупку
B11: 5 | C11: Днище КНС
B12: 6 | C12: Вес и ПЭ трубы
B13: 7 | C13: Грузоподъем
B14: 8 | C14: Детали трубопровода ПЭ ПВХ PP
B15: 9 | C15: Детали трубопровода сталь
B16: 10 | C16: Запорная арматура
B17: 11 | C17: Металлопрокат
B18: 12 | C18: Метизы
... B23: 17 | C23: Работы

Sheet Списки
A1: Выбор | B1: Стадия | C1: Шкаф управления | D1: Ввод электропитания | E1: Пуск ШУ | F1: Модуль передачи данных в систему диспетчеризации: | G1: Вид насосной станции | H1: Корзина или Дробилка | I1: Тип запорной арматуры | L1: Материал трубы | M1: Тип соединения | P1: Наименование изделия | Q1: Материал | R1: Среда | S1: ЕИ | U1: ЕИ для ОЛ | W1: Валюта | Y1: DN подвод патрубка | Z1: Диаметр | AB1: Давление | AC1: Давление_для_фланцев | AD1: Давление_для_проч_эл | AE1: Жесткость | AG1: Категории | AI1: Труба на части | AK1: Расположение | AM1: Установка | AO1: Тип емкости | AQ1: Д шахты обслуживания | AS1: Класс опасности | AU1: Тип патрубка | AW1: Тип крышки | AY1: Отвод | AZ1: Тройник | BA1: Фланец | BB1: Тип_ОЛ | BC1: Тип емкости | BD1: Вид днища | BF1: Назначение ОЛ | BH1: Тип смолы | BI1: Марка смолы | BJ1: Отдел | BM1: Диапозон давления | BN1: Предполагаемый тип соединения подводящего трубопровода с КНС | BO1: Напорный трубопровод DN150 1+1 | BP1: 1 | BQ1: 1+1
A2: Да | B2: проект | C2: Внутренний | D2: Один | E2: Стандартный | F2: CIM 150 Profibus-DR | G2: КНС | H2: Корзина для мусора | I2: Задвижка клиновая с обрезиненным клином | L2: ПЭ | M2: фланец | P2: Труба | Q2: СК/НПС | R2: К | S2: шт | U2: л/с | W2: руб | Y2: 50 | Z2: 300 | AB2: 0.1 | AC2: 0,1-0,6 | AD2: 0,1-0,4 | AE2: 1250 | AG2: Грузоподъем | AI2: Целая труба | AK2: Горизонтальное | AM2: Наземная | AO2: Накопительная | AQ2: 700 | AS2: I | AU2: Раструб | AW2: Крышка из нерж. стали | AY2: Отвод с углом изгиба от 0 до 30. 15 град | AZ2: Тройник равнопроходной | BA2: Формованный фланец под ламинарное/муфтовое соединение | BB2: ОЛ емкости | BC2: Типовая | BD2: С патрубком | BF2: Материальный расчет | BH2: Стандарт | BI2: ИЗО | BJ2: Дирекция по продажам (Направление продаж трубной продукции) | BM2: 0...0,1 | BP2: 2 | BQ2: 2+1
A3: Нет | B3: рабочая | C3: Уличный | D3: Двойной с АВР | E3: Плавный | F3: CIM 200Modbus RTU/COMLI | G3: ДНС | H3: Дробилка | I3: Задвижка шиберная | L3: ПВХ | M3: муфта | P3: Муфта | Q3: СК/ВЭС | S3: м | U3: м3/ч | W3: евро | Y3: 65 | Z3: 400 | AB3: 0.4 | AC3: 0,6-1,0 | AD3: 0.6 | AE3: 2500 | AG3: Выключатели | AI3: Труба частями | AK3: Вертикальное | AM3: Подземная | AO3: Химстойкая | AQ3: 800 | AS3: II | AU3: Формованный стеклокомпозитный фланец | AW3: Крышка стеклокомпозитная | AY3: Отвод с углом изгиба от 0 до 30. 30 град | BA3: Металлический фланец на формованном упоре | BB3: ОЛ насосной станции | BC3: Сборная | BD3: Без патрубка | BF3: Расчет на всплытие | BH3: Винилэфирная стандарт | BI3: Девинил911 | BJ3: Дирекция по продажам (Направление проектных продаж) | BM3: 0...0,16 | BQ3: нестандартное
B4: кд | E4: Частотный преобразователь | F4: CIM 250 GSM/GPRS | G4: ВНС | H4: Корзина для мусора и Дробилка | I4: Задвижка шиберная с электроприводом | L4: ПНД | M4: раструб | P4: Фасонные детали | S4: кг | U4: м3/сут | W4: долл | Y4: 80 | Z4: 500 | AB4: 0.6 | AC4: 1,0-1,6 | AD4: 1 | AE4: 5000 | AG4: Детали труб_да ПЭ ПВХ PPR | AM4: В помещении | AO4: Аккумулирующая | AQ4: 900 | AS4: III | AU4: Металлический фланец на формованном упоре | AY4: Отвод с углом изгиба от 31 до 60. 45 град | BB4: ОЛ колодца | BF4: Расчет кольцевой жесткости (толщины стенки корпуса) | BH4: Винилэфирная высокотемпературная (до 180°С) | BI4: Derakan470 | BJ4: Дирекция инжиниринга и проектных работ (Проектно-конструкторский отдел) | BM4: 0...0,25
A5: Отправить на подбор смолы | B5: продажа | H5: нет | I5: Задвижка клиновая с обрезиненным клином с электроприводом | L5: ПП | S5: чел. ч | Y5: 100 | Z5: 600 | AB5: 1 | AC5: 1,6-2,0 | AD5: 1.6 | AE5: 10000 | AG5: Детали трубопровода сталь | AM5: Автомобиль | AO5: Питьевая | AQ5: 1000 | AS5: IV | AU5: Фланцевый патрубок с заглушкой | AY5: Отвод с углом изгиба от 31 до 60. 60 град | BF5: Согласовательный чертеж | BJ5: Дирекция инжиниринга и проектных работ (Опытно-технологический отдел) | BM5: 0...0,4
B6: тендер | L6: Асбестцемент | S6: м² | Y6: 150 | Z6: 700 | AB6: 1.6 | AD6: 2 | AG6: Запорная арматура | AO6: Емкость с насосным оборудованием | AQ6: 1100 | AU6: Фланцевый патрубок | AY6: Отвод с углом изгиба от 61 до 90. 75 град | BJ6: Дирекция инжиниринга и проектных работ (Конструкторско-технологический отдел) | BM6: 0...0,6
A7: 6 | L7: Труба Корсис | S7: руб/м | Y7: 200 | Z7: 800 | AB7: 2 | AG7: Металлопрокат | AQ7: 1200 | AY7: Отвод с углом изгиба от 61 до 90. 90 град | BJ7: Дирекция по развитию (Отдел продаж емкостного оборудования) | BM7: 0…1
A8: 12 | L8: Труба стеклокомпозитная | Y8: 250 | Z8: 900 | AB8: 2.5 | AG8: Метизы | AQ8: 1300 | BJ8: Департамент по закупкам и логистике | BM8: 0…1,6
Y9: 300 | Z9: 1000 | AB9: 3.2 | AG9: Прочее оборудование | AQ9: 1400 | BM9: 0…2,5
Y10: 350 | Z10: 1100 | AG10: Насосы, АТМ | AQ10: 3000 | BM10: 0…4
E11: =IF(ISBLANK(B11),"",IF(OR(B11=Списки!AG15:AG17),"нет","да")) | Y11: 400 | Z11: 1200 | AG11: Датчики | BM11: 0…6
Y12: 450 | Z12: 1300 | AG12: Расходомеры | BM12: 0…10
Y13: 500 | Z13: 1400 | AG13: Шкафы
Y14: 550 | Z14: 1500 | AG14: Прочие материалы
Y15: 600 | Z15: 1600 | AG15: Собственное производство
Y16: 650 | Z16: 1700 | AG16: Работы
Y17: 700 | Z17: 1800 | AG17: ФОТ
Y18: 750 | Z18: 1900
Y19: 800 | Z19: 2000
Y20: 850 | Z20: 2100
Y21: 900 | Z21: 2200
Y22: 950 | Z22: 2300
Y23: 1000 | Z23: 2400
Y24: 1100 | Z24: 2500
Y25: 1200 | Z25: 2600
Y26: 1300 | Z26: 2700
Y27: 1400 | Z27: 2800
Y28: 1500 | Z28: 2900
Y29: 1600 | Z29: 3000
Z30: 3200
Z31: 3600

Sheet Инструкции1
C1: Инструкции | D1: к содержанию
B3: Что запрещается?
B4: 1. | C4: Изменять названия листов, категорий
B5: 2. | C5: Изменять навзания шапки таблиц во вкладках с Категоряими
B6: 3. | C6: Вставлять в ячейку скопированное из другого файла (можно только через правую кнопку мыши "Вставить значения")
B7: 4. | C7: Менять цвета (если добавляете какие-то цвета в процессе работы, то когда закончите свою раюоту - верните, пожалуйста, исходные цвета
B8: 5. | C8: В наименовании номенклатуры использовать знак "~" (тильда).
B10: Как пользоваться Опросным Листом для КНС?
B12: 1. | C12: Заполните ячейки с общей информацией по задача/объекту
D19: Номер ОЛ вводится вручную
D20: Тип станции можно выбрать из списка
B28: 2.1. | C28: Согласно поставленной задаче выбирается диаметр корпуса и жесткость. Диаметр должен быть согласован с менеджерами (труба со склада или из конкретного выпуска)
D35: Глубина корпуса (подземная часть) расчитывается отдельно рядом с основным полем ОЛ. Если подобранная глубина корпуса не соответствует исходным данным, можно поставить длину вручную
D36: Обязательно для заполнения вкладка по ТТ МВК Да/Нет, т.к. много блоков учтены именно для МВК
B37: 2.2. | C37: Заполняются исходные данные (если таковые имеются): диаметры входных и выходных патрубков, их глубины, количество, материал
D40: Все ячейки из данного блока обязательны к заполнению для разработки мат. расчета.
B54: 2.3. | C54: Основные параметры КНС: расход и расчетный напор для подбора насосного оборудования и габаритов корпуса
D57: Производительность КНС лучше всегда указывать в м3/ч, т.к. подбор габаритов корпуса рассчитывается в м3/ч. Производительность вводится вручную
B64: 2.4. | C64: Подбор корпуса происходит рядом с основным листом КНС. Подбор корпуса зависит от высоты полезного объема, мин. уровня жидкости в КНС. В этой таблице вручную заполняется только уровень из тех. паспорта насоса, высота рамы насосов, остальные параметра - расчетные
D67: Согласно ТЗ (или поставленной задаче) выбирается количество пусков насосов в час: 5,10,20 пусков в час, 5-10-20 минутная работа насосов)
D73: Мин.уровень жидкости для работы насоса указан в тех.паспорте подобранного насоса
D74: Например: уровень C.W.L.
B86: 2.5. | C86: После предварительного подбора корпуса заполняются данные о шкафах управления (если таковые имеются), наличии датчиков, доп. Оборудования и теплоизоляции
B97: Как пользоваться Калькулятором?
C99: Заполняйте ячейки только на белом фоне (они без формул). Ячейки в бежевом цвете НЕ ЗАПОЛНЯТЬ (они содержат формулы).
C117: Если нужно посчитать не по формуле, а поставить конкретное число, то для этого по всему калькулятору есть столбец Н. То есть в любой строчке расчета можно поставить значение вручную,
B132: Как заполнять поля?
C134: Прежде чем выбрать номенклатуру (из выпадающего списка или, если не нашли подходящую, вписать вручную), необходимо выбрать из выпадающего списка категорию номенклатуры. То есть в каждой категории своя номенклатура.
D136: Вручную можно заполнить наименование оборудования, труб, металлопрокатов, если необходимой позиции нет в выпадающем списке
D141: Согласно выбранной категории подтягивается перечень позиций, и нужная выбирается. Если нужно ввести вручную всегда значения ставятся в столбец Н, если не нужно, все подтягивается автоматически
C150: Если позиция была введена вручную (не из списка номенклатуры), то и стоимость этой позиции нужно будет ввести вручную (это будет столбец L)
B170: Как добавлять/удалять строки
B172: 1. | C172: Выделите любую заполненную строку → Скопируйте (Ctrl+C или правкой кнопкой мыши Копировать) → выделите ВСЮ пустую строку и вставьте то, что скопировали в буфер (Ctrl+V или правой кнопкой мыши Вставить)
C179: Или выбеделите ВСЮ заполненную строку и просто потяните за уголок вниз (или вверх)
B190: 3. | C190: Если необзодимо УДАЛИТЬ, то выделите ВСЮ строку, предназначенную для уделения → на верхней панели инструментов вкладка Главная → Удалить
B193: Как добавлять номенклатуру, цены, скидки и пр. во вкладки Категории
B195: 1. | C195: Важный момент - шапки заголовков и наименования самих вкладок менять НЕЛЬЗЯ.
B197: 2. | C197: Чтобы добавить номенклатуру, необходимо либо вручную внести в пустую строку (формат и формулы подтянуться автоматически) либо скопировать из другого файла, но!!! Через правую кнопку мыши "Вставить значения"
B217: 3. | C217: В графах ЕИ и Валюта выбрать из выпадающего списка необходимую ЕИ и валюту. Или вставить скопированную как описано в п.1. ВНИМАНИЕ! ВСЕ ЕИ и валюта должны быть точно такие же как в выпадающем списке!
B219: 4. | C219: Указать цену, процент скидки. Если необходимо, написать комментарий. Все цены вписывать с НДС.
B221: 5. | C221: Можно исправить курс ЕВРО и ДОЛЛАРА при необходимости
B223: 6. | C223: ячейки с бежевым фоном не исправлять

Sheet ОЛ_КОЛОДЦА
B1: ОБЩЕСТВО С ОГРАНИЧЕННОЙ ОТВЕТСТВЕННОСТЬЮ «НОВЫЕ ТРУБНЫЕ ТЕХНОЛОГИИ» 141320, Московская область, г.о. Сергиево-Посадский, д. Коврово, д. 50, помещ. 2 E-mail: info@ntt.su, тел/факс: +7(499) 949-14-04
C4: ОПРОСНЫЙ ЛИСТ КОЛОДЦА
C6: *к заявке ООО «НТТ» № | E6: ОЛ/
C7: Тип колодца | E7: Распределительный
C8: Назначение ОЛ* | D8: → | E8: Материальный расчет
C9: *(выберите одно или несколько назначений) | D9: →
D10: →
D11: →
C12: *Дата заполнения:
C13: *Заказчик:
C14: Стадия проекта:
C15: Объект:
C16: Регион объекта:
C18: Предполагаемые параметры колодца:
C19: *Диаметр рабочей части колодца DN, мм | E19: 2000
C20: *Давление PN, Мпа | E20: 0.1
C21: *Жесткость SN, Па | E21: 5000
C22: Склад | D22: =IF(C22="Производство","Общий метраж выпуска →","Номер заказа →") -> Номер заказа →
C23: Высота возвышения корпуса горловины/корпуса колодца над землей, мм | E23: 300
C24: Установка под проезжей частью (Да/Нет): | E24: Нет
C25: *Глубина рабочей части корпуса (H), мм | E25: 4000
C26: Наличие горловины колодца | E26: Да
C27: Диаметр горловины колодца d,мм | E27: 1200
C28: Высота горловины h (до верха рабочей части емкости), мм | E28: 1800
C30: Лестница | E30: Да
C32: Смола:
C33: Тип смолы | E33: Стандарт
C34: Марка смолы | E34: =VLOOKUP(E33,Списки!$BH$1:$BI$4,2,) -> ИЗО
C35: MAX температура жидкости, оС
C36: Вид стоков | E36: Хозяйственно-бытовые
C37: Возможное MAX внутреннее давление, кг/см2
C39: Параметры патрубков:
C40: подводящего | G40: отводящего
C41: Материал подводящего патрубка | E41: ПЭ | G41: Материал отводящего патрубка | I41: ПЭ
C42: Глубина залегания H лотка, мм | E42: 2000 | G42: Глубина залегания, мм | I42: 2500
C43: Проходной (внутренний) диаметр, DА, мм. | E43: 300 | G43: Проходной (внутренний) диаметр, DB, мм. | I43: 300
C44: Направление подводящего патрубка, в часах | G44: Направление отводящего патрубка, в часах
C45: Количество подводящих патрубков, шт. | E45: 1 | G45: Количество отводящих патрубков, шт. | I45: 2
C47: Наличие дополнительного оборудования: | E47: Да
C48: Наличие дробилки/корзины для мусора | E48: Корзина для мусора
C49: Наличие запорной арматуры на подводящем трубопроводе | E49: Да
E50: Задвижка шиберная
C52: Шкаф управления | E52: Нет | G52: Датчики: | I52: Да
C53: Тип: | E53: Уличный | G53: давления | I53: Нет
C54: Марка шкафа: | G54: температуры | I54: Нет
C55: Ввод электропитания: | E55: Один | G55: уровня | I55: Нет
C56: Пуск ШУ: | E56: Стандартный | G56: манометр | I56: Нет
C57: Модуль передачи данных в систему диспетчеризации: | E57: CIM 250 GSM/GPRS | G57: расходомер | I57: Нет
C59: *Теплоизоляция | E59: Да
C60: Глубина теплоизоляции, мм | E60: 2000
C62: Обязательные дополнения к заявке:
C64: * - поля обязательные для заполнения
C66: Приложение: документы заказчика на
C69: Менеджер отдела продаж емкостного оборудования ООО «НТТ» | F69: ______________________________ (________________________)
C71: Начальник отдела продаж емкостного оборудования ООО «НТТ» | F71: ______________________________ (________________________)

Sheet Калькулятор колодца
C1: Материальный расчет | M1: к содержанию
C3: Дата заполнения таблицы | D3: Заказчик/ Объект/ Вид насосной станции/ Параметры | G3: DN трубы, мм | H3: Глубина корп., L мм | I3: Высота возвышения корпуса горловины/корпуса колодца над землей, мм | J3: DN вход. патрубка, мм | K3: Кол-во вход. патрубков, шт | L3: DN вых.патрубка, мм | M3: Кол-во выход. патрубков, шт | N3: Высота горловины, мм
H4: =IF(H5<3000,3000,IF(AND(H5>7000),12000,CEILING(H5,500))) -> 4000 | I4: =CONCATENATE(G5,"-b") -> 2000-b
D5: ="Заявка № "&ОЛ_КОЛОДЦА!E6&" "&ОЛ_КОЛОДЦА!E13&" "&ОЛ_КОЛОДЦА!E15&" "&ОЛ_КОЛОДЦА!E16&" "&G5&"х"&H5&"мм" -> Заявка № ОЛ/ 2000х4000мм | G5: =ОЛ_КОЛОДЦА!E19 -> 2000 | H5: =IF(ОЛ_КОЛОДЦА!E26="да",ОЛ_КОЛОДЦА!E25,ОЛ_КОЛОДЦА!E25+I5) -> 4000 | I5: =ОЛ_КОЛОДЦА!E23 -> 300 | J5: =ОЛ_КОЛОДЦА!E43 -> 300 | K5: =ОЛ_КОЛОДЦА!E45 -> 1 | L5: =ОЛ_КОЛОДЦА!I43 -> 300 | M5: =ОЛ_КОЛОДЦА!I45 -> 2 | N5: =IF(ОЛ_КОЛОДЦА!E26="да",ОЛ_КОЛОДЦА!E28+I5,0) -> 2100
C6: Наименование изделия | D6: Материал изделия | E6: Транспортируемая среда | F6: Давление трубопровода, PN МПа | H6: Жесткость, SN Па | J6: D гильзы для прохода вход.патрубка, мм | L6: D гильзы для прохода выход. труб-да, мм | N6: Диаметр горовины, мм
F7: =IF(AND('Калькулятор колодца'!G8>0.6,OR(CONCATENATE('Калькулятор колодца'!G5,'Калькулятор колодца'!I8)=CONCATENATE('Вес трубы, ПЭ трубы'!B51,'Вес трубы, ПЭ трубы'!C51),CONCATENATE('Калькулятор колодца'!G5,'Калькулятор колодца'!I8)=CONCATENATE('Вес трубы, ПЭ трубы'!B55,'Вес трубы, ПЭ трубы'!C55),CONCATENATE('Калькулятор колодца'!G5,'Калькулятор колодца'!I8)=CONCATENATE('Вес трубы, ПЭ трубы'!B57,'Вес трубы, ПЭ трубы'!C57))),1.6,IF(AND(G5=1300,OR(I8=5000,I8=10000),'Калькулятор колодца'!G8<=0.4),0.4,IF(G8<=0.6,0.6,1))) -> 0.6 | J7: +100 | K7: Вручную | L7: +100 | M7: Вручную
C8: Труба | D8: СК/НПС | E8: К | G8: =ОЛ_КОЛОДЦА!E20 -> 0.1 | I8: =ОЛ_КОЛОДЦА!E21 -> 5000 | K8: =IF(J5>=200,_xlfn.CEILING.MATH(IF(J5<100,J5,J5+100),100),_xlfn.CEILING.MATH(IF(J5<100,J5,J5+100),50)) -> 400 | M8: =IF(L5>=200,_xlfn.CEILING.MATH(IF(L5<100,L5,L5+100),100),_xlfn.CEILING.MATH(IF(L5<100,L5,L5+100),50)) -> 400 | N8: =IF(ОЛ_КОЛОДЦА!E26="нет","0",ОЛ_КОЛОДЦА!E27) -> 1200
B9: № | C9: Категория | D9: Материалы,работы, услуги. | F9: Закупка | G9: Вес, кг/пм | H9: Кол-во за 1 ед. | J9: Общ. кол-во | K9: ЕИ | L9: Цена за 1 ед., руб | N9: Сумма, руб | O9: Примечание | P9: МТО | Q9: Логистика
B11: 1 | D11: =CONCATENATE("Корпус колодца ",G5,"х",H5,"мм"," ","(где ",I5,"мм"," - подземная часть), в т.ч.:") -> Корпус колодца 2000х4000мм (где 300мм - подземная часть), в т.ч.:
B12: 1.1 | D12: Корпус. Материалы
I13: Кол-во корпусов: | J13: 1 | K13: шт
C14: Собственное производство | D14: =IF(C8="","",CONCATENATE(C8," ",D8,"-",E8," ",G5,"-",G8,"-",I8)) -> Труба СК/НПС-К 2000-0,1-5000 | E14: Целая труба | F14: =IF(E14=Списки!AI3,"Справочно","") | G14: =IFERROR(I14*INDEX('Вес трубы, ПЭ трубы'!E:G,MATCH(CONCATENATE(G5&";"&F7&";"&I8),'Вес трубы, ПЭ трубы'!E:E,),3),"") -> 1585.2 | I14: =H5/1000 -> 4 | J14: =IF(H14="",I14,H14) -> 4 | K14: м | L14: 1 | M14: =IFERROR(IF(L14<>"","",VLOOKUP(C14&D14&K14,НН!A:J,10,)),"") | N14: =IFERROR(IF(L14="",M14*J14,J14*L14),"") -> 4
C15: Собственное производство | D15: Придание изделию товарного вида | F15: {=IF(C15="","",IF(OR(C15=Списки!$AG$15:$AG$17),"нет","да"))} -> нет | I15: =$G$5/1300*J14 -> 6.1538462 | J15: =ROUNDUP(IF($E$14=Списки!$AI$2,IF(H15="",I15,H15),0),1) -> 6.2 | K15: чел. ч | M15: =IFERROR(IF(L15<>"","",VLOOKUP(C15&D15&K15,НН!A:J,10,)),"") -> 1207.8 | N15: =IFERROR(IF(L15="",M15*J15,J15*L15),"") -> 7488.36
C16: Собственное производство | D16: =IF(C8="","",CONCATENATE(C8," ",D8,"-",E8," ",G5,"-",G8,"-",I8)) -> Труба СК/НПС-К 2000-0,1-5000 | F16: нет | G16: =IFERROR(I16*INDEX('Вес трубы, ПЭ трубы'!E:G,MATCH(CONCATENATE(#REF!&";"&F8&";"&#REF!),'Вес трубы, ПЭ трубы'!E:E,),3),"") | J16: =IF($E$14=Списки!$AI$2,0,IF(H16="",I16,H16)) -> 0 | K16: м | M16: =IFERROR(IF(L16<>"","",VLOOKUP(C16&D16&K16,НН!A:J,10,)),"") | N16: =IFERROR(IF(L16="",SUM(#REF!),J16*L16),0) -> 0
C17: Собственное производство | D17: Придание изделию товарного вида | F17: {=IF(C17="","",IF(OR(C17=Списки!$AG$15:$AG$17),"нет","да"))} -> нет | I17: =$G$5/1300*J16 -> 0 | J17: =ROUNDUP(IF(H17="",I17,H17),1) -> 0 | K17: чел. ч | M17: =IFERROR(IF(L17<>"","",VLOOKUP(C17&D17&K17,НН!A:J,10,)),"") -> 1207.8 | N17: =IFERROR(IF(L17="",M17*J17,J17*L17),"") -> 0
C18: Собственное производство | D18: =IF(C8="","",CONCATENATE(C8," ",D8,"-",E8," ",G5,"-",G8,"-",I8)) -> Труба СК/НПС-К 2000-0,1-5000 | F18: нет | J18: =IF($E$14=Списки!$AI$2,0,IF(H18="",I18,H18)) -> 0 | K18: м | M18: =IFERROR(IF(L18<>"","",VLOOKUP(C18&D18&K18,НН!A:J,10,)),"") | N18: =IFERROR(IF(L18="",SUM(#REF!),J18*L18),0) -> 0
C19: Собственное производство | D19: Придание изделию товарного вида | F19: {=IF(C19="","",IF(OR(C19=Списки!$AG$15:$AG$17),"нет","да"))} -> нет | I19: =$G$5/1300*J18 -> 0 | J19: =ROUNDUP(IF(H19="",I19,H19),1) -> 0 | K19: чел. ч | M19: =IFERROR(IF(L19<>"","",VLOOKUP(C19&D19&K19,НН!A:J,10,)),"") -> 1207.8 | N19: =IFERROR(IF(L19="",M19*J19,J19*L19),"") -> 0
C20: Собственное производство | D20: =IF(C8="","",CONCATENATE("Муфта-1 ",D8,"-",E8," ",G5,"-",1)) -> Муфта-1 СК/НПС-К 2000-1 | F20: нет | H20: 1 | J20: =IF($E$14=Списки!$AI$2,0,IF(H20="",I20,H20)) -> 0 | K20: шт | M20: =IFERROR(IF(L20<>"","",VLOOKUP(C20&D20&K20,НН!A:J,10,)),"") | N20: =IFERROR(IF(L20="",M20*J20,J20*L20),0) -> 0
C21: Собственное производство | D21: =IF(C43="да","Механическое формованное дно","Механическая формовка плоского днища") -> Механическое формованное дно | F21: {=IF(C21="","",IF(OR(C21=Списки!$AG$15:$AG$17),"нет","да"))} -> нет | I21: =((PI()*(($G$5+300)/(1000*2))^2)*0.01*1850)+(((G5/1000)^2*PI()*0.008*1850)/4) -> 123.35856 | J21: =IF(H21="",I21,H21) -> 123.35856 | K21: кг | M21: =IFERROR(IF(L21<>"","",VLOOKUP(C21&D21&K21,НН!A:J,10,)),"") -> 214.4 | N21: =IFERROR(IF(L21="",M21*J21,J21*L21),"") -> 26448.076
C22: ФОТ | D22: ФОТ | F22: {=IF(C22="","",IF(OR(C22=Списки!$AG$15:$AG$17),"нет","да"))} -> нет | I22: =IF(COUNTIF(D21,"*мех*")=1,0.28,IF(COUNTIF(D21,"*ламин*")=1,0.56,1)) -> 0.28 | J22: =ROUNDUP(IF(H22="",IFERROR(J21*I22,""),H22),1) -> 34.6 | K22: чел. ч | M22: =IFERROR(IF(L22<>"","",VLOOKUP(C22&D22&K22,НН!A:J,10,)),"") -> 1207.8 | N22: =IFERROR(IF(L22="",M22*J22,J22*L22),"") -> 41789.88
C23: Собственное производство | D23: =IF(C43="да","Ламинирование дна к фальшполу","Ламинирование плоского днища") -> Ламинирование дна к фальшполу | F23: {=IF(C23="","",IF(OR(C23=Списки!$AG$15:$AG$17),"нет","да"))} -> нет | I23: =IF(H23="",IFERROR(IF(H21="",J21,H21)*3/10,""),"") -> 37.007569 | J23: =IF(H23="",I23,H23) -> 37.007569 | K23: кг | M23: =IFERROR(IF(L23<>"","",VLOOKUP(C23&D23&K23,НН!A:J,10,)),"") -> 310.2 | N23: =IFERROR(IF(L23="",M23*J23,J23*L23),"") -> 11479.748
C24: ФОТ | D24: ФОТ | F24: {=IF(C24="","",IF(OR(C24=Списки!$AG$15:$AG$17),"нет","да"))} -> нет | I24: =IF(COUNTIF(D23,"*мех*")=1,0.28,IF(COUNTIF(D23,"*ламин*")=1,0.56,1)) -> 0.56 | J24: =ROUNDUP(IF(H24="",IFERROR(J23*I24,""),H24),1) -> 20.8 | K24: чел. ч | M24: =IFERROR(IF(L24<>"","",VLOOKUP(C24&D24&K24,НН!A:J,10,)),"") -> 1207.8 | N24: =IFERROR(IF(L24="",M24*J24,J24*L24),"") -> 25122.24
D25: Входящий патрубок
C26: Собственное производство | D26: =IF('Калькулятор колодца'!E41="Труба стеклокомпозитная","Муфта-2 СК/НПС-К "&J$5&"-1",IF(ОЛ_КОЛОДЦА!E41=Списки!L$8,IF(J$5>=300,"Труба СК/НПС-К "&K$8&"-0,1-2500","Ручная формовка патрубка"),IF(J$5>=200,"Труба СК/НПС-К "&_xlfn.CEILING.MATH(IF(J$8="",K$8,J$8),50)&"-0,1-2500","Ручная формовка патрубка"))) -> Труба СК/НПС-К 400-0,1-2500 | E26: =IF('Калькулятор колодца'!E41="Труба стеклокомпозитная","Муфта-2 СК/НПС-К "&J$5&"-1","Стеклокомпозитная гильза Ø"&K$8) -> Стеклокомпозитная гильза Ø400 | F26: {=IF(C26="","",IF(OR(C26=Списки!$AG$15:$AG$17),"нет","да"))} -> нет | J26: =IFERROR(IF(SEARCH("*гильза*",E26)=1,0.5*$K$5),VLOOKUP(IF(J8="",K8,J8),'Для расчетов'!$A$36:$F$60,4,)*$K$5) -> 0.5 | K26: =IFERROR(IF(SEARCH("*труба*",D26)=1,"м"),"кг") -> м | L26: =IFERROR(IF(SEARCH("м",K26)=1,"1.00"),"") -> 1.00 | M26: =IFERROR(IF(L26<>"","",VLOOKUP(C26&D26&K26,НН!A:J,10,)),"") | N26: =IFERROR(IF(L26="",M26*J26,J26*L26),0) -> 0
C27: Собственное производство | D27: Придание изделию товарного вида | I27: =K8/1300*J26 -> 0.15384615 | J27: =IF(COUNTIF(D26,"*труба*")=1,K8/1300*J26,0) -> 0.15384615 | K27: чел. ч | M27: =IFERROR(IF(L27<>"","",VLOOKUP(C27&D27&K27,НН!A:J,10,)),"") -> 1207.8 | N27: =IFERROR(IF(L27="",M27*J27,J27*L27),"") -> 185.81538
C28: Собственное производство | D28: =IFERROR(IF(SEARCH("*муфта*",E26)=1,"Ламинирование проходной муфты к корпусу"),"Ламинирование патрубка к корпусу") -> Ламинирование патрубка к корпусу | F28: {=IF(C28="","",IF(OR(C28=Списки!$AG$15:$AG$17),"нет","да"))} -> нет | J28: =IF(OR(ОЛ_КОЛОДЦА!$E$43="",ОЛ_КОЛОДЦА!$E$45=""),0,IFERROR(IF(SEARCH("*муфта*",E26)=1,VLOOKUP(IF(J8="",K8,J8),'Для расчетов'!$A$36:$F$60,4,)*3/10*$K$5),VLOOKUP(IF(J8="",K8,J8),'Для расчетов'!$A$36:$F$60,4,)*$K$5*3/10)) -> 0.33 | K28: кг | M28: =IFERROR(IF(L28<>"","",VLOOKUP(C28&D28&K28,НН!A:J,10,)),"") -> 310.2 | N28: =IFERROR(IF(L28="",M28*J28,J28*L28),"") -> 102.366
C29: ФОТ | D29: ФОТ | F29: {=IF(C29="","",IF(OR(C29=Списки!$AG$15:$AG$17),"нет","да"))} -> нет | I29: =IF(COUNTIF(D28,"*мех*")=1,0.28,IF(COUNTIF(D28,"*ламин*")=1,1)) -> 1 | J29: =ROUNDUP(IF(OR(ОЛ_КОЛОДЦА!$E$43="",ОЛ_КОЛОДЦА!$E$45=""),0,IF(H29="",IFERROR(J28*I29,""),H29)),1) -> 0.4 | K29: чел. ч | M29: =IFERROR(IF(L29<>"","",VLOOKUP(C29&D29&K29,НН!A:J,10,)),"") -> 1207.8 | N29: =IFERROR(IF(L29="",M29*J29,J29*L29),"") -> 483.12 | O29: ламинирование патрубка/муфты к корпуск коэффициент = 1
D30: Выходящий патрубок
C31: Собственное производство | D31: =IF(ОЛ_КОЛОДЦА!I41=Списки!L$8,IF(L$5>=300,"Труба СК/НПС-К "&M$8&"-0,1-2500","Ручная формовка патрубка"),IF(L$5>=200,"Труба СК/НПС-К "&_xlfn.CEILING.MATH(IF(L$8="",M$8,L$8),50)&"-0,1-2500","Ручная формовка патрубка")) -> Труба СК/НПС-К 400-0,1-2500 | E31: =IF(ОЛ_КОЛОДЦА!I41="Труба стеклокомпозитная","Муфта-2 СК/НПС-К "&L$5&"-1","Стеклокомпозитная гильза Ø"&M$8) -> Стеклокомпозитная гильза Ø400 | F31: {=IF(C31="","",IF(OR(C31=Списки!$AG$15:$AG$17),"нет","да"))} -> нет | J31: =IFERROR(IF(SEARCH("*гильза*",E31)=1,0.5*$M$5),VLOOKUP(IF(L8="",M8,L8),'Для расчетов'!$A$36:$F$60,4,)*$M$5) -> 1 | K31: =IFERROR(IF(SEARCH("*труба*",D31)=1,"м"),"кг") -> м | L31: =IFERROR(IF(SEARCH("м",K31)=1,"1.00"),"") -> 1.00 | M31: =IFERROR(IF(L31<>"","",VLOOKUP(C31&D31&K31,НН!A:J,10,)),"") | N31: =IFERROR(IF(L31="",M31*J31,J31*L31),0) -> 0
C32: Собственное производство | D32: Придание изделию товарного вида | F32: {=IF(C32="","",IF(OR(C32=Списки!$AG$15:$AG$17),"нет","да"))} -> нет | I32: =M8/1300*J31 -> 0.30769231 | J32: =IF(COUNTIF(D31,"*труба*")=1,M8/1300*J31,0) -> 0.30769231 | K32: чел. ч | M32: =IFERROR(IF(L32<>"","",VLOOKUP(C32&D32&K32,НН!A:J,10,)),"") -> 1207.8 | N32: =IFERROR(IF(L32="",M32*J32,J32*L32),"") -> 371.63077
C33: Собственное производство | D33: =IFERROR(IF(SEARCH("*муфта*",E31)=1,"Ламинирование проходной муфты к корпусу"),"Ламинирование патрубка к корпусу") -> Ламинирование патрубка к корпусу | F33: {=IF(C33="","",IF(OR(C33=Списки!$AG$15:$AG$17),"нет","да"))} -> нет | J33: =IF(OR(ОЛ_КОЛОДЦА!$I$43="",ОЛ_КОЛОДЦА!$I$45=""),0,IFERROR(IF(SEARCH("*муфта*",E31)=1,VLOOKUP(IF(J8="",K8,J8),'Для расчетов'!$A$36:$F$60,4,)*3/10*$M$5),VLOOKUP(IF(J8="",K8,J8),'Для расчетов'!$A$36:$F$60,4,)*$M$5*3/10)) -> 0.66 | K33: кг | M33: =IFERROR(IF(L33<>"","",VLOOKUP(C33&D33&K33,НН!A:J,10,)),"") -> 310.2 | N33: =IFERROR(IF(L33="",M33*J33,J33*L33),"") -> 204.732
C34: ФОТ | D34: ФОТ | F34: {=IF(C34="","",IF(OR(C34=Списки!$AG$15:$AG$17),"нет","да"))} -> нет | I34: =IF(COUNTIF(D33,"*мех*")=1,0.28,IF(COUNTIF(D33,"*ламин*")=1,1)) -> 1 | J34: =ROUNDUP(IF(OR(ОЛ_КОЛОДЦА!$I$43="",ОЛ_КОЛОДЦА!$I$45=""),0,IF(H34="",IFERROR(J33*I34,""),H34)),1) -> 0.7 | K34: чел. ч | M34: =IFERROR(IF(L34<>"","",VLOOKUP(C34&D34&K34,НН!A:J,10,)),"") -> 1207.8 | N34: =IFERROR(IF(L34="",M34*J34,J34*L34),"") -> 845.46 | O34: ламинирование патрубка/муфты к корпуск коэффициент = 1
C36: =ОЛ_КОЛОДЦА!E26 -> Да | D36: Горловина для колодца: | E36: DN: | F36: =N8 -> 1200 | G36: SN: | H36: 2500 | I36: PN: | J36: 0.1 | K36: кол-во: | L36: 1 | M36: шт.
C37: Собственное производство | D37: ="Труба СК/НПС-К "&F36&"-"&J36&"-"&H36 -> Труба СК/НПС-К 1200-0,1-2500 | E37: Заготовка трубы для горловины колодца | F37: {=IF(C37="","",IF(OR(C37=Списки!$AG$15:$AG$17),"нет","да"))} -> нет | I37: =N5/1000 -> 2.1 | J37: =IF(ОЛ_КОЛОДЦА!E26="нет",0,IF(H37="",I37,H37)*L36) -> 2.1 | K37: м | L37: 1 | M37: =IFERROR(IF(L37<>"","",VLOOKUP(C37&D37&K37,НН!A:J,10,)),"") | N37: =IFERROR(IF(L37="",SUM(#REF!),J37*L37),0) -> 2.1
C38: Собственное производство | D38: Придание изделию товарного вида | F38: {=IF(C38="","",IF(OR(C38=Списки!$AG$15:$AG$17),"нет","да"))} -> нет | I38: =$F$36/1300*J37 -> 1.9384615 | J38: =ROUNDUP(IF(H38="",I38,H38),1) -> 2 | K38: чел. ч | M38: =IFERROR(IF(L38<>"","",VLOOKUP(C38&D38&K38,НН!A:J,10,)),"") -> 1207.8 | N38: =IFERROR(IF(L38="",M38*J38,J38*L38),"") -> 2415.6
C39: Собственное производство | D39: ="Муфта соединительная Муфта-1 "&F36&"-1" -> Муфта соединительная Муфта-1 1200-1 | E39: Да | F39: {=IF(C39="","",IF(OR(C39=Списки!$AG$15:$AG$17),"нет","да"))} -> нет | I39: 1 | J39: =IF(E39="нет",0,IF(C36="нет",0,IF(H39="",I39,H39)))*L36 -> 1 | K39: шт | L39: 1 | M39: =IFERROR(IF(L39<>"","",VLOOKUP(C39&D39&K39,НН!A:J,10,)),"") | N39: =IFERROR(IF(L39="",M39*J39,J39*L39),"") -> 1
C40: Собственное производство | D40: Ламинирование горловины к корпусу емкости | F40: {=IF(C40="","",IF(OR(C40=Списки!$AG$15:$AG$17),"нет","да"))} -> нет | I40: =IF(ОЛ_КОЛОДЦА!E26="нет",0,VLOOKUP(F36,'Для расчетов'!$A$36:$F$72,4,)) -> 10.3 | J40: =IF($C$36="нет",0,IF(H40="",I40,H40))*L36 -> 10.3 | K40: кг | M40: =IFERROR(IF(L40<>"","",VLOOKUP(C40&D40&K40,НН!A:J,10,)),"") -> 310.2 | N40: =IFERROR(IF(L40="",M40*J40,J40*L40),"") -> 3195.06
C41: ФОТ | D41: ФОТ | F41: {=IF(C41="","",IF(OR(C41=Списки!$AG$15:$AG$17),"нет","да"))} -> нет | I41: =IF(COUNTIF(D40,"*мех*")=1,0.28,IF(COUNTIF(D40,"*ламин*")=1,0.56,1)) -> 0.56 | J41: =ROUNDUP(IF($C$36="нет",0,IFERROR(IF(H41="",J40*I41,H41),"")),1) -> 5.8 | K41: чел. ч | M41: =IFERROR(IF(L41<>"","",VLOOKUP(C41&D41&K41,НН!A:J,10,)),"") -> 1207.8 | N41: =IFERROR(IF(L41="",M41*J41,J41*L41),"") -> 7005.24
F42: {=IF(ISBLANK(C42),"",IF(OR(C42=Списки!$AG$15:$AG$17),"нет","да"))} | J42: =IF(ISBLANK(D42),"",IF(H42="",I42,H42)) | M42: =IFERROR(IF(L42<>"","",VLOOKUP(C42&D42&K42,НН!A:J,10,)),"") | N42: =IFERROR(IF(L42="",M42*J42,J42*L42),"")
C43: Да | D43: Фальшпол:
C44: Детали труб_да ПЭ ПВХ PPR | D44: Труба ПВХ Ду160 оранжевая (наружная) | E44: Отверстия для гильз под бетон 2шт | F44: {=IF(C44="","",IF(OR(C44=Списки!$AG$15:$AG$17),"нет","да"))} -> да | I44: 1 | J44: =IF(C43="НЕТ",0,I44) -> 1 | K44: м | M44: =IFERROR(IF(L44<>"","",VLOOKUP(C44&D44&K44,НН!A:J,10,)),"") -> 2901 | N44: =IFERROR(IF(L44="",M44*J44,J44*L44),"") -> 2901
C45: Собственное производство | D45: Механическая формовка деталей фальшпола | F45: {=IF(C45="","",IF($C$43="нет","-",IF(OR(C45=Списки!$AG$15:$AG$17),"нет","да")))} -> нет | H45: =4*0.01*1850 -> 74 | J45: =IF($C$43="нет",0,IF(H45="",I45,H45)) -> 74 | K45: кг | M45: =IFERROR(IF(L45<>"","",VLOOKUP(C45&D45&K45,НН!A:J,10,)),"") -> 214.4 | N45: =IFERROR(IF(L45="",M45*J45,J45*L45),"") -> 15865.6
C46: ФОТ | D46: ФОТ | F46: {=IF(C46="","",IF($C$43="нет","-",IF(OR(C46=Списки!$AG$15:$AG$17),"нет","да")))} -> нет | I46: =IF(COUNTIF(D45,"*мех*")=1,0.28,IF(COUNTIF(D45,"*ламин*")=1,0.56,1)) -> 0.28 | J46: =ROUNDUP(IF(H46="",IFERROR(J45*I46,""),H46),1) -> 20.8 | K46: чел. ч | M46: =IFERROR(IF(L46<>"","",VLOOKUP(C46&D46&K46,НН!A:J,10,)),"") -> 1207.8 | N46: =IFERROR(IF(L46="",M46*J46,J46*L46),"") -> 25122.24
C47: Собственное производство | D47: Ламинирование фальшпола к корпусу | F47: {=IF(C47="","",IF($C$43="нет","-",IF(OR(C47=Списки!$AG$15:$AG$17),"нет","да")))} -> нет | I47: =IF(H47="",3*J45/10,"") -> 22.2 | J47: =IF($C$43="нет",0,IF(H47="",I47,H47)) -> 22.2 | K47: кг | M47: =IFERROR(IF(L47<>"","",VLOOKUP(C47&D47&K47,НН!A:J,10,)),"") -> 310.2 | N47: =IFERROR(IF(L47="",M47*J47,J47*L47),"") -> 6886.44
C48: ФОТ | D48: ФОТ | F48: {=IF(C48="","",IF($C$43="нет","-",IF(OR(C48=Списки!$AG$15:$AG$17),"нет","да")))} -> нет | I48: =IF(COUNTIF(D47,"*мех*")=1,0.28,IF(COUNTIF(D47,"*ламин*")=1,0.56,1)) -> 0.56 | J48: =ROUNDUP(IF(H48="",IFERROR(J47*I48,""),H48),1) -> 12.5 | K48: чел. ч | M48: =IFERROR(IF(L48<>"","",VLOOKUP(C48&D48&K48,НН!A:J,10,)),"") -> 1207.8 | N48: =IFERROR(IF(L48="",M48*J48,J48*L48),"") -> 15097.5
F49: {=IF(ISBLANK(C49),"",IF($C$43="нет","-",IF(OR(C49=Списки!$AG$15:$AG$17),"нет","да")))} | J49: =IF(ISBLANK(D49),"",IF(H49="",I49,H49)) | M49: =IFERROR(IF(L49<>"","",VLOOKUP(C49&D49&K49,НН!A:J,10,)),"") | N49: =IFERROR(IF(L49="",M49*J49,J49*L49),"")
D50: Теплоизоляция: | F50: {=IF(ISBLANK(C50),"",IF(OR(C50=Списки!$AG$15:$AG$17),"нет","да"))} | M50: {=IF(D50="ФОТ",I50*#REF!,IFERROR(IF(L50<>"","",IF((VLOOKUP(D50&K50,INDIRECT("'"&INDEX(Списки!$AG$2:$AG$17,MATCH(TRUE,COUNTIF(INDIRECT("'"&Списки!$AG$2:$AG$17 &"'!A1:A20000"),D50&K50)>0,0))&"'!A:h"),7,0))=0,"",VLOOKUP(D50&K50,INDIRECT("'"&INDEX(Списки!$AG$2:$AG$17,MATCH(TRUE,COUNTIF(INDIRECT("'"&Списки!$AG$2:$AG$17 &"'!A1:A20000"),D50&K50)>0,0))&"'!A:h"),7,0))),""))} | N50: =IFERROR(IF(L50="",M50*J50,J50*L50),"")
C51: Прочие материалы | D51: Теплоизоляция - Изофом ППЭ ОР 15 1,5х40 | E51: Вертикальная изоляция корпуса | F51: {=IF(C51="","",IF(ОЛ_КОЛОДЦА!E59="нет","-",IF(OR(C51=Списки!$AG$15:$AG$17),"нет","да")))} -> да | I51: =PI()*($G$5/(1000*2))^2*ОЛ_КОЛОДЦА!$E$60/1000 -> 6.2831853 | J51: =IF(ОЛ_КОЛОДЦА!$E$59="нет",0,IF(ISBLANK(D51),"",IF(H51="",I51,H51))) -> 6.2831853 | K51: м² | M51: =IFERROR(IF(L51<>"","",VLOOKUP(C51&D51&K51,НН!A:J,10,)),"") -> 750 | N51: =IFERROR(IF(L51="",M51*J51,J51*L51),"") -> 4712.389
C52: Прочие материалы | D52: Теплоизоляция - Изофом ППЭ ОР 15 1,5х40 | E52: Изоляция крышки | F52: {=IF(C52="","",IF(ОЛ_КОЛОДЦА!E59="нет","-",IF(OR(C52=Списки!$AG$15:$AG$17),"нет","да")))} -> да | I52: =PI()*($G$5/(1000*2))^2 -> 3.1415927 | J52: =IF(ОЛ_КОЛОДЦА!$E$59="нет",0,IF(ISBLANK(D52),"",IF(H52="",I52,H52))) -> 3.1415927 | K52: м² | M52: =IFERROR(IF(L52<>"","",VLOOKUP(C52&D52&K52,НН!A:J,10,)),"") -> 750 | N52: =IFERROR(IF(L52="",M52*J52,J52*L52),"") -> 2356.1945
C53: Собственное производство | D53: Защитный слой ламинации 4 мм на теплоизоляцию | F53: {=IF(C53="","",IF(ОЛ_КОЛОДЦА!E59="нет","-",IF(OR(C53=Списки!$AG$15:$AG$17),"нет","да")))} -> нет | I53: =(I51+I52)*0.004*1850 -> 69.743357 | J53: =IF(ОЛ_КОЛОДЦА!$E$59="нет",0,IF(ISBLANK(D53),"",IF(H53="",I53,H53))) -> 69.743357 | K53: кг | M53: =IFERROR(IF(L53<>"","",VLOOKUP(C53&D53&K53,НН!A:J,10,)),"") -> 310.2 | N53: =IFERROR(IF(L53="",M53*J53,J53*L53),"") -> 21634.389
C54: ФОТ | D54: ФОТ | F54: {=IF(C54="","",IF(ОЛ_КОЛОДЦА!E59="нет","-",IF(OR(C54=Списки!$AG$15:$AG$17),"нет","да")))} -> нет | I54: =IF(COUNTIF(D53,"*мех*")=1,0.28,IF(COUNTIF(D53,"*ламин*")=1,0.56,1)) -> 0.56 | J54: =ROUNDUP(IF(ОЛ_КОЛОДЦА!$E$59="нет",0,IF(H54="",IFERROR(J53*I54,""),H54)),1) -> 39.1 | K54: чел. ч | M54: =IFERROR(IF(L54<>"","",VLOOKUP(C54&D54&K54,НН!A:J,10,)),"") -> 1207.8 | N54: =IFERROR(IF(L54="",M54*J54,J54*L54),"") -> 47224.98
M55: =IFERROR(IF(L55<>"","",VLOOKUP(C55&D55&K55,НН!A:J,10,)),"")
C56: Да | D56: =IF(G5<2000,"Петли монтажные по чертежу НТТ 648, в т.ч.:","Петли монтажные усиленные по чертежу НТТ 1959, в т.ч.:") -> Петли монтажные усиленные по чертежу НТТ 1959, в т.ч.: | F56: 4 | G56: шт
C57: =IF(D57="","","Метизы") -> Метизы | D57: =_xlfn.IFNA(IF(ОЛ_КОЛОДЦА!$E$19<2000,'Вспомогат. таблицы'!$A$14,'Вспомогат. таблицы'!$A$2),"") -> Болт М24-6ɡх100.21.Ст20 ГОСТ 7798-70 | E57: =IFERROR(IF(SEARCH("*петель*",D57)=1,IF(#REF!<2000,"Прим. - Петля простая","Прим. - Петля усиленная"),""),"") | F57: {=IF(C57="","",IF(OR(C57=Списки!$AG$15:$AG$17),"нет","да"))} -> да | G57: =IFERROR(3.56*0.14*J57,"") -> 3.9872 | I57: =IFERROR(IF(H57="",IF($G$5>=2000,VLOOKUP(D57,'Вспомогат. таблицы'!$A$2:$B$11,2,),VLOOKUP(D57,'Вспомогат. таблицы'!$A$15:$B$24,2,)),""),"") -> 2 | J57: =IF(C56="нет",0,IF(C57="","",IFERROR(IF(H57="",I57,H57)*$F$56,""))) -> 8 | K57: =IF(C57="","","шт") -> шт | M57: =IFERROR(IF(L57<>"","",VLOOKUP(C57&D57&K57,НН!A:J,10,)),"") -> 105 | N57: =IFERROR(IF(L57="",M57*J57,J57*L57),"") -> 840
C58: Метизы | D58: =IF(ОЛ_КОЛОДЦА!$E$19<2000,'Вспомогат. таблицы'!$A$15,'Вспомогат. таблицы'!$A$3) -> Шайба 24.21.Ст20 ГОСТ 11371-78 | E58: =IFERROR(IF(SEARCH("*петель*",D58)=1,IF(#REF!<2000,"Прим. - Петля простая","Прим. - Петля усиленная"),""),"") | F58: {=IF(C58="","",IF(OR(C58=Списки!$AG$15:$AG$17),"нет","да"))} -> да | G58: =32.3*J58/1000 -> 0.2584 | I58: =IF(H58="",IF($G$5>=2000,VLOOKUP(D58,'Вспомогат. таблицы'!$A$2:$B$11,2,),VLOOKUP(D58,'Вспомогат. таблицы'!$A$15:$B$24,2,)),"") -> 2 | J58: =IF(C56="нет",0,IF(H58="",I58,H58)*$F$56) -> 8 | K58: шт | M58: =IFERROR(IF(L58<>"","",VLOOKUP(C58&D58&K58,НН!A:J,10,)),"") -> 6 | N58: =IFERROR(IF(L58="",M58*J58,J58*L58),"") -> 48
C59: Метизы | D59: =IF(ОЛ_КОЛОДЦА!$E$19<2000,'Вспомогат. таблицы'!$A$16,'Вспомогат. таблицы'!$A$4) -> Шайба 24.30х13 Ст20 ГОСТ 6402-70 | E59: =IFERROR(IF(SEARCH("*петель*",D59)=1,IF(#REF!<2000,"Прим. - Петля простая","Прим. - Петля усиленная"),""),"") | F59: {=IF(C59="","",IF(OR(C59=Списки!$AG$15:$AG$17),"нет","да"))} -> да | I59: =IF(H59="",IF($G$5>=2000,VLOOKUP(D59,'Вспомогат. таблицы'!$A$2:$B$11,2,),VLOOKUP(D59,'Вспомогат. таблицы'!$A$15:$B$24,2,)),"") -> 2 | J59: =IF(C56="нет",0,IF(H59="",I59,H59)*$F$56) -> 8 | K59: шт | M59: =IFERROR(IF(L59<>"","",VLOOKUP(C59&D59&K59,НН!A:J,10,)),"") -> 5.91 | N59: =IFERROR(IF(L59="",M59*J59,J59*L59),"") -> 47.28
C60: Метизы | D60: =IF(ОЛ_КОЛОДЦА!$E$19<2000,'Вспомогат. таблицы'!$A$17,'Вспомогат. таблицы'!$A$5) -> Гайка М24-7Н.Ст20 ГОСТ 5915-70 | E60: =IFERROR(IF(SEARCH("*петель*",D60)=1,IF(#REF!<2000,"Прим. - Петля простая","Прим. - Петля усиленная"),""),"") | F60: {=IF(C60="","",IF(OR(C60=Списки!$AG$15:$AG$17),"нет","да"))} -> да | G60: =27.12*J60/1000 -> 0.21696 | I60: =IF(H60="",IF($G$5>=2000,VLOOKUP(D60,'Вспомогат. таблицы'!$A$2:$B$11,2,),VLOOKUP(D60,'Вспомогат. таблицы'!$A$15:$B$24,2,)),"") -> 2 | J60: =IF(C56="нет",0,IF(H60="",I60,H60)*$F$56) -> 8 | K60: шт | M60: =IFERROR(IF(L60<>"","",VLOOKUP(C60&D60&K60,НН!A:J,10,)),"") -> 28 | N60: =IFERROR(IF(L60="",M60*J60,J60*L60),"") -> 224
C61: Металлопрокат | D61: =IF(ОЛ_КОЛОДЦА!$E$19<2000,'Вспомогат. таблицы'!$A$18,'Вспомогат. таблицы'!$A$6) -> Лист г/к Б-ПН-О-6,0х1500х3000 ГОСТ 19903-74 // Ст3пс ГОСТ 14637-89 | E61: =IFERROR(IF(SEARCH("*петель*",D61)=1,IF(#REF!<2000,"Прим. - Петля простая","Прим. - Петля усиленная"),""),"") | F61: {=IF(C61="","",IF(OR(C61=Списки!$AG$15:$AG$17),"нет","да"))} -> да | G61: =107*J61/1000 -> 0.03424 | I61: =IF(H61="",IF($G$5>=2000,VLOOKUP(D61,'Вспомогат. таблицы'!$A$2:$B$11,2,),VLOOKUP(D61,'Вспомогат. таблицы'!$A$15:$B$24,2,)),"") -> 0.08 | J61: =IF(C56="нет",0,IF(H61="",I61,H61)*$F$56) -> 0.32 | K61: м² | M61: =IFERROR(IF(L61<>"","",VLOOKUP(C61&D61&K61,НН!A:J,10,)),"") -> 5833.33 | N61: =IFERROR(IF(L61="",M61*J61,J61*L61),"") -> 1866.6656
C62: Металлопрокат | D62: =IF(ОЛ_КОЛОДЦА!$E$19<2000,'Вспомогат. таблицы'!$A$19,'Вспомогат. таблицы'!$A$7) -> Лист г/к Б-ПН-О-12,0х1500х3000 ГОСТ 19903-74 // Ст3пс ГОСТ 14637-89 | E62: =IFERROR(IF(SEARCH("*петель*",D62)=1,IF(#REF!<2000,"Прим. - Петля простая","Прим. - Петля усиленная"),""),"") | F62: {=IF(C62="","",IF(OR(C62=Списки!$AG$15:$AG$17),"нет","да"))} -> да | G62: =F56*0.785 -> 3.14 | I62: =IF(H62="",IF($G$5>=2000,VLOOKUP(D62,'Вспомогат. таблицы'!$A$2:$B$11,2,),VLOOKUP(D62,'Вспомогат. таблицы'!$A$15:$B$24,2,)),"") -> 0.05 | J62: =IF(C56="нет",0,IF(H62="",I62,H62)*$F$56) -> 0.2 | K62: м² | M62: =IFERROR(IF(L62<>"","",VLOOKUP(C62&D62&K62,НН!A:J,10,)),"") -> 11222.22 | N62: =IFERROR(IF(L62="",M62*J62,J62*L62),"") -> 2244.444
C63: Металлопрокат | D63: =IF(ОЛ_КОЛОДЦА!$E$19<2000,'Вспомогат. таблицы'!$A$20,'Вспомогат. таблицы'!$A$8) -> Арматура 20-А-I Ст3пс ГОСТ 5781-82 гладкая (А240) | E63: =IFERROR(IF(SEARCH("*петель*",D63)=1,IF(#REF!<2000,"Прим. - Петля простая","Прим. - Петля усиленная"),""),"") | F63: {=IF(C63="","",IF(OR(C63=Списки!$AG$15:$AG$17),"нет","да"))} -> да | G63: =F56*2.26 -> 9.04 | I63: =IF(H63="",IF($G$5>=2000,VLOOKUP(D63,'Вспомогат. таблицы'!$A$2:$B$11,2,),VLOOKUP(D63,'Вспомогат. таблицы'!$A$15:$B$24,2,)),"") -> 0.9 | J63: =IF(C56="нет",0,IF(H63="",I63,H63)*$F$56) -> 3.6 | K63: м | M63: =IFERROR(IF(L63<>"","",VLOOKUP(C63&D63&K63,НН!A:J,10,)),"") -> 190 | N63: =IFERROR(IF(L63="",M63*J63,J63*L63),"") -> 684
C64: Собственное производство | D64: =IF(ОЛ_КОЛОДЦА!$E$19<2000,'Вспомогат. таблицы'!$A$21,'Вспомогат. таблицы'!$A$9) -> Ламинирование петель к корпусу | F64: {=IF(C64="","",IF(OR(C64=Списки!$AG$15:$AG$17),"нет","да"))} -> нет | I64: =IF(H64="",IF($G$5>=2000,VLOOKUP(D64,'Вспомогат. таблицы'!$A$2:$B$11,2,),VLOOKUP(D64,'Вспомогат. таблицы'!$A$15:$B$24,2,)),"") -> 0.6 | J64: =IF(C56="нет",0,IF(H64="",I64,H64)*$F$56) -> 2.4 | K64: кг | M64: =IFERROR(IF(L64<>"","",VLOOKUP(C64&D64&K64,НН!A:J,10,)),"") -> 310.2 | N64: =IFERROR(IF(L64="",M64*J64,J64*L64),"") -> 744.48 | O64: Ламинирование 1 простой петли = 0,4 кг, ламинирование 1 усиленной петли =0,6 кг
C65: ФОТ | D65: =IF(ОЛ_КОЛОДЦА!$E$19<2000,'Вспомогат. таблицы'!$A$22,'Вспомогат. таблицы'!$A$10) -> ФОТ | E65: =IFERROR(IF(SEARCH("*петель*",D65)=1,IF(#REF!<2000,"Прим. - Петля простая","Прим. - Петля усиленная"),""),"") | F65: {=IF(C65="","",IF(OR(C65=Списки!$AG$15:$AG$17),"нет","да"))} -> нет | I65: =IF(COUNTIF(D64,"*мех*")=1,0.28,IF(COUNTIF(D64,"*ламин*")=1,0.56,1)) -> 0.56 | J65: =IF(C56="нет",0,ROUNDUP(IF(H65="",IFERROR(J64*I65,""),H65),1)) -> 1.4 | K65: чел. ч | M65: =IFERROR(IF(L65<>"","",VLOOKUP(C65&D65&K65,НН!A:J,10,)),"") -> 1207.8 | N65: =IFERROR(IF(L65="",M65*J65,J65*L65),"") -> 1690.92
F66: {=IF(ISBLANK(C66),"",IF(OR(C66=Списки!$AG$15:$AG$17),"нет","да"))} | J66: =IF(ISBLANK(D66),"",IF(H66="",I66,H66)) | M66: =IFERROR(IF(L66<>"","",VLOOKUP(C66&D66&K66,НН!A:J,10,)),"") | N66: =IFERROR(IF(L66="",M66*J66,J66*L66),"")
D67: Дробилка: | F67: {=IF(ISBLANK(C67),"",IF(OR(C67=Списки!$AG$15:$AG$17),"нет","да"))} | M67: {=IFERROR(IF(L67<>"","",IF((VLOOKUP(D67&K67,INDIRECT("'"&INDEX(Списки!$AG$2:$AG$17,MATCH(TRUE,COUNTIF(INDIRECT("'"&Списки!$AG$2:$AG$17 &"'!A1:A300000"),D67&K67)>0,0))&"'!A:h"),7,0))=0,"",VLOOKUP(D67&K67,INDIRECT("'"&INDEX(Списки!$AG$2:$AG$17,MATCH(TRUE,COUNTIF(INDIRECT("'"&Списки!$AG$2:$AG$17 &"'!A1:A300000"),D67&K67)>0,0))&"'!A:h"),7,0))),"")}
C68: Собственное производство | D68: Механическая формовка деталей канала под дробилку | F68: {=IF(C68="","",IF(OR(ОЛ_КОЛОДЦА!$E$48=Списки!$H$2,ОЛ_КОЛОДЦА!$E$48=Списки!$H$5),"-",IF(OR(C68=Списки!$AG$15:$AG$17),"нет","да")))} -> - | H68: =4.7*0.007*1850 -> 60.865 | J68: =IF(OR(ОЛ_КОЛОДЦА!$E$48=Списки!$H$2,ОЛ_КОЛОДЦА!$E$48=Списки!$H$5),0,IF(H68="",I68,H68)) -> 0 | K68: кг | M68: =IFERROR(IF(L68<>"","",VLOOKUP(C68&D68&K68,НН!A:J,10,)),"") -> 214.4 | N68: =IFERROR(IF(L68="",M68*J68,J68*L68),"") -> 0
C69: ФОТ | D69: ФОТ | F69: {=IF(C69="","",IF(OR(ОЛ_КОЛОДЦА!$E$48=Списки!$H$2,ОЛ_КОЛОДЦА!$E$48=Списки!$H$5),"-",IF(OR(C69=Списки!$AG$15:$AG$17),"нет","да")))} -> - | I69: =IF(COUNTIF(D68,"*мех*")=1,0.28,IF(COUNTIF(D68,"*ламин*")=1,0.56,1)) -> 0.28 | J69: =ROUNDUP(IF(H69="",IFERROR(J68*I69,""),H69),1) -> 0 | K69: чел. ч | M69: =IFERROR(IF(L69<>"","",VLOOKUP(C69&D69&K69,НН!A:J,10,)),"") -> 1207.8 | N69: =IFERROR(IF(L69="",M69*J69,J69*L69),"") -> 0
C70: Собственное производство | D70: Ламинирование деталей площадки под дробилку в сборке | F70: {=IF(C70="","",IF(OR(ОЛ_КОЛОДЦА!$E$48=Списки!$H$2,ОЛ_КОЛОДЦА!$E$48=Списки!$H$5),"-",IF(OR(C70=Списки!$AG$15:$AG$17),"нет","да")))} -> - | I70: =IF(H70="",IFERROR(IF(H68="",I68,H68)*3/10,""),"") -> 18.2595 | J70: =IF(OR(ОЛ_КОЛОДЦА!$E$48=Списки!$H$2,ОЛ_КОЛОДЦА!$E$48=Списки!$H$5),0,IF(H70="",I70,H70)) -> 0 | K70: кг | M70: =IFERROR(IF(L70<>"","",VLOOKUP(C70&D70&K70,НН!A:J,10,)),"") -> 310.2 | N70: =IFERROR(IF(L70="",M70*J70,J70*L70),"") -> 0
C71: ФОТ | D71: ФОТ | F71: {=IF(C71="","",IF(OR(ОЛ_КОЛОДЦА!$E$48=Списки!$H$2,ОЛ_КОЛОДЦА!$E$48=Списки!$H$5),"-",IF(OR(C71=Списки!$AG$15:$AG$17),"нет","да")))} -> - | I71: =IF(COUNTIF(D70,"*мех*")=1,0.28,IF(COUNTIF(D70,"*ламин*")=1,IF(D70="Ламинирование деталей площадки под дробилку в сборке",1,0.56),1)) -> 1 | J71: =ROUNDUP(IF(H71="",IFERROR(J70*I71,""),H71),1) -> 0 | K71: чел. ч | M71: =IFERROR(IF(L71<>"","",VLOOKUP(C71&D71&K71,НН!A:J,10,)),"") -> 1207.8 | N71: =IFERROR(IF(L71="",M71*J71,J71*L71),"") -> 0 | O71: Коэффициент ламинации 1
C72: Металлопрокат | D72: Уголок 50х50х5мм 12Х18Н10Т (AISI304) ГОСТ 8509-93 | F72: {=IF(C72="","",IF(OR(ОЛ_КОЛОДЦА!$E$48=Списки!$H$2,ОЛ_КОЛОДЦА!$E$48=Списки!$H$5),"-",IF(OR(C72=Списки!$AG$15:$AG$17),"нет","да")))} -> - | I72: =IF(H72="",ROUNDUP(2*(ОЛ_КОЛОДЦА!E42/1000),),"") -> 4 | J72: =IF(OR(ОЛ_КОЛОДЦА!$E$48=Списки!$H$2,ОЛ_КОЛОДЦА!$E$48=Списки!$H$5),0,IF(ISBLANK(D72),"",IF(H72="",I72,H72))) -> 0 | K72: м | M72: =IFERROR(IF(L72<>"","",VLOOKUP(C72&D72&K72,НН!A:J,10,)),"") -> 1500 | N72: =IFERROR(IF(L72="",M72*J72,J72*L72),"") -> 0
C73: Металлопрокат | D73: Круг 5 мм 12Х18Н10Т ГOCT 5949-75 | F73: {=IF(C73="","",IF(OR(ОЛ_КОЛОДЦА!$E$48=Списки!$H$2,ОЛ_КОЛОДЦА!$E$48=Списки!$H$5),"-",IF(OR(C73=Списки!$AG$15:$AG$17),"нет","да")))} -> - | I73: =I74*(3.14*0.05) -> 0.471 | J73: =IF(OR(ОЛ_КОЛОДЦА!$E$48=Списки!$H$2,ОЛ_КОЛОДЦА!$E$48=Списки!$H$5),0,IF(ISBLANK(D73),"",IF(H73="",I73,H73))) -> 0 | K73: м | M73: =IFERROR(IF(L73<>"","",VLOOKUP(C73&D73&K73,НН!A:J,10,)),"") -> 125 | N73: =IFERROR(IF(L73="",M73*J73,J73*L73),"") -> 0
C74: Грузоподъем | D74: Цепь короткозвенная сварная 5 мм DIN 766 А2/А4 | E74: ="Для подъема и спуска дробилки L= "&ROUNDUP((ОЛ_КОЛОДЦА!E42/1000+1),0)&" м" -> Для подъема и спуска дробилки L= 3 м | F74: {=IF(C74="","",IF(OR(ОЛ_КОЛОДЦА!$E$48=Списки!$H$2,ОЛ_КОЛОДЦА!$E$48=Списки!$H$5),"-",IF(OR(C74=Списки!$AG$15:$AG$17),"нет","да")))} -> - | I74: =IF(H74="",ROUNDUP((ОЛ_КОЛОДЦА!E42/1000+1),),"") -> 3 | J74: =IF(OR(ОЛ_КОЛОДЦА!$E$48=Списки!$H$2,ОЛ_КОЛОДЦА!$E$48=Списки!$H$5),0,IF(ISBLANK(D74),"",IF(H74="",I74,H74))) -> 0 | K74: м | M74: =IFERROR(IF(L74<>"","",VLOOKUP(C74&D74&K74,НН!A:J,10,)),"") -> 450 | N74: =IFERROR(IF(L74="",M74*J74,J74*L74),"") -> 0
C75: Грузоподъем | D75: Карабин винтовой 5 мм нерж. А4 ART 8253 | F75: {=IF(C75="","",IF(OR(ОЛ_КОЛОДЦА!$E$48=Списки!$H$2,ОЛ_КОЛОДЦА!$E$48=Списки!$H$5),"-",IF(OR(C75=Списки!$AG$15:$AG$17),"нет","да")))} -> - | I75: =IF(H75="",ROUNDUP(I74/2,),"") -> 2 | J75: =IF(OR(ОЛ_КОЛОДЦА!$E$48=Списки!$H$2,ОЛ_КОЛОДЦА!$E$48=Списки!$H$5),0,IF(ISBLANK(D75),"",IF(H75="",I75,H75))) -> 0 | K75: шт | M75: =IFERROR(IF(L75<>"","",VLOOKUP(C75&D75&K75,НН!A:J,10,)),"") -> 320 | N75: =IFERROR(IF(L75="",M75*J75,J75*L75),"") -> 0
B77: 1.2 | D77: Корпус Работы (ФОТ)
C78: Собственное производство | D78: Предварительные работы для подготовки трубы (транспортировка, разметка осей, шлифовка) | E78: =D14 -> Труба СК/НПС-К 2000-0,1-5000 | F78: {=IF(C78="","",IF(OR(C78=Списки!$AG$15:$AG$17),"нет","да"))} -> нет | I78: =($G$5/(200*6))*J14 -> 6.6666667 | J78: =ROUNDUP(IF(H78="",I78,H78),1) -> 6.7 | K78: чел. ч | M78: =IFERROR(IF(L78<>"","",VLOOKUP(C78&D78&K78,НН!A:J,10,)),"") -> 1207.8 | N78: =IFERROR(IF(L78="",M78*J78,J78*L78),"") -> 8092.26 | O78: DN/(200*6) * Lтр
C79: Собственное производство | D79: Предварительные работы для подготовки трубы (транспортировка, разметка осей, шлифовка) | E79: =D37 -> Труба СК/НПС-К 1200-0,1-2500 | F79: {=IF(C79="","",IF(OR(C79=Списки!$AG$15:$AG$17),"нет","да"))} -> нет | I79: =($F$36/(200*6))*J37 -> 2.1 | J79: =IF(C36="нет",0,ROUNDUP(IF(H79="",I79,H79),1)) -> 2.1 | K79: чел. ч | M79: =IFERROR(IF(L79<>"","",VLOOKUP(C79&D79&K79,НН!A:J,10,)),"") -> 1207.8 | N79: =IFERROR(IF(L79="",M79*J79,J79*L79),"") -> 2536.38 | O79: DN/(200*6) * Lтр
C80: Собственное производство | D80: Прорезка отверстия патрубка в корпусе | E80: =E26 -> Стеклокомпозитная гильза Ø400 | F80: {=IF(C80="","",IF(OR(C80=Списки!$AG$15:$AG$17),"нет","да"))} -> нет | I80: =(K8*3.14*0.5*K5)/1000 -> 0.628 | J80: =ROUNDUP(IF(H80="",I80,H80),1) -> 0.7 | K80: чел. ч | M80: =IFERROR(IF(L80<>"","",VLOOKUP(C80&D80&K80,НН!A:J,10,)),"") -> 1207.8 | N80: =IFERROR(IF(L80="",M80*J80,J80*L80),"") -> 845.46 | O80: прорезка любого отверстия: (DN* П/1000)*0,5*количество патрубков - вырезать 1 м окружности занимает 0,5 чел.ч.
C81: Собственное производство | D81: Прорезка отверстия патрубка в корпусе | E81: =E31 -> Стеклокомпозитная гильза Ø400 | F81: {=IF(C81="","",IF(OR(C81=Списки!$AG$15:$AG$17),"нет","да"))} -> нет | I81: =(M8*3.14*0.5*M5)/1000 -> 1.256 | J81: =ROUNDUP(IF(H81="",I81,H81),1) -> 1.3 | K81: чел. ч | M81: =IFERROR(IF(L81<>"","",VLOOKUP(C81&D81&K81,НН!A:J,10,)),"") -> 1207.8 | N81: =IFERROR(IF(L81="",M81*J81,J81*L81),"") -> 1570.14
C82: Собственное производство | D82: Прорезка отверстия для горловины обслуживания | E82: =F36 -> 1200 | F82: {=IF(C82="","",IF(OR(C82=Списки!$AG$15:$AG$17),"нет","да"))} -> нет | I82: =(E82*3.14*0.5*L36)/1000 -> 1.884 | J82: =IF($C$36="нет",0,ROUNDUP(IF(H82="",I82,H82),1)) -> 1.9 | K82: чел. ч | M82: =IFERROR(IF(L82<>"","",VLOOKUP(C82&D82&K82,НН!A:J,10,)),"") -> 1207.8 | N82: =IFERROR(IF(L82="",M82*J82,J82*L82),"") -> 2294.82
C83: Собственное производство | D83: Изготовление Петель монтажных | F83: {=IF(C83="","",IF(OR(C83=Списки!$AG$15:$AG$17),"нет","да"))} -> нет | I83: =ROUNDUP(0.5*F56,) -> 2 | J83: =IF(C56="нет",0,ROUNDUP(IF(H83="",I83,H83),1)) -> 2 | K83: чел. ч | M83: =IFERROR(IF(L83<>"","",VLOOKUP(C83&D83&K83,НН!A:J,10,)),"") -> 1207.8 | N83: =IFERROR(IF(L83="",M83*J83,J83*L83),"") -> 2415.6 | O83: 0,5 чел. За 1 петлю
C84: Собственное производство | D84: Монтаж Петель монтажных | F84: {=IF(C84="","",IF(OR(C84=Списки!$AG$15:$AG$17),"нет","да"))} -> нет | I84: =ROUNDUP(0.5*F56,) -> 2 | J84: =IF(C56="нет",0,ROUNDUP(IF(H84="",I84,H84),1)) -> 2 | K84: чел. ч | M84: =IFERROR(IF(L84<>"","",VLOOKUP(C84&D84&K84,НН!A:J,10,)),"") -> 1207.8 | N84: =IFERROR(IF(L84="",M84*J84,J84*L84),"") -> 2415.6 | O84: 0,5 чел. За 1 петлю
C85: Собственное производство | D85: Монтаж теплоизоляции | F85: {=IF(C85="","",IF(OR(C85=Списки!$AG$15:$AG$17),"нет","да"))} -> нет | I85: =J51*1+J52*1 -> 9.424778 | J85: =ROUNDUP(IF(ОЛ_КОЛОДЦА!$E$59="нет",0,IF(H85="",I85,H85)),1) -> 9.5 | K85: чел. ч | M85: =IFERROR(IF(L85<>"","",VLOOKUP(C85&D85&K85,НН!A:J,10,)),"") -> 1207.8 | N85: =IFERROR(IF(L85="",M85*J85,J85*L85),"") -> 11474.1 | O85: 1 м2 = 1 чел.ч для вертикальной части корпуса, 1 м2 = 1 чел.ч для изоляции крышки
D86: Последняя строка
E87: Итого: Корпус | G87: =SUM(G14:G86) -> 1601.8768 | N87: =IF($E$14=Списки!$AI$3,SUM($N$16:$N$86),SUM($N$14:$N$86)) -> 308979.31
E88: в т.ч. Материалы на закупку: | N88: {=SUM(SUMIF($C$16:$C$86,Списки!$AG$2:$AG$14,$N$16:$N$86))} -> 15923.973
E89: в т.ч. Труба, муфта: | N89: =IF($E$14=Списки!$AI$3,SUMIFS(N16:N77,D16:D77,"муфта*",F16:F77,"нет")+SUMIFS(N16:N77,D16:D77,"Труба*",F16:F77,"нет"),N14+SUMIFS(N16:N77,D16:D77,"муфта*",F16:F77,"нет")+SUMIFS(N16:N77,D16:D77,"Труба*",F16:F77,"нет"))+SUMIFS(N16:N77,E16:E77,"муфта*",F16:F77,"нет") -> 7.1 | P89: необходимо указать стоимость трубы/муфты
E90: в т.ч. Работы участка фитингов, ФОТ: | J90: =ROUNDUP(SUMIFS($J$14:$J$86,$K$14:$K$86,Списки!$S$5)-SUMIFS($J$14:$J$86,$K$14:$K$86,Списки!$S$5,$D$14:$D$86,"*изготов*"),1) -> 169 | K90: чел. ч | N90: =SUMIF($K$14:$K$86,Списки!$S$5,$N$14:$N$86)-SUMIFS($N$14:$N$86,$K$14:$K$86,Списки!$S$5,$D$14:$D$86,"*изготов*") -> 204071.75
E91: в т.ч. Работы участка РМУ, ФОТ: | J91: =ROUNDUP(SUMIFS($J$14:$J$86,$K$14:$K$86,Списки!$S$5,$D$14:$D$86,"*изготов*"),1) -> 2 | K91: чел. ч | N91: =SUMIFS($N$14:$N$86,$K$14:$K$86,Списки!$S$5,$D$14:$D$86,"*изготов*") -> 2415.6
E92: в т.ч. Формовка: | J92: =SUMIFS($J$14:$J$86,$K$14:$K$86,Списки!$S$4) -> 339.99949 | K92: кг | N92: =SUMIF($K$14:$K$86,Списки!$S$4,$N$14:$N$86) -> 86560.891
B93: 2 | D93: Корзина Материалы: | F93: {=IF(ISBLANK(C93),"",IF(OR(C93=Списки!$AG$15:$AG$17),"нет","да"))} | M93: {=IF(D93="ФОТ",I93*#REF!,IFERROR(IF(L93<>"","",IF((VLOOKUP(D93&K93,INDIRECT("'"&INDEX(Списки!$AG$2:$AG$17,MATCH(TRUE,COUNTIF(INDIRECT("'"&Списки!$AG$2:$AG$17 &"'!A1:A300000"),D93&K93)>0,0))&"'!A:h"),7,0))=0,"",VLOOKUP(D93&K93,INDIRECT("'"&INDEX(Списки!$AG$2:$AG$17,MATCH(TRUE,COUNTIF(INDIRECT("'"&Списки!$AG$2:$AG$17 &"'!A1:A300000"),D93&K93)>0,0))&"'!A:h"),7,0))),""))}
B94: 2.1 | D94: Количество корзин | J94: 1 | K94: шт | M94: {=IFERROR(IF(L94<>"","",IF((VLOOKUP(D94&K94,INDIRECT("'"&INDEX(Списки!$AG$2:$AG$17,MATCH(TRUE,COUNTIF(INDIRECT("'"&Списки!$AG$2:$AG$17 &"'!A1:A300000"),D94&K94)>0,0))&"'!A:h"),7,0))=0,"",VLOOKUP(D94&K94,INDIRECT("'"&INDEX(Списки!$AG$2:$AG$17,MATCH(TRUE,COUNTIF(INDIRECT("'"&Списки!$AG$2:$AG$17 &"'!A1:A300000"),D94&K94)>0,0))&"'!A:h"),7,0))),"")}
C95: Металлопрокат | D95: Уголок 20х20х1,5мм 08Х18Н10Т(AISI304) ГОСТ 8509-93 | F95: {=IF(C95="","",IF(OR(C95=Списки!$AG$15:$AG$17),"нет","да"))} -> да | I95: 10 | J95: =IF(OR(ОЛ_КОЛОДЦА!$E$48=Списки!$H$3,ОЛ_КОЛОДЦА!$E$48=Списки!$H$5),0,IF(H95="",I95,H95))*J94 -> 10 | K95: м | M95: =IFERROR(IF(L95<>"","",VLOOKUP(C95&D95&K95,НН!A:J,10,)),"") -> 850 | N95: =IFERROR(IF(L95="",M95*J95,J95*L95),"") -> 8500
C96: Металлопрокат | D96: Лист нержавеющий перфорированный 1х1000х2000мм Qg 10.0-12.0 марка 10х18н10 | F96: {=IF(C96="","",IF(OR(C96=Списки!$AG$15:$AG$17),"нет","да"))} -> да | I96: =IF(H96="",2,"") -> 2 | J96: =IF(OR(ОЛ_КОЛОДЦА!$E$48=Списки!$H$3,ОЛ_КОЛОДЦА!$E$48=Списки!$H$5),0,IF(H96="",I96,H96))*J94 -> 2 | K96: м² | M96: =IFERROR(IF(L96<>"","",VLOOKUP(C96&D96&K96,НН!A:J,10,)),"") -> 8750 | N96: =IFERROR(IF(L96="",M96*J96,J96*L96),"") -> 17500
C97: Металлопрокат | D97: Труба 45х3,0 ГОСТ 9941-81 ст 12Х18Н10Т (AISI 321) (бесшовная холоднодеформированная) ГОСТ 9941-81 | F97: {=IF(C97="","",IF(OR(C97=Списки!$AG$15:$AG$17),"нет","да"))} -> да | I97: =IF(H97="",ROUNDUP(2*(ОЛ_КОЛОДЦА!E42/1000),),"") -> 4 | J97: =IF(OR(ОЛ_КОЛОДЦА!$E$48=Списки!$H$3,ОЛ_КОЛОДЦА!$E$48=Списки!$H$5),0,IF(H97="",I97,H97))*J94 -> 4 | K97: м | M97: =IFERROR(IF(L97<>"","",VLOOKUP(C97&D97&K97,НН!A:J,10,)),"") -> 3900 | N97: =IFERROR(IF(L97="",M97*J97,J97*L97),"") -> 15600
C98: Металлопрокат | D98: Круг 5 мм 12Х18Н10Т ГOCT 5949-75 | F98: {=IF(C98="","",IF(OR(C98=Списки!$AG$15:$AG$17),"нет","да"))} -> да | I98: =I99*(3.14*0.05) -> 0.471 | J98: =IF(OR(ОЛ_КОЛОДЦА!$E$48=Списки!$H$3,ОЛ_КОЛОДЦА!$E$48=Списки!$H$5),0,IF(H98="",I98,H98))*J94 -> 0.471 | K98: м | M98: =IFERROR(IF(L98<>"","",VLOOKUP(C98&D98&K98,НН!A:J,10,)),"") -> 125 | N98: =IFERROR(IF(L98="",M98*J98,J98*L98),"") -> 58.875
C99: Грузоподъем | D99: Цепь короткозвенная сварная 3 мм DIN 766 А2/А4 | E99: ="Для подъема и спуска корзины L= "&ROUNDUP((ОЛ_КОЛОДЦА!E42/1000+1),0)&" м" -> Для подъема и спуска корзины L= 3 м | F99: {=IF(C99="","",IF(OR(C99=Списки!$AG$15:$AG$17),"нет","да"))} -> да | I99: =IF(H99="",ROUNDUP((ОЛ_КОЛОДЦА!E42/1000+1),),"") -> 3 | J99: =IF(OR(ОЛ_КОЛОДЦА!$E$48=Списки!$H$3,ОЛ_КОЛОДЦА!$E$48=Списки!$H$5),0,IF(H99="",I99,H99))*J94 -> 3 | K99: м | M99: =IFERROR(IF(L99<>"","",VLOOKUP(C99&D99&K99,НН!A:J,10,)),"") -> 180 | N99: =IFERROR(IF(L99="",M99*J99,J99*L99),"") -> 540
C100: Грузоподъем | D100: Карабин винтовой 5 мм нерж. А4 ART 8253 | F100: {=IF(C100="","",IF(OR(C100=Списки!$AG$15:$AG$17),"нет","да"))} -> да | I100: =IF(H100="",ROUNDUP(I99/2,),"") -> 2 | J100: =IF(OR(ОЛ_КОЛОДЦА!$E$48=Списки!$H$3,ОЛ_КОЛОДЦА!$E$48=Списки!$H$5),0,I100)*J94 -> 2 | K100: шт | M100: =IFERROR(IF(L100<>"","",VLOOKUP(C100&D100&K100,НН!A:J,10,)),"") -> 320 | N100: =IFERROR(IF(L100="",M100*J100,J100*L100),"") -> 640
B101: 2.2 | D101: Корзина Работа (ФОТ) | F101: {=IF(ISBLANK(C101),"",IF(OR(C101=Списки!$AG$15:$AG$17),"нет","да"))} | M101: {=IF(D101="ФОТ",I101*#REF!,IFERROR(IF(L101<>"","",IF((VLOOKUP(D101&K101,INDIRECT("'"&INDEX(Списки!$AG$2:$AG$17,MATCH(TRUE,COUNTIF(INDIRECT("'"&Списки!$AG$2:$AG$17 &"'!A1:A300000"),D101&K101)>0,0))&"'!A:h"),7,0))=0,"",VLOOKUP(D101&K101,INDIRECT("'"&INDEX(Списки!$AG$2:$AG$17,MATCH(TRUE,COUNTIF(INDIRECT("'"&Списки!$AG$2:$AG$17 &"'!A1:A300000"),D101&K101)>0,0))&"'!A:h"),7,0))),""))}
C102: Собственное производство | D102: Изготовление Сороудерживающей корзины | F102: {=IF(C102="","",IF(OR(C102=Списки!$AG$15:$AG$17),"нет","да"))} -> нет | I102: =IF(G1<2500,6,7)*J94 -> 6 | J102: =ROUNDUP(IF(OR(ОЛ_КОЛОДЦА!$E$48=Списки!$H$3,ОЛ_КОЛОДЦА!$E$48=Списки!$H$5),0,IF(H102="",I102,H102)),1) -> 6 | K102: чел. ч | M102: =IFERROR(IF(L102<>"","",VLOOKUP(C102&D102&K102,НН!A:J,10,)),"") -> 1207.8 | N102: =IFERROR(IF(L102="",M102*J102,J102*L102),"") -> 7246.8
C103: Собственное производство | D103: Монтаж Сороудерживающей корзины | F103: {=IF(C103="","",IF(OR(C103=Списки!$AG$15:$AG$17),"нет","да"))} -> нет | I103: =IF(G1<2500,5,6)*J94 -> 5 | J103: =ROUNDUP(IF(OR(ОЛ_КОЛОДЦА!$E$48=Списки!$H$3,ОЛ_КОЛОДЦА!$E$48=Списки!$H$5),0,IF(H103="",I103,H103)),1) -> 5 | K103: чел. ч | M103: =IFERROR(IF(L103<>"","",VLOOKUP(C103&D103&K103,НН!A:J,10,)),"") -> 1207.8 | N103: =IFERROR(IF(L103="",M103*J103,J103*L103),"") -> 6039
C104: Собственное производство | D104: Изготовление направляющих корзины | F104: {=IF(C104="","",IF(OR(C104=Списки!$AG$15:$AG$17),"нет","да"))} -> нет | I104: =2*J94 -> 2 | J104: =ROUNDUP(IF(OR(ОЛ_КОЛОДЦА!$E$48=Списки!$H$3,ОЛ_КОЛОДЦА!$E$48=Списки!$H$5),0,IF(H104="",I104,H104)),1) -> 2 | K104: чел. ч | M104: =IFERROR(IF(L104<>"","",VLOOKUP(C104&D104&K104,НН!A:J,10,)),"") -> 1207.8 | N104: =IFERROR(IF(L104="",M104*J104,J104*L104),"") -> 2415.6 | O104: обычно у корзины 2 направляющие, за 2 шт. - 2 чел.ч.
...

Sheet ОЛ_ЕМКОСТИ
B1: ОБЩЕСТВО С ОГРАНИЧЕННОЙ ОТВЕТСТВЕННОСТЬЮ «НОВЫЕ ТРУБНЫЕ ТЕХНОЛОГИИ» 141320, Московская область, г.о. Сергиево-Посадский, д. Коврово, д. 50, помещ. 2 E-mail: info@ntt.su, тел/факс: +7(499) 949-14-04
C4: ОПРОСНЫЙ ЛИСТ ЕМКОСТИ
C6: *к заявке ООО «НТТ» № | E6: ОЛ/
C7: Тип емкости
C8: Назначение ОЛ* | D8: → | E8: Материальный расчет
C9: *(выберите одно или несколько назначений) | D9: →
D10: →
D11: →
C12: *Дата заполнения:
C13: *Заказчик:
C14: Стадия проекта: | E14: проект
C15: Объект:
C16: Регион объекта:
C18: Предполагаемый размер емкости*: | E18: Ручной ввод | F18: Расчет
C19: *Объем, м3 | E19: 100 | F19: =IF(E19="",VLOOKUP(ОЛ_ЕМКОСТИ!$E$24&ОЛ_ЕМКОСТИ!$E$25&ОЛ_ЕМКОСТИ!$E$39,'для шапки'!$B$2:$I$9,8,),"")
C20: *Диаметр DN, мм | E20: 3000
C21: *Давление PN, Мпа | D21: ВАЖНО от выбранного давления зависит масса формованных слоев на стыке (кг) | E21: 0.1
C22: *Жесткость SN, Па | E22: 10000
C23: Производство | D23: =IF(C23="Производство","Общий метраж выпуска →","Номер заказа →") -> Общий метраж выпуска →
C24: Расположение | E24: Горизонтальное | I24: =E24&E25 -> ГоризонтальноеПодземная
C25: Установка | E25: Подземная
C26: Высота возвышения корпуса емкости/шахты обслуживания над землей, мм | E26: 300
C27: Установка под проезжей частью (Да/Нет): | E27: Нет
C28: Длина рабочей части емкости при горизонтальном расположении, мм | F28: =IF(E28="",VLOOKUP(ОЛ_ЕМКОСТИ!$E$24&ОЛ_ЕМКОСТИ!$E$25&ОЛ_ЕМКОСТИ!$E$39,'для шапки'!$B$2:$I$9,2,),"") -> 13400
C29: Длина рабочей части емкости при вертикальном расположении, мм | E29: 4000 | F29: =IF(E29="",VLOOKUP(ОЛ_ЕМКОСТИ!$E$24&ОЛ_ЕМКОСТИ!$E$25&ОЛ_ЕМКОСТИ!$E$39,'для шапки'!$B$2:$L$9,11,),"")
C31: Смола:
C33: Тип смолы | E33: Стандарт
C34: Марка смолы | E34: =VLOOKUP(E33,Списки!$BH$1:$BI$4,2,) -> ИЗО
C35: MAX температура жидкости, оС
C36: Вид стоков | E36: Производственные
C37: Возможное MAX внутреннее давление, кг/см2
C39: Наличие шахты обслуживания | E39: Да
C40: Диаметр шахты d,мм | E40: 1200
C41: Высота шахты h (до верха рабочей части емкости), мм | E41: 2000
C43: Лестница | E43: Да
C45: Параметры патрубков:
C47: подводящего: | G47: отводящего:
C48: Материал патрубка | E48: ПЭ | G48: Материал патрубка | I48: ПЭ
C49: *Номинальный диаметр патрубка DN, мм | E49: 400 | G49: *Номинальный диаметр патрубка DN, мм | I49: 300
C50: Кол-во патрубков | E50: 1 | G50: Кол-во патрубков | I50: 2
C51: *Глубина залегания H лотка (от уровня грунта до низа лотка патрубка), мм | E51: 2400 | G51: *Глубина залегания H лотка (от уровня грунта до низа лотка патрубка), мм | I51: 2600
C54: Наличие насосного оборудования: | E54: Да
M55: Vэф= | N55: =(E56)/(4*P55*E60) -> 2.5 | O55: м3 | P55: 5 | Q55: 10 | R55: 20 | S55: пусков в час
C56: *Максимальный приток сточных вод | D56: =IF(F56=[3]Списки!$U$2,CONCATENATE("(",ROUND(E56/1000*3600,2)," м3/ч)"),IF(F56=[3]Списки!$U$3,"",CONCATENATE("(",ROUND(E56/24,2)," м3/ч)"))) | E56: 50 | F56: м3/ч | G56: <- выберите ЕИ | M56: Vмин= | N56: =(E56/2)*P56/60 -> 2.0833333 | O56: м3 | P56: 5 | Q56: 10 | R56: 20 | S56: поминутная работа
C57: *Расчетный напор на выходе, м | E57: 10 | M57: Vраб= | N57: =N56 -> 2.0833333 | O57: м3
C58: Марка насосов:
C59: *Количество насосов: | M59: hраб= | N59: =4*N57/(PI()*POWER(E20/1000,2)) -> 0.29473138 | O59: м
D60: - рабочих | E60: 1 | M60: hР= | N60: =N59+0.3+N65+N62 -> 1.3547314 | O60: м | P60: с учетом поплавков и рамы насосов
D61: - резервных | E61: 1 | M61: Нподз | N61: =E56/1000+N60 -> 1.4047314 | O61: мм | P61: =ROUNDUP(N61*1000,-2) -> 1500
D62: - запасных на склад | M62: Минимальный уровень жидкости для работы насоса (из тех. паспорта подобранного насоса вводится вручную) | N62: 0.6 | O62: м
C63: Взрывозащита насосов: | E63: Нет | M63: Мин. уровень жидкости в КНС (уровень 1 поплавка от дна КНС) | N63: =N62+N65 -> 0.76 | O63: м
M64: Высота подъема на выходе из КНС (геометр. Подъем) | N64: =P61/1000-N62-N65-I56/1000 -> 0.74 | O64: м
C65: Наличие дополнительного оборудования: | E65: Да | M65: Высота рамы насосов | N65: 0.16 | O65: м
C67: Наличие дробилки/корзины для мусора | E67: Корзина для мусора
C68: Наличие запорной арматуры на подводящем трубопроводе | E68: Да
E69: Задвижка шиберная
C71: Шкаф управления | E71: Да | G71: Датчики: | I71: Да
C72: Тип: | E72: Уличный | G72: давления | I72: Да
C73: Марка шкафа: | G73: температуры | I73: Нет
C74: Ввод электропитания: | E74: Один | G74: уровня | I74: Нет
C75: Пуск ШУ: | E75: Стандартный | G75: манометр | I75: Нет
C76: Модуль передачи данных в систему диспетчеризации: | E76: CIM 250 GSM/GPRS | G76: расходомер | I76: Нет
C78: Вентиляция | E78: Приточная
C80: *Теплоизоляция | E80: Да
C81: Глубина теплоизоляции, мм | E81: 2000
C83: Обязательные дополнения к заявке:
C85: * - поля обязательные для заполнения
C87: Приложение: документы заказчика на
C90: Менеджер отдела продаж емкостного оборудования ООО «НТТ» | F90: ______________________________ (________________________)
C92: Начальник отдела продаж емкостного оборудования ООО «НТТ» | F92: ______________________________ (________________________)

Sheet Калькулятор ЕМК
C1: Материальный расчет | M1: к содержанию
C3: Дата заполнения таблицы | D3: Заказчик/ Объект/ Вид емкости/ Параметры | G3: DN трубы, мм | H3: Габаритная длина рабочей части емкости, L мм | I3: =IF(ОЛ_ЕМКОСТИ!E24="горизонтальное",IF(ОЛ_ЕМКОСТИ!E39="да","Длина трубы для емкости при горизонтальном расположении с шахтой обслуживания, мм","Длина трубы для емкости при горизонтальном расположении без шахты обслуживания, мм"),IF(ОЛ_ЕМКОСТИ!E39="да","Длина трубы для емкости при вертикальном расположении с шахтой обслуживания, мм","Длина трубы для емкости при вертикальном расположении без шахты обслуживания, мм")) -> Длина трубы для емкости при горизонтальном расположении с шахтой обслуживания, мм | J3: Высота возвышения корпуса емкости/шахты обслуживания над землей, мм | K3: Объем емкости, м3 | L3: Объем 2х элиптических днищ для горизонтальной установки, м3 | M3: Количество одинаковых линий
H4: =IF(H5<3000,3000,IF(AND(H5>7000),12000,CEILING(H5,500))) -> 12000 | I4: =IF(I5<3000,3000,IF(AND(I5>7000),12000,CEILING(I5,500))) -> 12000
D5: ="Заявка № "&ОЛ_ЕМКОСТИ!E6&" Заказчик: "&ОЛ_ЕМКОСТИ!E13&" "&ОЛ_ЕМКОСТИ!E15&" "&ОЛ_ЕМКОСТИ!E7&" емкость "&G5&"х"&H5&"мм" -> Заявка № ОЛ/ Заказчик: емкость 3000х13400мм | G5: =ОЛ_ЕМКОСТИ!E20 -> 3000 | H5: =INDEX('для шапки'!$C$2:$K$11,MATCH(ОЛ_ЕМКОСТИ!$E$24&ОЛ_ЕМКОСТИ!$E$25&ОЛ_ЕМКОСТИ!$E$39,'для шапки'!$B$2:$B$11,),MATCH('Калькулятор ЕМК'!H3,'для шапки'!$C$1:$K$1,)) -> 13400 | I5: =INDEX('для шапки'!$C$2:$K$11,MATCH(ОЛ_ЕМКОСТИ!$E$24&ОЛ_ЕМКОСТИ!$E$25&ОЛ_ЕМКОСТИ!$E$39,'для шапки'!$B$2:$B$11,),MATCH('Калькулятор ЕМК'!I3,'для шапки'!$C$1:$K$1,)) -> 13400 | J5: =INDEX('для шапки'!$C$2:$K$11,MATCH(ОЛ_ЕМКОСТИ!$E$24&ОЛ_ЕМКОСТИ!$E$25&ОЛ_ЕМКОСТИ!$E$39,'для шапки'!$B$2:$B$11,),MATCH('Калькулятор ЕМК'!J3,'для шапки'!$C$1:$K$1,)) -> 300 | K5: =INDEX('для шапки'!$C$2:$K$11,MATCH(ОЛ_ЕМКОСТИ!$E$24&ОЛ_ЕМКОСТИ!$E$25&ОЛ_ЕМКОСТИ!$E$39,'для шапки'!$B$2:$B$11,),MATCH('Калькулятор ЕМК'!K3,'для шапки'!$C$1:$K$1,)) -> 100 | L5: =(PI()*((G5/1000)^3))/15 -> 5.6548668 | M5: 1
C6: Наименование изделия | D6: Материал изделия | E6: Транспортируемая среда | F6: Давление трубопровода, PN МПа | H6: Жесткость, SN Па | K6: D шахты обслуживания, мм | L6: Количество шахт, шт. | M6: Высота шахты h (до верха рабочей части емкости), мм | N6: Кол-во емкостей
F7: =IF(AND('Калькулятор ЕМК'!G8>0.6,OR(CONCATENATE('Калькулятор ЕМК'!G5,'Калькулятор ЕМК'!H8)=CONCATENATE('Вес трубы, ПЭ трубы'!B51,'Вес трубы, ПЭ трубы'!C51),CONCATENATE('Калькулятор ЕМК'!G5,'Калькулятор ЕМК'!H8)=CONCATENATE('Вес трубы, ПЭ трубы'!B55,'Вес трубы, ПЭ трубы'!C55),CONCATENATE('Калькулятор ЕМК'!G5,'Калькулятор ЕМК'!H8)=CONCATENATE('Вес трубы, ПЭ трубы'!B57,'Вес трубы, ПЭ трубы'!C57))),1.6,IF(AND(G5=1300,OR(H8=5000,H8=10000),'Калькулятор ЕМК'!G8<=0.4),0.4,IF(G8<=0.6,0.6,1))) -> 0.6 | G7: =IF(G8<=0.6,0.6,1) -> 0.6 | J7: +100 | K7: Вручную | L7: +100 | M7: =IF(M8*1000<3000,3000,IF(AND(M8*1000>7000,M8*1000<12000),12000,CEILING(M8*1000,500))) -> 2000000
C8: Труба | D8: =IF(ОЛ_ЕМКОСТИ!$E$7=Списки!$AO$3,"СК/ВЭС","СК/НПС") -> СК/НПС | E8: К | G8: =ОЛ_ЕМКОСТИ!E21 -> 0.1 | H8: =ОЛ_ЕМКОСТИ!E22 -> 10000 | K8: =IF(ОЛ_ЕМКОСТИ!E39="нет","0",ОЛ_ЕМКОСТИ!E40) -> 1200 | L8: 2 | M8: =IF(ОЛ_ЕМКОСТИ!E39="нет","0",ОЛ_ЕМКОСТИ!E41) -> 2000 | N8: 1
B9: № | C9: Категория | D9: Материалы,работы, услуги. | F9: Закупка | G9: Вес, кг/пм | H9: Кол-во за 1 ед. | J9: Общ. кол-во | K9: ЕИ | L9: Цена за 1 ед., руб | N9: Сумма, руб | O9: Примечание | P9: МТО | Q9: Логистика
B11: 1 | D11: =CONCATENATE("Корпус емкости"," ",G5,"х",H5,"мм"," ",", в т.ч.:") -> Корпус емкости 3000х13400мм , в т.ч.:
B12: 1.1 | D12: Корпус емкости. Материалы
C13: Собственное производство | D13: =IF(C8="","",CONCATENATE(C8," ",D8,"-",E8," ",G5,"-",G8,"-",H8)) -> Труба СК/НПС-К 3000-0,1-10000 | E13: Целая труба | F13: =IF(E13=Списки!AI3,"Справочно","") | G13: =IFERROR(I13*INDEX('Вес трубы, ПЭ трубы'!E:G,MATCH(CONCATENATE(G5&";"&F7&";"&H8),'Вес трубы, ПЭ трубы'!E:E,),3),"") -> 14455.98 | I13: =IF(C24="Старый способ",I5/1000*M5,((I5/1000+1.5)*M5)) -> 14.9 | J13: =IF(H13="",I13,H13) -> 14.9 | K13: м | L13: 1 | M13: =IFERROR(IF(L13<>"","",VLOOKUP(C13&D13&K13,НН!A:J,10,)),"") | N13: =IFERROR(IF(L13="",M13*J13,J13*L13),"") -> 14.9
C14: Собственное производство | D14: Придание изделию товарного вида | F14: {=IF(C14="","",IF(OR(C14=Списки!$AG$15:$AG$17),"нет","да"))} -> нет | I14: =$G$5/1300*J13 -> 34.384615 | J14: =ROUNDUP(IF($E$13=Списки!$AI$2,IF(H14="",I14,H14),0),1) -> 34.4 | K14: чел. ч | M14: =IFERROR(IF(L14<>"","",VLOOKUP(C14&D14&K14,НН!A:J,10,)),"") -> 1207.8 | N14: =IFERROR(IF(L14="",M14*J14,J14*L14),"") -> 41548.32
C15: Собственное производство | D15: =IF(C8="","",CONCATENATE(C8," ",D8,"-",E8," ",G5,"-",G8,"-",H8)) -> Труба СК/НПС-К 3000-0,1-10000 | F15: нет | G15: =IFERROR(I15*INDEX('Вес трубы, ПЭ трубы'!E:G,MATCH(CONCATENATE(#REF!&";"&F7&";"&#REF!),'Вес трубы, ПЭ трубы'!E:E,),3),"") | H15: 4.34 | J15: =IF(ОЛ_ЕМКОСТИ!$E$24=Списки!$AK$2,0,IF($E$13=Списки!$AI$2,0,IF(H15="",I15,H15))) -> 0 | K15: м | M15: =IFERROR(IF(L15<>"","",VLOOKUP(C15&D15&K15,НН!A:J,10,)),"") | N15: =IFERROR(IF(L15="",SUM(#REF!),J15*L15),0) -> 0
C16: Собственное производство | D16: Придание изделию товарного вида | F16: {=IF(C16="","",IF(OR(C16=Списки!$AG$15:$AG$17),"нет","да"))} -> нет | I16: =$G$5/1300*J15 -> 0 | J16: =ROUNDUP(IF(H16="",I16,H16),1) -> 0 | K16: чел. ч | M16: =IFERROR(IF(L16<>"","",VLOOKUP(C16&D16&K16,НН!A:J,10,)),"") -> 1207.8 | N16: =IFERROR(IF(L16="",M16*J16,J16*L16),"") -> 0
C17: Собственное производство | D17: =IF(C8="","",CONCATENATE(C8," ",D8,"-",E8," ",G5,"-",G8,"-",H8)) -> Труба СК/НПС-К 3000-0,1-10000 | F17: нет | H17: 4 | J17: =IF(ОЛ_ЕМКОСТИ!$E$24=Списки!$AK$2,0,IF($E$13=Списки!$AI$2,0,IF(H17="",I17,H17))) -> 0 | K17: м | M17: =IFERROR(IF(L17<>"","",VLOOKUP(C17&D17&K17,НН!A:J,10,)),"") | N17: =IFERROR(IF(L17="",SUM(#REF!),J17*L17),0) -> 0
C18: Собственное производство | D18: Придание изделию товарного вида | F18: {=IF(C18="","",IF(OR(C18=Списки!$AG$15:$AG$17),"нет","да"))} -> нет | I18: =$G$5/1300*J17 -> 0 | J18: =ROUNDUP(IF(H18="",I18,H18),1) -> 0 | K18: чел. ч | M18: =IFERROR(IF(L18<>"","",VLOOKUP(C18&D18&K18,НН!A:J,10,)),"") -> 1207.8 | N18: =IFERROR(IF(L18="",M18*J18,J18*L18),"") -> 0
C19: Собственное производство | D19: =IF(C8="","",CONCATENATE("Муфта-1 ",D8,"-",E8," ",G5,"-",1)) -> Муфта-1 СК/НПС-К 3000-1 | F19: нет | H19: 1 | J19: =IF(ОЛ_ЕМКОСТИ!$E$24=Списки!$AK$2,0,IF($E$13=Списки!$AI$2,0,IF(H19="",I19,H19))) -> 0 | K19: шт | M19: =IFERROR(IF(L19<>"","",VLOOKUP(C19&D19&K19,НН!A:J,10,)),"") | N19: =IFERROR(IF(L19="",M19*J19,J19*L19),0) -> 0
C20: Собственное производство | D20: Ламинирование стыков частей трубы | F20: нет | J20: =IF(ОЛ_ЕМКОСТИ!$E$24=Списки!$AK$2,0,IF($E$13=Списки!$AI$2,0,IF(H20="",I20,H20))) -> 0 | K20: кг | M20: =IFERROR(IF(L20<>"","",VLOOKUP(C20&D20&K20,НН!A:J,10,)),"") | N20: =IFERROR(IF(L20="",M20*J20,J20*L20),0) -> 0
C21: ФОТ | D21: ФОТ | F21: нет | H21: 0.56 | J21: =IF(ОЛ_ЕМКОСТИ!$E$24=Списки!$AK$2,0,IF($E$13=Списки!$AI$2,0,IF(H21="",I21,H21))) -> 0 | K21: чел. ч | M21: =IFERROR(IF(L21<>"","",VLOOKUP(C21&D21&K21,НН!A:J,10,)),"") -> 1207.8 | N21: =IFERROR(IF(L21="",M21*J21,J21*L21),0) -> 0
G22: Транспортировочная длина трубы (отрезок): | H22: 6 | K22: м
C23: Собственное производство | D23: ="Муфта соединительная Муфта-1 "&G5&"-1" -> Муфта соединительная Муфта-1 3000-1 | F23: {=IF(C23="","",IF(OR(C23=Списки!$AG$15:$AG$17),"нет","да"))} -> нет | I23: =ROUNDDOWN((I5/1000-1.5)/H22,0) -> 1 | J23: =IF(ОЛ_ЕМКОСТИ!$E$24=Списки!AK3,0,IF(H23="",I23,H23)*M5) -> 1 | K23: шт | L23: 1 | M23: =IFERROR(IF(L23<>"","",VLOOKUP(C23&D23&K23,НН!A:J,10,)),"") | N23: =IFERROR(IF(L23="",M23*J23,J23*L23),"") -> 1
C24: Новый способ | E24: ВАЖНО от выбранного давления зависит масса формованных слоев на стыке (кг)
C25: Собственное производство | D25: =IF(C24="новый способ","Ламинация днища (косые и центральный стыки)",IF(ОЛ_ЕМКОСТИ!$E$24="горизонтальное","Механическая формовка эллиптических днищ",IF($C$72="да","Механическое формованное дно", "Механическая формовка плоского днища"))) -> Ламинация днища (косые и центральный стыки) | F25: {=IF(C25="","",IF(OR(C25=Списки!$AG$15:$AG$17),"нет","да"))} -> нет | I25: =((VLOOKUP(G5,'Для расчетов'!J36:S143,9,0))/0.707+(VLOOKUP(G5,'Для расчетов'!J36:S143,9,0))/2)*2 -> 428.83168 | J25: =IF(H25="",I25,H25)*M5 -> 428.83168 | K25: кг | M25: =IFERROR(IF(L25<>"","",VLOOKUP(C25&D25&K25,НН!A:J,10,)),"") -> 214.4 | N25: =IFERROR(IF(L25="",M25*J25,J25*L25),"") -> 91941.513
C26: ФОТ | D26: ФОТ | F26: {=IF(C26="","",IF(OR(C26=Списки!$AG$15:$AG$17),"нет","да"))} -> нет | I26: =IF(C24="старый способо",IF(COUNTIF(D25,"*мех*")=1,0.28,IF(COUNTIF(D25,"*ламин*")=1,0.56,1)),IF(COUNTIF(D25,"*мех*")=1,0.28,IF(COUNTIF(D25,"*ламин*")=1,0.56,1))) -> 0.56 | J26: =ROUNDUP(IF(H26="",IFERROR(J25*I26,""),H26),1) -> 240.2 | K26: чел. ч | M26: =IFERROR(IF(L26<>"","",VLOOKUP(C26&D26&K26,НН!A:J,10,)),"") -> 1207.8 | N26: =IFERROR(IF(L26="",M26*J26,J26*L26),"") -> 290113.56
C27: Собственное производство | D27: =IF(ОЛ_ЕМКОСТИ!E24=Списки!AK2,"Ламинирование эллиптического днища к корпусу",IF($C$72="да","Ламинирование дна к фальшполу","Ламинирование плоского днища к корпусу")) -> Ламинирование эллиптического днища к корпусу | F27: {=IF(C27="","",IF(OR(C27=Списки!$AG$15:$AG$17),"нет","да"))} -> нет | I27: =IF(H27="",IFERROR(IF(H25="",J25,H25)*3/10,""),"") -> 128.6495 | J27: =IFERROR(IF(C24="новый способ",0,),"0") -> 0 | K27: кг | M27: =IFERROR(IF(L27<>"","",VLOOKUP(C27&D27&K27,НН!A:J,10,)),"") -> 310.2 | N27: =IFERROR(IF(L27="",M27*J27,J27*L27),"") -> 0 | O27: расчет при новом способе: =(Мф/0,707 + Мф/2)*М5
C28: ФОТ | D28: ФОТ | F28: {=IF(C28="","",IF(OR(C28=Списки!$AG$15:$AG$17),"нет","да"))} -> нет | I28: =IF(COUNTIF(D27,"*мех*")=1,0.28,IF(COUNTIF(D27,"*ламин*")=1,0.56,1)) -> 0.56 | J28: =ROUNDUP(IFERROR(IF(H28="",J27*I28,H28),""),1) -> 0 | K28: чел. ч | M28: =IFERROR(IF(L28<>"","",VLOOKUP(C28&D28&K28,НН!A:J,10,)),"") -> 1207.8 | N28: =IFERROR(IF(L28="",M28*J28,J28*L28),"") -> 0 | O28: расчет при старом способе:
C30: Нет | D30: Перегородка
C31: Собственное производство | D31: Ручная формовка перегородки | E31: 1 | F31: {=IF(ISBLANK(C31),"",IF(OR(C31=Списки!$AG$15:$AG$17),"нет","да"))} -> нет | I31: 20 | J31: =IF(C30="нет",0,IF(I31="",I31,I31))*E31 -> 0 | K31: кг | M31: =IFERROR(IF(L31<>"","",VLOOKUP(C31&D31&K31,НН!A:J,10,)),"") -> 310.2 | N31: =IFERROR(IF(L31="",M31*J31,J31*L31),"") -> 0
C32: ФОТ | D32: ФОТ | F32: {=IF(ISBLANK(C32),"",IF(OR(C32=Списки!$AG$15:$AG$17),"нет","да"))} -> нет | I32: 1 | J32: =ROUNDUP(IF(H32="",J31*I32,H32),1) -> 0 | K32: чел. ч | M32: =IFERROR(IF(L32<>"","",VLOOKUP(C32&D32&K32,НН!A:J,10,)),"") -> 1207.8 | N32: =IFERROR(IF(L32="",M32*J32,J32*L32),"") -> 0
C33: Собственное производство | D33: Ламинирование перегородки к корпусу | F33: {=IF(ISBLANK(C33),"",IF(OR(C33=Списки!$AG$15:$AG$17),"нет","да"))} -> нет | I33: 1 | J33: =1*J31*3/10 -> 0 | K33: кг | M33: =IFERROR(IF(L33<>"","",VLOOKUP(C33&D33&K33,НН!A:J,10,)),"") -> 310.2 | N33: =IFERROR(IF(L33="",M33*J33,J33*L33),"") -> 0
C34: ФОТ | D34: ФОТ | F34: {=IF(ISBLANK(C34),"",IF(OR(C34=Списки!$AG$15:$AG$17),"нет","да"))} -> нет | I34: 1 | J34: =ROUNDUP(IF(H34="",J33*I34,H34),1) -> 0 | K34: чел. ч | M34: =IFERROR(IF(L34<>"","",VLOOKUP(C34&D34&K34,НН!A:J,10,)),"") -> 1207.8 | N34: =IFERROR(IF(L34="",M34*J34,J34*L34),"") -> 0
D36: Входящий патрубок | E36: =ОЛ_ЕМКОСТИ!E49 -> 400 | F36: =ОЛ_ЕМКОСТИ!E50 -> 1 | G36: шт | H36: ПЭ
C37: Собственное производство | D37: =IF(E36>=200,"Труба СК/НПС-К "&E36+100&"-0,1-2500","Ручная формовка патрубка") -> Труба СК/НПС-К 500-0,1-2500 | E37: =IF(H36="Труба стеклокомпозитная","Муфта-2 СК/НПС-К "&E36+100&"-1","Стеклокомпозитная гильза Ø"&E36+100) -> Стеклокомпозитная гильза Ø500 | F37: {=IF(C37="","",IF(OR(C37=Списки!$AG$15:$AG$17),"нет","да"))} -> нет | J37: =IFERROR(IF(SEARCH("*гильза*",E37)=1,0.5*F36),VLOOKUP(E36+100,'Для расчетов'!$A$36:$F$60,4,)*F36) -> 0.5 | K37: =IFERROR(IF(SEARCH("*труба*",D37)=1,"м"),"кг") -> м | L37: =IFERROR(IF(SEARCH("м",K37)=1,"1,00"),"") -> 1,00 | M37: =IFERROR(IF(L37<>"","",VLOOKUP(C37&D37&K37,НН!A:J,10,)),"") | N37: =IFERROR(IF(L37="",M37*J37,J37*L37),0) -> 0.5
C38: Собственное производство | D38: Придание изделию товарного вида | F38: {=IF(C38="","",IF(OR(C38=Списки!$AG$15:$AG$17),"нет","да"))} -> нет | I38: =($E$36+100)/1300*J37 -> 0.19230769 | J38: =IF(COUNTIF(D37,"*труба*")=1,(E36+100)/1300*J37,0) -> 0.19230769 | K38: чел. ч | M38: =IFERROR(IF(L38<>"","",VLOOKUP(C38&D38&K38,НН!A:J,10,)),"") -> 1207.8 | N38: =IFERROR(IF(L38="",M38*J38,J38*L38),"") -> 232.26923
C39: Собственное производство | D39: Ламинирование патрубка к корпусу | F39: {=IF(C39="","",IF(OR(C39=Списки!$AG$15:$AG$17),"нет","да"))} -> нет | J39: =(VLOOKUP(E36+100,'Для расчетов'!A36:D62,4,0)*3/10)*F36 -> 0.57 | K39: кг | M39: =IFERROR(IF(L39<>"","",VLOOKUP(C39&D39&K39,НН!A:J,10,)),"") -> 310.2 | N39: =IFERROR(IF(L39="",M39*J39,J39*L39),"") -> 176.814
C40: ФОТ | D40: ФОТ | F40: {=IF(C40="","",IF(OR(C40=Списки!$AG$15:$AG$17),"нет","да"))} -> нет | I40: =IF(COUNTIF(D39,"*мех*")=1,0.28,IF(COUNTIF(D39,"*ламин*")=1,1)) -> 1 | J40: =ROUNDUP(IF(OR(ОЛ_КОЛОДЦА!$E$43="",ОЛ_КОЛОДЦА!$E$45=""),0,IF(H40="",IFERROR(J39*I40,""),H40)),1) -> 0.6 | K40: чел. ч | M40: =IFERROR(IF(L40<>"","",VLOOKUP(C40&D40&K40,НН!A:J,10,)),"") -> 1207.8 | N40: =IFERROR(IF(L40="",M40*J40,J40*L40),"") -> 724.68
D42: Выходящий патрубок | E42: =ОЛ_ЕМКОСТИ!I49 -> 300 | F42: =ОЛ_ЕМКОСТИ!I50 -> 2 | G42: шт | H42: ПЭ
C43: Собственное производство | D43: =IF(E42>=200,"Труба СК/НПС-К "&E42+100&"-0,1-2500","Ручная формовка патрубка") -> Труба СК/НПС-К 400-0,1-2500 | E43: =IF(H42="Труба стеклокомпозитная","Муфта-2 СК/НПС-К "&E42+100&"-1","Стеклокомпозитная гильза Ø"&E42+100) -> Стеклокомпозитная гильза Ø400 | F43: {=IF(C43="","",IF(OR(C43=Списки!$AG$15:$AG$17),"нет","да"))} -> нет | J43: =IFERROR(IF(SEARCH("*гильза*",E43)=1,0.5*F42),VLOOKUP(E42+100,'Для расчетов'!$A$36:$F$60,4,)*F42) -> 1 | K43: =IFERROR(IF(SEARCH("*труба*",D43)=1,"м"),"кг") -> м | L43: =IFERROR(IF(SEARCH("м",K43)=1,"1,00"),"") -> 1,00 | M43: =IFERROR(IF(L43<>"","",VLOOKUP(C43&D43&K43,НН!A:J,10,)),"") | N43: =IFERROR(IF(L43="",M43*J43,J43*L43),0) -> 1
C44: Собственное производство | D44: Придание изделию товарного вида | F44: {=IF(C44="","",IF(OR(C44=Списки!$AG$15:$AG$17),"нет","да"))} -> нет | I44: =($E$42+100)/1300*J43 -> 0.30769231 | J44: =IF(COUNTIF(D43,"*труба*")=1,(E42+100)/1300*J43,0) -> 0.30769231 | K44: чел. ч | M44: =IFERROR(IF(L44<>"","",VLOOKUP(C44&D44&K44,НН!A:J,10,)),"") -> 1207.8 | N44: =IFERROR(IF(L44="",M44*J44,J44*L44),"") -> 371.63077
C45: Собственное производство | D45: Ламинирование патрубка к корпусу | F45: {=IF(C45="","",IF(OR(C45=Списки!$AG$15:$AG$17),"нет","да"))} -> нет | J45: =(VLOOKUP(E42+100,'Для расчетов'!A42:D68,4,0)*3/10)*F42 -> 0.66 | K45: кг | M45: =IFERROR(IF(L45<>"","",VLOOKUP(C45&D45&K45,НН!A:J,10,)),"") -> 310.2 | N45: =IFERROR(IF(L45="",M45*J45,J45*L45),"") -> 204.732
C46: ФОТ | D46: ФОТ | F46: {=IF(C46="","",IF(OR(C46=Списки!$AG$15:$AG$17),"нет","да"))} -> нет | I46: =IF(COUNTIF(D45,"*мех*")=1,0.28,IF(COUNTIF(D45,"*ламин*")=1,1)) -> 1 | J46: =ROUNDUP(IF(OR(ОЛ_КОЛОДЦА!$E$43="",ОЛ_КОЛОДЦА!$E$45=""),0,IF(H46="",IFERROR(J45*I46,""),H46)),1) -> 0.7 | K46: чел. ч | M46: =IFERROR(IF(L46<>"","",VLOOKUP(C46&D46&K46,НН!A:J,10,)),"") -> 1207.8 | N46: =IFERROR(IF(L46="",M46*J46,J46*L46),"") -> 845.46
D48: Теплоизоляция: | M48: {=IF(D48="ФОТ",I48*#REF!,IFERROR(IF(L48<>"","",IF((VLOOKUP(D48&K48,INDIRECT("'"&INDEX(Списки!$AG$2:$AG$17,MATCH(TRUE,COUNTIF(INDIRECT("'"&Списки!$AG$2:$AG$17 &"'!A1:A3000000"),D48&K48)>0,0))&"'!A:h"),7,0))=0,"",VLOOKUP(D48&K48,INDIRECT("'"&INDEX(Списки!$AG$2:$AG$17,MATCH(TRUE,COUNTIF(INDIRECT("'"&Списки!$AG$2:$AG$17 &"'!A1:A3000000"),D48&K48)>0,0))&"'!A:h"),7,0))),""))} | N48: =IFERROR(IF(L48="",M48*J48,J48*L48),"")
C49: Прочие материалы | D49: Теплоизоляция - Изофом ППЭ ОР 15 1,5х40 | E49: Вертикальная изоляция корпуса | F49: {=IF(C49="","",IF(ОЛ_ЕМКОСТИ!$E$80="нет","-",IF(OR(C49=Списки!$AG$15:$AG$17),"нет","да")))} -> да | I49: =(PI()*($F$54/(1000*2))*ОЛ_ЕМКОСТИ!$E$81/1000)*F53 -> 7.5398224 | J49: =IF(ОЛ_ЕМКОСТИ!$E$80="нет",0,IF(ISBLANK(D49),"",IF(H49="",I49,H49))) -> 7.5398224 | K49: м² | M49: =IFERROR(IF(L49<>"","",VLOOKUP(C49&D49&K49,НН!A:J,10,)),"") -> 750 | N49: =IFERROR(IF(L49="",M49*J49,J49*L49),"") -> 5654.8668
C50: Прочие материалы | D50: Теплоизоляция - Изофом ППЭ ОР 15 1,5х40 | E50: Изоляция крышки | F50: {=IF(C50="","",IF(ОЛ_ЕМКОСТИ!$E$80="нет","-",IF(OR(C50=Списки!$AG$15:$AG$17),"нет","да")))} -> да | I50: =PI()*($G$5/(1000*2))^2 -> 7.0685835 | J50: =IF(ОЛ_ЕМКОСТИ!$E$80="нет",0,IF(ISBLANK(D50),"",IF(H50="",I50,H50))) -> 7.0685835 | K50: м² | M50: =IFERROR(IF(L50<>"","",VLOOKUP(C50&D50&K50,НН!A:J,10,)),"") -> 750 | N50: =IFERROR(IF(L50="",M50*J50,J50*L50),"") -> 5301.4376
C51: Собственное производство | D51: Защитный слой ламинации 4 мм на теплоизоляцию | F51: {=IF(C51="","",IF(ОЛ_ЕМКОСТИ!$E$80="нет","-",IF(OR(C51=Списки!$AG$15:$AG$17),"нет","да")))} -> нет | I51: =(I49+I50)*0.004*1850 -> 108.1022 | J51: =IF(ОЛ_ЕМКОСТИ!$E$80="нет",0,IF(ISBLANK(D51),"",IF(H51="",I51,H51))) -> 108.1022 | K51: кг | M51: =IFERROR(IF(L51<>"","",VLOOKUP(C51&D51&K51,НН!A:J,10,)),"") -> 310.2 | N51: =IFERROR(IF(L51="",M51*J51,J51*L51),"") -> 33533.303
C52: ФОТ | D52: ФОТ | F52: {=IF(C52="","",IF(ОЛ_ЕМКОСТИ!$E$80="нет","-",IF(OR(C52=Списки!$AG$15:$AG$17),"нет","да")))} -> нет | I52: =IF(COUNTIF(D51,"*мех*")=1,0.28,IF(COUNTIF(D51,"*ламин*")=1,0.56,1)) -> 0.56 | J52: =ROUNDUP(IF(H52="",IFERROR(J51*I52,""),H52),1) -> 60.6 | K52: чел. ч | M52: =IFERROR(IF(L52<>"","",VLOOKUP(C52&D52&K52,НН!A:J,10,)),"") -> 1207.8 | N52: =IFERROR(IF(L52="",M52*J52,J52*L52),"") -> 73192.68
C53: =ОЛ_ЕМКОСТИ!E39 -> Да | D53: Шахта обслуживания: | F53: =L8 -> 2 | G53: шт
E54: DN | F54: =K8 -> 1200 | G54: SN | H54: 5000 | I54: PN | J54: 0.1
C55: Собственное производство | D55: ="Труба СК/НПС-К "&F54&"-"&J54&"-"&H54 -> Труба СК/НПС-К 1200-0,1-5000 | E55: Заготовка трубы для шахты обслуживания | F55: {=IF(ISBLANK(C55),"",IF(OR(C55=Списки!$AG$15:$AG$17),"нет","да"))} -> нет | I55: =M8/1000 -> 2 | J55: =IF(C53="нет",0,IF(ОЛ_ЕМКОСТИ!E40="",0,IF(H55="",I55,H55)*F53)) -> 4 | K55: м | L55: 1 | M55: =IFERROR(IF(L55<>"","",VLOOKUP(C55&D55&K55,НН!A:J,10,)),"") | N55: =IFERROR(IF(L55="",M55*J55,J55*L55),"") -> 4
C56: Собственное производство | D56: Придание изделию товарного вида | F56: {=IF(C56="","",IF(OR(C56=Списки!$AG$15:$AG$17),"нет","да"))} -> нет | I56: =$F$54/1300*J55 -> 3.6923077 | J56: =IF(C53="нет",0,ROUNDUP(IF($E$13=Списки!$AI$2,IF(H56="",I56,H56),0),1)) -> 3.7 | K56: чел. ч | M56: =IFERROR(IF(L56<>"","",VLOOKUP(C56&D56&K56,НН!A:J,10,)),"") -> 1207.8 | N56: =IFERROR(IF(L56="",M56*J56,J56*L56),"") -> 4468.86
C57: Собственное производство | D57: ="Муфта соединительная Муфта-1 "&F54&"-1" -> Муфта соединительная Муфта-1 1200-1 | E57: Да | F57: нет | I57: 1 | J57: =IF(C53="нет",0,IF(E57="нет",0,IF(ОЛ_ЕМКОСТИ!E40="",0,IF(H57="",I57,H57)*F53))) -> 2 | K57: шт | L57: 1 | M57: =IFERROR(IF(L57<>"","",VLOOKUP(C57&D57&K57,НН!A:J,10,)),"") | N57: =IFERROR(IF(L57="",M57*J57,J57*L57),"") -> 2
C58: Собственное производство | D58: Ламинирование шахты обслуживания к корпусу | F58: {=IF(ISBLANK(C58),"",IF(OR(C58=Списки!$AG$15:$AG$17),"нет","да"))} -> нет | I58: =IFERROR(VLOOKUP(K8,'Для расчетов'!$A$36:$F$72,4,),"") -> 10.3 | J58: =IFERROR(IF(C53="нет",0,IF(ОЛ_ЕМКОСТИ!E40="",0,IF(H58="",I58,H58)*F53)),"") -> 20.6 | K58: кг | M58: =IFERROR(IF(L58<>"","",VLOOKUP(C58&D58&K58,НН!A:J,10,)),"") -> 310.2 | N58: =IFERROR(IF(L58="",M58*J58,J58*L58),"") -> 6390.12
C59: ФОТ | D59: ФОТ | F59: {=IF(C59="","",IF(OR(C59=Списки!$AG$15:$AG$17),"нет","да"))} -> нет | I59: =IF(COUNTIF(D58,"*мех*")=1,0.28,IF(COUNTIF(D58,"*ламин*")=1,0.56,1)) -> 0.56 | J59: =IFERROR(IF(C53="нет",0,ROUNDUP(IF(ОЛ_ЕМКОСТИ!$E$40="",0,IF(H59="",IFERROR(J58*I59,""),H59)),1)),"") -> 11.6 | K59: чел. ч | M59: =IFERROR(IF(L59<>"","",VLOOKUP(C59&D59&K59,НН!A:J,10,)),"") -> 1207.8 | N59: =IFERROR(IF(L59="",M59*J59,J59*L59),"") -> 14010.48
C61: Да | D61: =IF(F54<2000,"Петли монтажные по чертежу НТТ 648, в т.ч.:","Петли монтажные усиленные по чертежу НТТ 1959, в т.ч.:") -> Петли монтажные по чертежу НТТ 648, в т.ч.: | F61: =F53*2 -> 4 | G61: шт
C62: =IF(D62="","","Метизы") -> Метизы | D62: =_xlfn.IFNA(IF(G5<2000,'Вспомогат. таблицы'!A14,'Вспомогат. таблицы'!A2),"") -> Болт М24-6ɡх100.21.Ст20 ГОСТ 7798-70 | E62: =IFERROR(IF(SEARCH("*петель*",D62)=1,IF(ОЛ_ЕМКОСТИ!E20<2000,"Прим. - Петля простая","Прим. - Петля усиленная"),""),"") | F62: {=IF(C62="","",IF(OR(C62=Списки!$AG$15:$AG$17),"нет","да"))} -> да | G62: =IFERROR(3.56*0.14*J62,"") -> 3.9872 | I62: =IFERROR(IF(H62="",IF($G$5>=2000,VLOOKUP(D62,'Вспомогат. таблицы'!$A$2:$B$11,2,),VLOOKUP(D62,'Вспомогат. таблицы'!$A$15:$B$24,2,)),""),"") -> 2 | J62: =IF($C$61="нет",0,IF(C62="","",IFERROR(IF(H62="",I62,H62)*$F$61,""))) -> 8 | K62: =IF(C62="","","шт") -> шт | M62: =IFERROR(IF(L62<>"","",VLOOKUP(C62&D62&K62,НН!A:J,10,)),"") -> 105 | N62: =IFERROR(IF(L62="",M62*J62,J62*L62),"") -> 840
C63: Метизы | D63: =IF($G$5<2000,'Вспомогат. таблицы'!A15,'Вспомогат. таблицы'!A3) -> Шайба 24.21.Ст20 ГОСТ 11371-78 | E63: =IFERROR(IF(SEARCH("*петель*",D63)=1,IF($G$5<2000,"Прим. - Петля простая","Прим. - Петля усиленная"),""),"") | F63: {=IF(C63="","",IF(OR(C63=Списки!$AG$15:$AG$17),"нет","да"))} -> да | G63: =32.3*J63/1000 -> 0.2584 | I63: =IF(H63="",IF($G$5>=2000,VLOOKUP(D63,'Вспомогат. таблицы'!$A$2:$B$11,2,),VLOOKUP(D63,'Вспомогат. таблицы'!$A$15:$B$24,2,)),"") -> 2 | J63: =IF($C$61="нет",0,IF(H63="",I63,H63)*$F$61) -> 8 | K63: шт | M63: =IFERROR(IF(L63<>"","",VLOOKUP(C63&D63&K63,НН!A:J,10,)),"") -> 6 | N63: =IFERROR(IF(L63="",M63*J63,J63*L63),"") -> 48
C64: Метизы | D64: =IF($G$5<2000,'Вспомогат. таблицы'!A16,'Вспомогат. таблицы'!A4) -> Шайба 24.30х13 Ст20 ГОСТ 6402-70 | E64: =IFERROR(IF(SEARCH("*петель*",D64)=1,IF($G$5<2000,"Прим. - Петля простая","Прим. - Петля усиленная"),""),"") | F64: {=IF(C64="","",IF(OR(C64=Списки!$AG$15:$AG$17),"нет","да"))} -> да | I64: =IF(H64="",IF($G$5>=2000,VLOOKUP(D64,'Вспомогат. таблицы'!$A$2:$B$11,2,),VLOOKUP(D64,'Вспомогат. таблицы'!$A$15:$B$24,2,)),"") -> 2 | J64: =IF($C$61="нет",0,IF(H64="",I64,H64)*$F$61) -> 8 | K64: шт | M64: =IFERROR(IF(L64<>"","",VLOOKUP(C64&D64&K64,НН!A:J,10,)),"") -> 5.91 | N64: =IFERROR(IF(L64="",M64*J64,J64*L64),"") -> 47.28
C65: Метизы | D65: =IF($G$5<2000,'Вспомогат. таблицы'!A17,'Вспомогат. таблицы'!A5) -> Гайка М24-7Н.Ст20 ГОСТ 5915-70 | E65: =IFERROR(IF(SEARCH("*петель*",D65)=1,IF($G$5<2000,"Прим. - Петля простая","Прим. - Петля усиленная"),""),"") | F65: {=IF(C65="","",IF(OR(C65=Списки!$AG$15:$AG$17),"нет","да"))} -> да | G65: =27.12*J65/1000 -> 0.21696 | I65: =IF(H65="",IF($G$5>=2000,VLOOKUP(D65,'Вспомогат. таблицы'!$A$2:$B$11,2,),VLOOKUP(D65,'Вспомогат. таблицы'!$A$15:$B$24,2,)),"") -> 2 | J65: =IF($C$61="нет",0,IF(H65="",I65,H65)*$F$61) -> 8 | K65: шт | M65: =IFERROR(IF(L65<>"","",VLOOKUP(C65&D65&K65,НН!A:J,10,)),"") -> 28 | N65: =IFERROR(IF(L65="",M65*J65,J65*L65),"") -> 224
C66: Металлопрокат | D66: =IF($G$5<2000,'Вспомогат. таблицы'!A18,'Вспомогат. таблицы'!A6) -> Лист г/к Б-ПН-О-6,0х1500х3000 ГОСТ 19903-74 // Ст3пс ГОСТ 14637-89 | E66: =IFERROR(IF(SEARCH("*петель*",D66)=1,IF($G$5<2000,"Прим. - Петля простая","Прим. - Петля усиленная"),""),"") | F66: {=IF(C66="","",IF(OR(C66=Списки!$AG$15:$AG$17),"нет","да"))} -> да | G66: =107*J66/1000 -> 0.03424 | I66: =IF(H66="",IF($G$5>=2000,VLOOKUP(D66,'Вспомогат. таблицы'!$A$2:$B$11,2,),VLOOKUP(D66,'Вспомогат. таблицы'!$A$15:$B$24,2,)),"") -> 0.08 | J66: =IF($C$61="нет",0,IF(H66="",I66,H66)*$F$61) -> 0.32 | K66: м² | M66: =IFERROR(IF(L66<>"","",VLOOKUP(C66&D66&K66,НН!A:J,10,)),"") -> 5833.33 | N66: =IFERROR(IF(L66="",M66*J66,J66*L66),"") -> 1866.6656
C67: Металлопрокат | D67: =IF($G$5<2000,'Вспомогат. таблицы'!A19,'Вспомогат. таблицы'!A7) -> Лист г/к Б-ПН-О-12,0х1500х3000 ГОСТ 19903-74 // Ст3пс ГОСТ 14637-89 | E67: =IFERROR(IF(SEARCH("*петель*",D67)=1,IF($G$5<2000,"Прим. - Петля простая","Прим. - Петля усиленная"),""),"") | F67: {=IF(C67="","",IF(OR(C67=Списки!$AG$15:$AG$17),"нет","да"))} -> да | G67: =F61*0.785 -> 3.14 | I67: =IF(H67="",IF($G$5>=2000,VLOOKUP(D67,'Вспомогат. таблицы'!$A$2:$B$11,2,),VLOOKUP(D67,'Вспомогат. таблицы'!$A$15:$B$24,2,)),"") -> 0.05 | J67: =IF($C$61="нет",0,IF(H67="",I67,H67)*$F$61) -> 0.2 | K67: м² | M67: =IFERROR(IF(L67<>"","",VLOOKUP(C67&D67&K67,НН!A:J,10,)),"") -> 11222.22 | N67: =IFERROR(IF(L67="",M67*J67,J67*L67),"") -> 2244.444
C68: Металлопрокат | D68: =IF($G$5<2000,'Вспомогат. таблицы'!A20,'Вспомогат. таблицы'!A8) -> Арматура 20-А-I Ст3пс ГОСТ 5781-82 гладкая (А240) | E68: =IFERROR(IF(SEARCH("*петель*",D68)=1,IF($G$5<2000,"Прим. - Петля простая","Прим. - Петля усиленная"),""),"") | F68: {=IF(C68="","",IF(OR(C68=Списки!$AG$15:$AG$17),"нет","да"))} -> да | G68: =F61*2.26 -> 9.04 | I68: =IF(H68="",IF($G$5>=2000,VLOOKUP(D68,'Вспомогат. таблицы'!$A$2:$B$11,2,),VLOOKUP(D68,'Вспомогат. таблицы'!$A$15:$B$24,2,)),"") -> 0.9 | J68: =IF($C$61="нет",0,IF(H68="",I68,H68)*$F$61) -> 3.6 | K68: м | M68: =IFERROR(IF(L68<>"","",VLOOKUP(C68&D68&K68,НН!A:J,10,)),"") -> 190 | N68: =IFERROR(IF(L68="",M68*J68,J68*L68),"") -> 684
C69: Собственное производство | D69: =IF($G$5<2000,'Вспомогат. таблицы'!A21,'Вспомогат. таблицы'!A9) -> Ламинирование петель к корпусу | E69: =IFERROR(IF(SEARCH("*петель*",D69)=1,IF($G$5<2000,"Прим. - Петля простая","Прим. - Петля усиленная"),""),"") -> Прим. - Петля усиленная | F69: {=IF(C69="","",IF(OR(C69=Списки!$AG$15:$AG$17),"нет","да"))} -> нет | I69: =IF(H69="",IF($G$5>=2000,VLOOKUP(D69,'Вспомогат. таблицы'!$A$2:$B$11,2,),VLOOKUP(D69,'Вспомогат. таблицы'!$A$15:$B$24,2,)),"") -> 0.6 | J69: =IF($C$61="нет",0,IF(H69="",I69,H69)*$F$61) -> 2.4 | K69: кг | M69: =IFERROR(IF(L69<>"","",VLOOKUP(C69&D69&K69,НН!A:J,10,)),"") -> 310.2 | N69: =IFERROR(IF(L69="",M69*J69,J69*L69),"") -> 744.48 | O69: Ламинирование 1 простой петли = 0,4 кг, ламинирование 1 усиленной петли =0,6 кг
C70: ФОТ | D70: =IF($G$5<2000,'Вспомогат. таблицы'!A22,'Вспомогат. таблицы'!A10) -> ФОТ | E70: =IFERROR(IF(SEARCH("*петель*",D70)=1,IF($G$5<2000,"Прим. - Петля простая","Прим. - Петля усиленная"),""),"") | F70: {=IF(C70="","",IF(OR(C70=Списки!$AG$15:$AG$17),"нет","да"))} -> нет | I70: =IF(COUNTIF(D69,"*мех*")=1,0.28,IF(COUNTIF(D69,"*ламин*")=1,0.56,1)) -> 0.56 | J70: =ROUNDUP(IF($C$61="нет",0,I70*J69),1) -> 1.4 | K70: чел. ч | M70: =IFERROR(IF(L70<>"","",VLOOKUP(C70&D70&K70,НН!A:J,10,)),"") -> 1207.8 | N70: =IFERROR(IF(L70="",M70*J70,J70*L70),"") -> 1690.92
C72: Нет | D72: Фальшпол: | E72: фальшпол может быть предусмотрен, только если есть насосное оборудование
C73: Детали труб_да ПЭ ПВХ PPR | D73: Труба ПВХ Ду160 оранжевая (наружная) | E73: Отверстия для гильз под бетон 2шт | F73: {=IF(C73="","",IF(OR(C73=Списки!$AG$15:$AG$17),"нет","да"))} -> да | I73: 1 | J73: =IF(C72="НЕТ",0,I73)*$M$5 -> 0 | K73: м | M73: =IFERROR(IF(L73<>"","",VLOOKUP(C73&D73&K73,НН!A:J,10,)),"") -> 2901 | N73: =IFERROR(IF(L73="",M73*J73,J73*L73),"") -> 0
C74: Собственное производство | D74: Механическая формовка деталей фальшпола | F74: {=IF(C74="","",IF($E$64="нет","-",IF(OR(C74=Списки!$AG$15:$AG$17),"нет","да")))} -> нет | H74: =4*0.005*1850*M5 -> 37 | J74: =IF(C72="НЕТ",0,H74)*$M$5 -> 0 | K74: кг | M74: =IFERROR(IF(L74<>"","",VLOOKUP(C74&D74&K74,НН!A:J,10,)),"") -> 214.4 | N74: =IFERROR(IF(L74="",M74*J74,J74*L74),"") -> 0
C75: ФОТ | D75: ФОТ | F75: {=IF(C75="","",IF($E$64="нет","-",IF(OR(C75=Списки!$AG$15:$AG$17),"нет","да")))} -> нет | I75: =IF(COUNTIF(D74,"*мех*")=1,0.28,IF(COUNTIF(D74,"*ламин*")=1,0.56,1)) -> 0.28 | J75: =ROUNDUP(IF(H75="",IFERROR(J74*I75,""),H75),1) -> 0 | K75: чел. ч | M75: =IFERROR(IF(L75<>"","",VLOOKUP(C75&D75&K75,НН!A:J,10,)),"") -> 1207.8 | N75: =IFERROR(IF(L75="",M75*J75,J75*L75),"") -> 0
C76: Собственное производство | D76: Ламинирование фальшпола к корпусу | F76: {=IF(C76="","",IF($E$64="нет","-",IF(OR(C76=Списки!$AG$15:$AG$17),"нет","да")))} -> нет | I76: =IF(H76="",3*J74/10,"") -> 0 | J76: =IF($C$72="нет",0,IF(H76="",I76,H76)*$M$5) -> 0 | K76: кг | M76: =IFERROR(IF(L76<>"","",VLOOKUP(C76&D76&K76,НН!A:J,10,)),"") -> 310.2 | N76: =IFERROR(IF(L76="",M76*J76,J76*L76),"") -> 0
C77: ФОТ | D77: ФОТ | F77: {=IF(C77="","",IF($E$64="нет","-",IF(OR(C77=Списки!$AG$15:$AG$17),"нет","да")))} -> нет | I77: =IF(COUNTIF(D76,"*мех*")=1,0.28,IF(COUNTIF(D76,"*ламин*")=1,0.56,1)) -> 0.56 | J77: =ROUNDUP(IF(H77="",IFERROR(J76*I77,""),H77),1) -> 0 | K77: чел. ч | M77: =IFERROR(IF(L77<>"","",VLOOKUP(C77&D77&K77,НН!A:J,10,)),"") -> 1207.8 | N77: =IFERROR(IF(L77="",M77*J77,J77*L77),"") -> 0
B78: 1.2 | D78: Корпус емкости Работы (ФОТ)
C79: Собственное производство | D79: Предварительные работы для подготовки трубы (транспортировка, разметка осей, шлифовка) | E79: =D13 -> Труба СК/НПС-К 3000-0,1-10000 | F79: {=IF(C79="","",IF(OR(C79=Списки!$AG$15:$AG$17),"нет","да"))} -> нет | I79: =($G$5/(200*6))*J13 -> 37.25 | J79: =ROUNDUP(IF(H79="",I79,H79),1) -> 37.3 | K79: чел. ч | M79: =IFERROR(IF(L79<>"","",VLOOKUP(C79&D79&K79,НН!A:J,10,)),"") -> 1207.8 | N79: =IFERROR(IF(L79="",M79*J79,J79*L79),"") -> 45050.94 | O79: DN/(200*6) * Lтр
C80: Собственное производство | D80: Предварительные работы для подготовки трубы (транспортировка, разметка осей, шлифовка) | E80: =D55 -> Труба СК/НПС-К 1200-0,1-5000 | F80: {=IF(C80="","",IF(OR(C80=Списки!$AG$15:$AG$17),"нет","да"))} -> нет | I80: =($F54/(200*6))*J55 -> 4 | J80: =IF(C53="нет",0,ROUNDUP(IF(ОЛ_ЕМКОСТИ!E40="",0,IF(H80="",I80,H80)),1)) -> 4 | K80: чел. ч | M80: =IFERROR(IF(L80<>"","",VLOOKUP(C80&D80&K80,НН!A:J,10,)),"") -> 1207.8 | N80: =IFERROR(IF(L80="",M80*J80,J80*L80),"") -> 4831.2
C81: Собственное производство | D81: Предварительные работы для подготовки трубы (транспортировка, разметка осей, шлифовка) | E81: =E36+100 -> 500 | F81: {=IF(C81="","",IF(OR(C81=Списки!$AG$15:$AG$17),"нет","да"))} -> нет | I81: =((E36+100)/(200*6))*J55 -> 1.6666667 | J81: =ROUNDUP(IF(H81="",I81,H81),1) -> 1.7 | K81: чел. ч | M81: =IFERROR(IF(L81<>"","",VLOOKUP(C81&D81&K81,НН!A:J,10,)),"") -> 1207.8 | N81: =IFERROR(IF(L81="",M81*J81,J81*L81),"") -> 2053.26
C82: Собственное производство | D82: Прорезка отверстия патрубка в корпусе | E82: =E42+100 -> 400 | F82: {=IF(C82="","",IF(OR(C82=Списки!$AG$15:$AG$17),"нет","да"))} -> нет | I82: =((E42+100)/(200*6))*J55 -> 1.3333333 | J82: =ROUNDUP(IF(H82="",I82,H82),1) -> 1.4 | K82: чел. ч | M82: =IFERROR(IF(L82<>"","",VLOOKUP(C82&D82&K82,НН!A:J,10,)),"") -> 1207.8 | N82: =IFERROR(IF(L82="",M82*J82,J82*L82),"") -> 1690.92 | O82: прорезка любого отверстия: (DN* П/1000)*0,5*количество патрубков - вырезать 1 м окружности занимает 0,5 чел.ч.
C83: Собственное производство | D83: Прорезка отверстия шахты обслуживания | E83: =D55 -> Труба СК/НПС-К 1200-0,1-5000 | F83: {=IF(C83="","",IF(OR(C83=Списки!$AG$15:$AG$17),"нет","да"))} -> нет | I83: =$F$53*F54*PI()/1000*0.5 -> 3.7699112 | J83: =IF(C53="нет",0,ROUNDUP(IF(ОЛ_ЕМКОСТИ!E40="",0,IF(H83="",I83,H83)),1)) -> 3.8 | K83: чел. ч | M83: =IFERROR(IF(L83<>"","",VLOOKUP(C83&D83&K83,НН!A:J,10,)),"") -> 1207.8 | N83: =IFERROR(IF(L83="",M83*J83,J83*L83),"") -> 4589.64
C84: Собственное производство | D84: Изготовление Петель монтажных | E84: =IF(SEARCH("*петель*",D84)=1,IF(G5<2000,"Прим. - Петли простые","Прим. - Петли усиленные")) -> Прим. - Петли усиленные | F84: {=IF(C84="","",IF(OR(C84=Списки!$AG$15:$AG$17),"нет","да"))} -> нет | I84: =ROUNDUP(0.5*F61,) -> 2 | J84: =IF($C$61="нет",0,ROUNDUP(IF(H84="",I84,H84),1)) -> 2 | K84: чел. ч | M84: =IFERROR(IF(L84<>"","",VLOOKUP(C84&D84&K84,НН!A:J,10,)),"") -> 1207.8 | N84: =IFERROR(IF(L84="",M84*J84,J84*L84),"") -> 2415.6 | O84: 0,5 чел. За 1 петлю
C85: Собственное производство | D85: Монтаж Петель монтажных | E85: =IF(SEARCH("*петель*",D85)=1,IF(G5<2000,"Прим. - Петли простые","Прим. - Петли усиленные")) -> Прим. - Петли усиленные | F85: {=IF(C85="","",IF(OR(C85=Списки!$AG$15:$AG$17),"нет","да"))} -> нет | I85: =ROUNDUP(0.5*F61,) -> 2 | J85: =IF($C$61="нет",0,ROUNDUP(IF(H85="",I85,H85),1)) -> 2 | K85: чел. ч | M85: =IFERROR(IF(L85<>"","",VLOOKUP(C85&D85&K85,НН!A:J,10,)),"") -> 1207.8 | N85: =IFERROR(IF(L85="",M85*J85,J85*L85),"") -> 2415.6 | O85: 0,5 чел. За 1 петлю
C86: Собственное производство | D86: Монтаж теплоизоляции | F86: {=IF(C86="","",IF(OR(C86=Списки!$AG$15:$AG$17),"нет","да"))} -> нет | I86: =J49*1+J50*1 -> 14.608406 | J86: =ROUNDUP(IF(ОЛ_ЕМКОСТИ!$E$80="нет",0,IF(H86="",I86,H86)),1) -> 14.7 | K86: чел. ч | M86: =IFERROR(IF(L86<>"","",VLOOKUP(C86&D86&K86,НН!A:J,10,)),"") -> 1207.8 | N86: =IFERROR(IF(L86="",M86*J86,J86*L86),"") -> 17754.66
D87: Последняя строка
E88: Итого: Корпус | G88: =SUM(G13:G87) -> 14472.657 | N88: =IF($E$13=Списки!$AI$3,SUM($N$14:$N$87),SUM($N$13:$N$87)) -> 657925.74
E89: в т.ч. Материалы на закупку: | N89: {=SUM(SUMIF($C$14:$C$87,Списки!$AG$2:$AG$14,$N$14:$N$87))} -> 16910.694
E90: в т.ч. Труба, муфта: | N90: =IF($E$13=Списки!$AI$3,SUMIFS(N14:N78,D14:D78,"муфта*",F14:F78,"нет")+SUMIFS(N13:N78,D13:D78,"Труба*",F13:F78,"нет"),N13+SUMIFS(N13:N78,D13:D78,"муфта*",F13:F78,"нет")+SUMIFS(N13:N78,D13:D78,"Труба*",F13:F78,"нет"))+SUMIFS(N13:N78,E13:E78,"муфта*",F13:F78,"нет") -> 23.4 | P90: необходимо указать стоимость трубы/муфты
E91: в т.ч. Работы участка фитингов, ФОТ: | J91: =ROUNDUP(SUMIFS($J$14:$J$87,$K$14:$K$87,Списки!$S$5)-SUMIFS($J$14:$J$87,$K$14:$K$87,Списки!$S$5,$D$14:$D$87,"*изготов*"),1) -> 418.6 | K91: чел. ч | N91: =SUMIF($K$14:$K$87,Списки!$S$5,$N$14:$N$87)-SUMIFS($N$14:$N$87,$K$14:$K$87,Списки!$S$5,$D$14:$D$87,"*изготов*") -> 505585.08
E92: в т.ч. Работы участка РМУ, ФОТ: | J92: =SUMIFS($J$14:$J$87,$K$14:$K$87,Списки!$S$5,$D$14:$D$87,"*изготов*") -> 2 | N92: =SUMIFS($N$14:$N$87,$K$14:$K$87,Списки!$S$5,$D$14:$D$87,"*изготов*") -> 2415.6
E93: в т.ч. Формовка: | J93: =SUMIFS($J$13:$J$87,$K$13:$K$87,Списки!$S$4) -> 561.16389 | K93: кг | N93: =SUMIF($K$16:$K$87,Списки!$S$4,$N$16:$N$87) -> 132990.96
B94: 2 | D94: Корзина Материалы: | F94: {=IF(ISBLANK(C94),"",IF(OR(C94=Списки!$AG$15:$AG$17),"нет","да"))} | M94: {=IF(D94="ФОТ",I94*#REF!,IFERROR(IF(L94<>"","",IF((VLOOKUP(D94&K94,INDIRECT("'"&INDEX(Списки!$AG$2:$AG$17,MATCH(TRUE,COUNTIF(INDIRECT("'"&Списки!$AG$2:$AG$17 &"'!A1:A300000"),D94&K94)>0,0))&"'!A:h"),7,0))=0,"",VLOOKUP(D94&K94,INDIRECT("'"&INDEX(Списки!$AG$2:$AG$17,MATCH(TRUE,COUNTIF(INDIRECT("'"&Списки!$AG$2:$AG$17 &"'!A1:A300000"),D94&K94)>0,0))&"'!A:h"),7,0))),""))}
B95: 2.1 | D95: Количество корзин | J95: 1 | K95: шт | M95: {=IFERROR(IF(L95<>"","",IF((VLOOKUP(D95&K95,INDIRECT("'"&INDEX(Списки!$AG$2:$AG$17,MATCH(TRUE,COUNTIF(INDIRECT("'"&Списки!$AG$2:$AG$17 &"'!A1:A300000"),D95&K95)>0,0))&"'!A:h"),7,0))=0,"",VLOOKUP(D95&K95,INDIRECT("'"&INDEX(Списки!$AG$2:$AG$17,MATCH(TRUE,COUNTIF(INDIRECT("'"&Списки!$AG$2:$AG$17 &"'!A1:A300000"),D95&K95)>0,0))&"'!A:h"),7,0))),"")}
C96: Металлопрокат | D96: Уголок 20х20х1,5мм 08Х18Н10Т(AISI304) ГОСТ 8509-93 | F96: {=IF(C96="","",IF(OR(C96=Списки!$AG$15:$AG$17),"нет","да"))} -> да | I96: 10 | J96: =IF(OR(ОЛ_ЕМКОСТИ!$E$67=Списки!$H$3,ОЛ_ЕМКОСТИ!$E$67=Списки!$H$5),0,IF(H96="",I96,H96))*J95 -> 10 | K96: м | M96: =IFERROR(IF(L96<>"","",VLOOKUP(C96&D96&K96,НН!A:J,10,)),"") -> 850 | N96: =IFERROR(IF(L96="",M96*J96,J96*L96),"") -> 8500
C97: Металлопрокат | D97: Лист нержавеющий перфорированный 1х1000х2000мм Qg 10.0-12.0 марка 10х18н10 | F97: {=IF(C97="","",IF(OR(C97=Списки!$AG$15:$AG$17),"нет","да"))} -> да | I97: =IF(H97="",2,"") -> 2 | J97: =IF(OR(ОЛ_ЕМКОСТИ!$E$67=Списки!$H$3,ОЛ_ЕМКОСТИ!$E$67=Списки!$H$5),0,IF(H97="",I97,H97))*J95 -> 2 | K97: м² | M97: =IFERROR(IF(L97<>"","",VLOOKUP(C97&D97&K97,НН!A:J,10,)),"") -> 8750 | N97: =IFERROR(IF(L97="",M97*J97,J97*L97),"") -> 17500
C98: Металлопрокат | D98: Труба 45х3,0 ГОСТ 9941-81 ст 12Х18Н10Т (AISI 321) (бесшовная холоднодеформированная) ГОСТ 9941-81 | F98: {=IF(C98="","",IF(OR(C98=Списки!$AG$15:$AG$17),"нет","да"))} -> да | I98: =IF(H98="",ROUNDUP(2*(ОЛ_ЕМКОСТИ!E51/1000),),"") -> 5 | J98: =IF(OR(ОЛ_ЕМКОСТИ!$E$67=Списки!$H$3,ОЛ_ЕМКОСТИ!$E$67=Списки!$H$5),0,IF(H98="",I98,H98))*J95 -> 5 | K98: м | M98: =IFERROR(IF(L98<>"","",VLOOKUP(C98&D98&K98,НН!A:J,10,)),"") -> 3900 | N98: =IFERROR(IF(L98="",M98*J98,J98*L98),"") -> 19500
C99: Металлопрокат | D99: Круг 5 мм 12Х18Н10Т ГOCT 5949-75 | F99: {=IF(C99="","",IF(OR(C99=Списки!$AG$15:$AG$17),"нет","да"))} -> да | I99: =I100*(3.14*0.05) -> 0.628 | J99: =IF(OR(ОЛ_ЕМКОСТИ!$E$67=Списки!$H$3,ОЛ_ЕМКОСТИ!$E$67=Списки!$H$5),0,IF(H99="",I99,H99))*J95 -> 0.628 | K99: м | M99: =IFERROR(IF(L99<>"","",VLOOKUP(C99&D99&K99,НН!A:J,10,)),"") -> 125 | N99: =IFERROR(IF(L99="",M99*J99,J99*L99),"") -> 78.5
C100: Грузоподъем | D100: Цепь короткозвенная сварная 3 мм DIN 766 А2/А4 | E100: ="Для подъема и спуска корзины L= "&ROUNDUP((ОЛ_ЕМКОСТИ!E51/1000+1),0)&" м" -> Для подъема и спуска корзины L= 4 м | F100: {=IF(C100="","",IF(OR(C100=Списки!$AG$15:$AG$17),"нет","да"))} -> да | I100: =IF(H100="",ROUNDUP((ОЛ_ЕМКОСТИ!E51/1000+1),),"") -> 4 | J100: =IF(OR(ОЛ_ЕМКОСТИ!$E$67=Списки!$H$3,ОЛ_ЕМКОСТИ!$E$67=Списки!$H$5),0,IF(H100="",I100,H100))*J95 -> 4 | K100: м | M100: =IFERROR(IF(L100<>"","",VLOOKUP(C100&D100&K100,НН!A:J,10,)),"") -> 180 | N100: =IFERROR(IF(L100="",M100*J100,J100*L100),"") -> 720
C101: Грузоподъем | D101: Карабин винтовой 5 мм нерж. А4 ART 8253 | F101: {=IF(C101="","",IF(OR(C101=Списки!$AG$15:$AG$17),"нет","да"))} -> да | I101: =IF(H101="",ROUNDUP(I100/2,),"") -> 2 | J101: =IF(OR(ОЛ_ЕМКОСТИ!$E$67=Списки!$H$3,ОЛ_ЕМКОСТИ!$E$67=Списки!$H$5),0,I101)*J95 -> 2 | K101: шт | M101: =IFERROR(IF(L101<>"","",VLOOKUP(C101&D101&K101,НН!A:J,10,)),"") -> 320 | N101: =IFERROR(IF(L101="",M101*J101,J101*L101),"") -> 640
B102: 2.2 | D102: Корзина Работа (ФОТ) | F102: {=IF(ISBLANK(C102),"",IF(OR(C102=Списки!$AG$15:$AG$17),"нет","да"))} | M102: {=IF(D102="ФОТ",I102*#REF!,IFERROR(IF(L102<>"","",IF((VLOOKUP(D102&K102,INDIRECT("'"&INDEX(Списки!$AG$2:$AG$17,MATCH(TRUE,COUNTIF(INDIRECT("'"&Списки!$AG$2:$AG$17 &"'!A1:A300000"),D102&K102)>0,0))&"'!A:h"),7,0))=0,"",VLOOKUP(D102&K102,INDIRECT("'"&INDEX(Списки!$AG$2:$AG$17,MATCH(TRUE,COUNTIF(INDIRECT("'"&Списки!$AG$2:$AG$17 &"'!A1:A300000"),D102&K102)>0,0))&"'!A:h"),7,0))),""))}
C103: Собственное производство | D103: Изготовление Сороудерживающей корзины | F103: {=IF(C103="","",IF(OR(C103=Списки!$AG$15:$AG$17),"нет","да"))} -> нет | I103: =IF(G2<2500,6,7)*J95 -> 6 | J103: =ROUNDUP(IF(OR(ОЛ_ЕМКОСТИ!$E$67=Списки!$H$3,ОЛ_ЕМКОСТИ!$E$67=Списки!$H$5),0,IF(H103="",I103,H103)),1) -> 6 | K103: чел. ч | M103: =IFERROR(IF(L103<>"","",VLOOKUP(C103&D103&K103,НН!A:J,10,)),"") -> 1207.8 | N103: =IFERROR(IF(L103="",M103*J103,J103*L103),"") -> 7246.8
C104: Собственное производство | D104: Монтаж Сороудерживающей корзины | F104: {=IF(C104="","",IF(OR(C104=Списки!$AG$15:$AG$17),"нет","да"))} -> нет | I104: =IF(G2<2500,5,6)*J95 -> 5 | J104: =ROUNDUP(IF(OR(ОЛ_ЕМКОСТИ!$E$67=Списки!$H$3,ОЛ_ЕМКОСТИ!$E$67=Списки!$H$5),0,IF(H104="",I104,H104)),1) -> 5 | K104: чел. ч | M104: =IFERROR(IF(L104<>"","",VLOOKUP(C104&D104&K104,НН!A:J,10,)),"") -> 1207.8 | N104: =IFERROR(IF(L104="",M104*J104,J104*L104),"") -> 6039
C105: Собственное производство | D105: Изготовление направляющих корзины | F105: {=IF(C105="","",IF(OR(C105=Списки!$AG$15:$AG$17),"нет","да"))} -> нет | I105: =2*J95 -> 2 | J105: =ROUNDUP(IF(OR(ОЛ_ЕМКОСТИ!$E$67=Списки!$H$3,ОЛ_ЕМКОСТИ!$E$67=Списки!$H$5),0,IF(H105="",I105,H105)),1) -> 2 | K105: чел. ч | M105: =IFERROR(IF(L105<>"","",VLOOKUP(C105&D105&K105,НН!A:J,10,)),"") -> 1207.8 | N105: =IFERROR(IF(L105="",M105*J105,J105*L105),"") -> 2415.6
C106: Собственное производство | D106: Монтаж направляющих корзины | F106: {=IF(C106="","",IF(OR(C106=Списки!$AG$15:$AG$17),"нет","да"))} -> нет | I106: =2*J95 -> 2 | J106: =ROUNDUP(IF(OR(ОЛ_ЕМКОСТИ!$E$67=Списки!$H$3,ОЛ_ЕМКОСТИ!$E$67=Списки!$H$5),0,IF(H106="",I106,H106)),1) -> 2 | K106: чел. ч | M106: =IFERROR(IF(L106<>"","",VLOOKUP(C106&D106&K106,НН!A:J,10,)),"") -> 1207.8 | N106: =IFERROR(IF(L106="",M106*J106,J106*L106),"") -> 2415.6
D107: Последняя строка | M107: {=IFERROR(IF(L107<>"","",IF((VLOOKUP(D107&K107,INDIRECT("'"&INDEX(Списки!$AG$2:$AG$17,MATCH(TRUE,COUNTIF(INDIRECT("'"&Списки!$AG$2:$AG$17 &"'!A1:A300000"),D107&K107)>0,0))&"'!A:h"),7,0))=0,"",VLOOKUP(D107&K107,INDIRECT("'"&INDEX(Списки!$AG$2:$AG$17,MATCH(TRUE,COUNTIF(INDIRECT("'"&Списки!$AG$2:$AG$17 &"'!A1:A300000"),D107&K107)>0,0))&"'!A:h"),7,0))),"")}
E108: Итого: Корзина | G108: =SUM(G96:G107) -> 0 | M108: {=IFERROR(IF(L108<>"","",IF((VLOOKUP(D108&K108,INDIRECT("'"&INDEX(Списки!$AG$2:$AG$17,MATCH(TRUE,COUNTIF(INDIRECT("'"&Списки!$AG$2:$AG$17 &"'!A1:A300000"),D108&K108)>0,0))&"'!A:h"),7,0))=0,"",VLOOKUP(D108&K108,INDIRECT("'"&INDEX(Списки!$AG$2:$AG$17,MATCH(TRUE,COUNTIF(INDIRECT("'"&Списки!$AG$2:$AG$17 &"'!A1:A300000"),D108&K108)>0,0))&"'!A:h"),7,0))),"")} | N108: =IF(OR(ОЛ_КОЛОДЦА!$E$48=Списки!$H$3,ОЛ_КОЛОДЦА!$E$48=Списки!$H$5),0,SUM(N96:N107)) -> 65055.5
...

Sheet для шапки
C1: Габаритная длина рабочей части емкости, L мм | D1: Длина трубы для емкости при вертикальном расположении с шахтой обслуживания, мм | E1: Длина трубы для емкости при вертикальном расположении без шахты обслуживания, мм | F1: Длина трубы для емкости при горизонтальном расположении с шахтой обслуживания, мм | G1: Длина трубы для емкости при горизонтальном расположении без шахты обслуживания, мм | H1: Высота возвышения корпуса емкости/шахты обслуживания над землей, мм | I1: Объем емкости, м3 | J1: D шахты обслуживания, мм | K1: Высота шахты h (до верха рабочей части емкости), мм | L1: Длина (для подставновки в ОЛ)
B2: ВертикальноеПодземнаяДа | C2: =D2 -> 4000 | D2: =IF(AND(ОЛ_ЕМКОСТИ!E19<>"",ОЛ_ЕМКОСТИ!E29<>""),ОЛ_ЕМКОСТИ!E29,IF(ОЛ_ЕМКОСТИ!$E$19="",ОЛ_ЕМКОСТИ!$E$29,IF(AND(ОЛ_ЕМКОСТИ!$E$19<>"",ОЛ_ЕМКОСТИ!$E$29=""),CEILING((4*I2/(PI()*(('Калькулятор ЕМК'!$G$5/1000)^2)))*1000,100)))) -> 4000 | H2: =ОЛ_ЕМКОСТИ!$E$26 -> 300 | I2: =IF(AND(ОЛ_ЕМКОСТИ!E19<>"",ОЛ_ЕМКОСТИ!E29<>""),ОЛ_ЕМКОСТИ!E19,IF(ОЛ_ЕМКОСТИ!$E$19="",ROUNDUP((D2/1000*PI()*(('Калькулятор ЕМК'!$G$5/1000)^2))/4,),ОЛ_ЕМКОСТИ!E19)) -> 100 | J2: =ОЛ_ЕМКОСТИ!$E$40 -> 1200 | K2: =ОЛ_ЕМКОСТИ!$E$41+H2 -> 2300 | L2: =D2 -> 4000
B3: ВертикальноеПодземнаяНет | C3: =E3+H3 -> 4300 | E3: =IF(AND(ОЛ_ЕМКОСТИ!E19<>"",ОЛ_ЕМКОСТИ!E29<>""),ОЛ_ЕМКОСТИ!E29,IF(ОЛ_ЕМКОСТИ!$E$19="",ОЛ_ЕМКОСТИ!$E$29,IF(AND(ОЛ_ЕМКОСТИ!$E$19<>"",ОЛ_ЕМКОСТИ!$E$29=""),CEILING((4*I3/(PI()*(('Калькулятор ЕМК'!$G$5/1000)^2)))*1000,100)))) -> 4000 | H3: =ОЛ_ЕМКОСТИ!$E$26 -> 300 | I3: =IF(AND(ОЛ_ЕМКОСТИ!E19<>"",ОЛ_ЕМКОСТИ!E29<>""),ОЛ_ЕМКОСТИ!E19,IF(ОЛ_ЕМКОСТИ!$E$19=0,ROUNDUP((E3/1000*PI()*(('Калькулятор ЕМК'!$G$5/1000)^2))/4,),ОЛ_ЕМКОСТИ!E19)) -> 100 | J3: 0 | K3: 0 | L3: =C3 -> 4300
B4: ВертикальноеНаземнаяДа | C4: =D4 -> 4000 | D4: =IF(AND(ОЛ_ЕМКОСТИ!E19<>"",ОЛ_ЕМКОСТИ!E29<>""),ОЛ_ЕМКОСТИ!E29,IF(ОЛ_ЕМКОСТИ!$E$19="",ОЛ_ЕМКОСТИ!$E$29,IF(AND(ОЛ_ЕМКОСТИ!$E$19<>"",ОЛ_ЕМКОСТИ!$E$29=""),CEILING((4*I4/(PI()*(('Калькулятор ЕМК'!$G$5/1000)^2)))*1000,100)))) -> 4000 | H4: 0 | I4: =IF(AND(ОЛ_ЕМКОСТИ!E19<>"",ОЛ_ЕМКОСТИ!E29<>""),ОЛ_ЕМКОСТИ!E19,IF(ОЛ_ЕМКОСТИ!$E$19=0,ROUNDUP((D4/1000*PI()*(('Калькулятор ЕМК'!$G$5/1000)^2))/4,),ОЛ_ЕМКОСТИ!E19)) -> 100 | J4: =ОЛ_ЕМКОСТИ!$E$40 -> 1200 | K4: =ОЛ_ЕМКОСТИ!$E$41 -> 2000 | L4: =D4 -> 4000
B5: ВертикальноеНаземнаяНет | C5: =E5 -> 4000 | E5: =IF(AND(ОЛ_ЕМКОСТИ!E19<>"",ОЛ_ЕМКОСТИ!E29<>""),ОЛ_ЕМКОСТИ!E29,IF(ОЛ_ЕМКОСТИ!$E$19="",ОЛ_ЕМКОСТИ!$E$29,IF(AND(ОЛ_ЕМКОСТИ!$E$19<>"",ОЛ_ЕМКОСТИ!$E$29=""),CEILING((4*I4/(PI()*(('Калькулятор ЕМК'!$G$5/1000)^2)))*1000,100)))) -> 4000 | H5: 0 | I5: =IF(AND(ОЛ_ЕМКОСТИ!E19<>"",ОЛ_ЕМКОСТИ!E29<>""),ОЛ_ЕМКОСТИ!E19,IF(ОЛ_ЕМКОСТИ!$E$19=0,ROUNDUP((E5/1000*PI()*(('Калькулятор ЕМК'!$G$5/1000)^2))/4,),ОЛ_ЕМКОСТИ!E19)) -> 100 | J5: 0 | K5: 0 | L5: =E5 -> 4000
B6: ГоризонтальноеПодземнаяДа | C6: =F6 -> 13400 | F6: =IF(AND(ОЛ_ЕМКОСТИ!E19<>"",ОЛ_ЕМКОСТИ!E28<>""),ОЛ_ЕМКОСТИ!E28,IF(ОЛ_ЕМКОСТИ!$E$19="",ОЛ_ЕМКОСТИ!$E$28,IF(AND(ОЛ_ЕМКОСТИ!E19<>"",ОЛ_ЕМКОСТИ!E28=""),CEILING((4*(I6-'Калькулятор ЕМК'!$L$5)/(PI()*(('Калькулятор ЕМК'!$G$5/1000)^2)))*1000,100)))) -> 13400 | H6: =ОЛ_ЕМКОСТИ!$E$26 -> 300 | I6: =IF(AND(ОЛ_ЕМКОСТИ!E19<>"",ОЛ_ЕМКОСТИ!E28<>""),ОЛ_ЕМКОСТИ!E19,IF(ОЛ_ЕМКОСТИ!$E$19=0,ROUNDUP((F6/1000*PI()*(('Калькулятор ЕМК'!$G$5/1000)^2))/4+'Калькулятор ЕМК'!L5,),ОЛ_ЕМКОСТИ!E19)) -> 100 | J6: =ОЛ_ЕМКОСТИ!$E$40 -> 1200 | K6: =ОЛ_ЕМКОСТИ!$E$41+H6 -> 2300 | L6: =F6 -> 13400
B7: ГоризонтальноеПодземнаяНет | C7: =G7 -> 13400 | G7: =IF(AND(ОЛ_ЕМКОСТИ!E19<>"",ОЛ_ЕМКОСТИ!E28<>""),ОЛ_ЕМКОСТИ!E28,IF(ОЛ_ЕМКОСТИ!$E$19="",ОЛ_ЕМКОСТИ!$E$28,CEILING((4*(I7-'Калькулятор ЕМК'!$L$5)/(PI()*(('Калькулятор ЕМК'!$G$5/1000)^2)))*1000,100))) -> 13400 | H7: =ОЛ_ЕМКОСТИ!$E$26 -> 300 | I7: =IF(AND(ОЛ_ЕМКОСТИ!E19<>"",ОЛ_ЕМКОСТИ!E28<>""),ОЛ_ЕМКОСТИ!E19,IF(ОЛ_ЕМКОСТИ!$E$19=0,ROUNDUP((G7/1000*PI()*(('Калькулятор ЕМК'!$G$5/1000)^2))/4+'Калькулятор ЕМК'!L5,),ОЛ_ЕМКОСТИ!E19)) -> 100 | J7: 0 | K7: 0 | L7: =G7 -> 13400
B8: ГоризонтальноеНаземнаяДа | C8: =F8+'Калькулятор ЕМК'!G5/2 -> 14900 | F8: =IF(AND(ОЛ_ЕМКОСТИ!E19<>"",ОЛ_ЕМКОСТИ!E28<>""),ОЛ_ЕМКОСТИ!E28,IF(ОЛ_ЕМКОСТИ!$E$19="",ОЛ_ЕМКОСТИ!$E$28,IF(AND(ОЛ_ЕМКОСТИ!E19<>"",ОЛ_ЕМКОСТИ!E28=""),CEILING((4*(I8-'Калькулятор ЕМК'!$L$5)/(PI()*(('Калькулятор ЕМК'!$G$5/1000)^2)))*1000,100)))) -> 13400 | H8: 0 | I8: =IF(AND(ОЛ_ЕМКОСТИ!E19<>"",ОЛ_ЕМКОСТИ!E28<>""),ОЛ_ЕМКОСТИ!E19,IF(ОЛ_ЕМКОСТИ!$E$19=0,ROUNDUP((F8/1000*PI()*(('Калькулятор ЕМК'!$G$5/1000)^2))/4+'Калькулятор ЕМК'!L5,),ОЛ_ЕМКОСТИ!E19)) -> 100 | J8: =ОЛ_ЕМКОСТИ!$E$40 -> 1200 | K8: =ОЛ_ЕМКОСТИ!$E$41 -> 2000 | L8: =F8 -> 13400
B9: ГоризонтальноеНаземнаяНет | C9: =G9+'Калькулятор ЕМК'!G5/2 -> 14900 | G9: =IF(AND(ОЛ_ЕМКОСТИ!E19<>"",ОЛ_ЕМКОСТИ!E28<>""),ОЛ_ЕМКОСТИ!E28,IF(ОЛ_ЕМКОСТИ!$E$19="",ОЛ_ЕМКОСТИ!$E$28,CEILING((4*(I9-'Калькулятор ЕМК'!$L$5)/(PI()*(('Калькулятор ЕМК'!$G$5/1000)^2)))*1000,100))) -> 13400 | H9: 0 | I9: =IF(AND(ОЛ_ЕМКОСТИ!E19<>"",ОЛ_ЕМКОСТИ!E28<>""),ОЛ_ЕМКОСТИ!E19,IF(ОЛ_ЕМКОСТИ!$E$19=0,ROUNDUP((G9/1000*PI()*(('Калькулятор ЕМК'!$G$5/1000)^2))/4+'Калькулятор ЕМК'!L5,),ОЛ_ЕМКОСТИ!E19)) -> 100 | J9: 0 | K9: 0 | L9: =G9 -> 13400

Sheet ОЛ_НАСОСНАЯ_СТАНЦИЯ
B1: ОБЩЕСТВО С ОГРАНИЧЕННОЙ ОТВЕТСТВЕННОСТЬЮ «НОВЫЕ ТРУБНЫЕ ТЕХНОЛОГИИ» 141320, Московская область, г.о. Сергиево-Посадский, д. Коврово, д. 50, помещ. 2 E-mail: info@ntt.su, тел/факс: +7(499) 949-14-04
C4: ОПРОСНЫЙ ЛИСТ НАСОСНОЙ СТАНЦИИ
C6: *к заявке ООО «НТТ» № | E6: ОЛ/
C7: Тип насосной станции | E7: Канализационная
C8: Назначение ОЛ* | D8: → | E8: Материальный расчет
C9: *(выберите одно или несколько назначений) | D9: →
D10: →
D11: →
C12: *Дата заполнения:
C13: *Заказчик:
C14: Стадия проекта: | E14: проект
C15: Объект:
C16: Регион объекта:
C18: Предполагаемый размер насосной станции*:
C20: *Диаметр DN, мм | E20: 3000
C21: *Давление PN, Мпа | E21: 0.1
C22: *Жесткость SN, Па | E22: 10000
C23: Производство | D23: =IF(C23="Производство","Общий метраж выпуска →","Номер заказа →") -> Общий метраж выпуска →
C24: *Глубина корпуса L (подземная часть) , мм | E24: =P46 -> 11500 | G24: ручной ввод
C25: Высота возвышения корпуса насосной станции над землей, мм | E25: 300 | F25: возвышение люков
C26: Установка под проезжей частью (Да/Нет): | E26: Нет
C27: По ТТ МВК (Да/Нет): | E27: Да
C29: Смола:
C31: Тип смолы | E31: Стандарт
C32: Марка смолы | E32: =VLOOKUP(E31,Списки!$BH$1:$BI$4,2,) -> ИЗО
C33: MAX температура жидкости, оС
C34: Вид стоков | E34: Дождевые
C35: Возможное MAX внутреннее давление, кг/см2
C37: Параметры патрубков:
C39: подводящего трубопровода: | G39: напорного трубопровода:
C40: Материал подводящего трубопровода | E40: ПЭ | G40: Материал напорного трубопровода: | I40: ПЭ | M40: Vэф= | N40: =(E51)/(4*P40*E55) -> 2.0124 | O40: м3 | P40: 5 | Q40: 10 | R40: 20 | S40: пусков в час
C41: *Глубина залегания подводящего трубопровода А, мм. | E41: 9910 | F41: =162.1-152.19 -> 9.91 | G41: *Глубина залегания напорного трубопровода В, мм | I41: 2300 | J41: =162.1-159.8 -> 2.3 | M41: Vмин= | N41: =(E51/2)*P41/60 -> 3.354 | O41: м3 | P41: 5 | Q41: 10 | R41: 20 | S41: поминутная работа
C42: *Номинальный диаметр подводящего трубопровода DА, мм | E42: 400 | G42: *Номинальный диаметр напорного трубопровода DВ, мм | I42: 150 | M42: Vраб= | N42: =N41 -> 3.354 | O42: м3
C43: *Направление подводящего трубопровода, в часах | G43: *Направление напорного трубопровода, в часах
C44: *Количество подводящих трубопроводов, шт. | E44: 1 | G44: *Количество напорных трубопроводов, шт. | I44: 2 | M44: hраб= | N44: =4*N42/(PI()*POWER(E20/1000,2)) -> 0.47449394 | O44: м
C45: Предполагаемый тип соединения подводящего трубопровода с КНС | E45: Раструб | G45: *Тип запорной арматуры | I45: Задвижка клиновая с обрезиненным клином | M45: hР= | N45: =N44+0.3+N50+N47 -> 1.5344939 | O45: м | P45: с учетом поплавков и рамы насосов
C46: Наличие дробилки/корзины для мусора | E46: Корзина для мусора | G46: Количество задвижек | I46: 7 | M46: Нподз | N46: =E41/1000+N45 -> 11.444494 | O46: мм | P46: =ROUNDUP(N46*1000,-2) -> 11500
C47: Наличие запорной арматуры на подводящем трубопроводе | E47: Да | G47: Наличие аварийного трубопровода | I47: Да | J47: 1 | M47: Минимальный уровень жидкости для работы насоса (из тех. паспорта подобранного насоса вводится вручную) | N47: 0.6 | O47: м
G48: Наличие трубопровода взмучивания | I48: Нет | J48: 1 | M48: Мин. уровень жидкости в КНС (уровень 1 поплавка от дна КНС) | N48: =N47+N50 -> 0.76 | O48: м
C49: Параметры для насосного оборудования: | M49: Высота подъема на выходе из КНС (геометр. Подъем) | N49: =P46/1000-N47-N50-I41/1000 -> 8.44 | O49: м
M50: Высота рамы насосов | N50: 0.16 | O50: м
C51: *Максимальный приток сточных вод | D51: =IF(F51=[3]Списки!$U$2,CONCATENATE("(",ROUND(E51/1000*3600,2)," м3/ч)"),IF(F51=[3]Списки!$U$3,"",CONCATENATE("(",ROUND(E51/24,2)," м3/ч)"))) | E51: =22.36*3.6 -> 80.496 | F51: м3/ч | G51: ← выберите ЕИ
C52: *Расчетный напор на выходе, м | E52: 12.8
C53: Марка насосов:
C54: *Количество насосов:
D55: - рабочих | E55: 2 | G55: схема обвязки напорного трубопровода | I55: 2+1
D56: - резервных | E56: 1
D57: - запасных на склад | E57: 1
C58: Автоматическая трубная муфта (из тех. паспорта насосов) | E58: 100
C59: Взрывозащита насосов: | E59: Нет
C61: Наличие дополнительного оборудования: | E61: Да
C63: Шкаф управления | E63: Да | G63: Датчики: | I63: Да
C64: Тип: | E64: Уличный | G64: давления | I64: Да
C65: Марка шкафа: | G65: уровня | I65: Да
C66: Ввод электропитания: | E66: Один | G66: расходомер | I66: Да
C67: Пуск ШУ: | E67: Плавный
C68: Модуль передачи данных в систему диспетчеризации: | E68: CIM 250 GSM/GPRS
C70: Вентиляция | E70: Приточно-вытяжная с мех. побуждением
C72: *Теплоизоляция | E72: Да
C73: Глубина теплоизоляции, мм | E73: 2000
C75: Обязательные дополнения к заявке:
C77: * - поля обязательные для заполнения
C79: Приложение: документы заказчика на | F79: листах
F82: ______________________________ (________________________)
F84: ______________________________ (________________________)

Sheet Калькулятор КНС
C1: Материальный расчет | M1: к содержанию
C3: Дата заполнения таблицы | D3: Заказчик/ Объект/ Вид насосной станции/ Параметры | G3: DN трубы, мм | H3: Полный габарит корп., Н мм | I3: Подзем. Часть L, м | J3: DN вход. патрубка, мм | K3: Кол-во вход. патрубков, шт | L3: DN напор. труб-да на вых.КНС, мм | M3: Кол-во напор. труб-дов, шт
H4: =IF(H5<3000,3000,IF(H5>7000,12000,CEILING(H5,500))) -> 12000 | I4: =CONCATENATE(G5,"-b") -> 3000-b
D5: ="Заявка № "&ОЛ_НАСОСНАЯ_СТАНЦИЯ!E6&" Заказчик: "&ОЛ_НАСОСНАЯ_СТАНЦИЯ!E13&" "&ОЛ_НАСОСНАЯ_СТАНЦИЯ!E15&" "&ОЛ_НАСОСНАЯ_СТАНЦИЯ!E7&" "&G5&"х"&H5&"мм" -> Заявка № ОЛ/ Заказчик: Канализационная 3000х11800мм | G5: =ОЛ_НАСОСНАЯ_СТАНЦИЯ!E20 -> 3000 | H5: =I5+ОЛ_НАСОСНАЯ_СТАНЦИЯ!E25 -> 11800 | I5: =IF(ОЛ_НАСОСНАЯ_СТАНЦИЯ!F24="",ОЛ_НАСОСНАЯ_СТАНЦИЯ!E24,ОЛ_НАСОСНАЯ_СТАНЦИЯ!F24) -> 11500 | J5: =ОЛ_НАСОСНАЯ_СТАНЦИЯ!E42 -> 400 | K5: =ОЛ_НАСОСНАЯ_СТАНЦИЯ!E44 -> 1 | L5: =ОЛ_НАСОСНАЯ_СТАНЦИЯ!I42 -> 150 | M5: =ОЛ_НАСОСНАЯ_СТАНЦИЯ!I44 -> 2
C6: Наименование изделия | D6: Материал изделия | E6: Транспортируемая среда | F6: Давление трубопровода, PN МПа | H6: Жесткость, SN Па | J6: D гильзы для прохода вход.патрубка, мм | L6: D гильзы для прохода напор. труб-да, мм
F7: =IF(AND('Калькулятор КНС'!G8>0.6,OR(CONCATENATE('Калькулятор КНС'!G5,'Калькулятор КНС'!I8)=CONCATENATE('Вес трубы, ПЭ трубы'!B51,'Вес трубы, ПЭ трубы'!C51),CONCATENATE('Калькулятор КНС'!G5,'Калькулятор КНС'!I8)=CONCATENATE('Вес трубы, ПЭ трубы'!B55,'Вес трубы, ПЭ трубы'!C55),CONCATENATE('Калькулятор КНС'!G5,'Калькулятор КНС'!I8)=CONCATENATE('Вес трубы, ПЭ трубы'!B57,'Вес трубы, ПЭ трубы'!C57))),1.6,IF(AND(G5=1300,OR(I8=5000,I8=10000),'Калькулятор КНС'!G8<=0.4),0.4,IF(G8<=0.6,0.6,1))) -> 0.6 | J7: +100 | K7: Вручную | L7: +100 | M7: Вручную
C8: Труба | D8: СК/НПС | E8: К | G8: =ОЛ_НАСОСНАЯ_СТАНЦИЯ!E21 -> 0.1 | I8: =ОЛ_НАСОСНАЯ_СТАНЦИЯ!E22 -> 10000 | K8: =IF(J5>=200,_xlfn.CEILING.MATH(IF(J5<100,J5,J5+100),100),_xlfn.CEILING.MATH(IF(J5<100,J5,J5+100),50)) -> 500 | M8: =IF(L5>=200,_xlfn.CEILING.MATH(IF(L5<100,L5,L5+100),100),_xlfn.CEILING.MATH(IF(L5<100,L5,L5+100),50)) -> 250
B9: № | C9: Категория | D9: Материалы,работы, услуги. | F9: Закупка | G9: Вес, кг/пм | H9: Кол-во за 1 ед. | J9: Общ. кол-во | K9: ЕИ | L9: Цена за 1 ед., руб | N9: Сумма, руб | O9: Примечание | P9: МТО | Q9: Логистика
B11: 1 | D11: =CONCATENATE("Корпус ",ОЛ_НАСОСНАЯ_СТАНЦИЯ!E7," ",G5,"х",H5,"мм"," ","(где ",I5,"мм"," - подземная часть), в т.ч.:") -> Корпус Канализационная 3000х11800мм (где 11500мм - подземная часть), в т.ч.:
B12: 1.1 | D12: Корпус КНС. Материалы
I13: Кол-во корпусов: | J13: 1 | K13: шт | M13: {=IFERROR(IF(L13<>"","",IF((VLOOKUP(D13&K13,INDIRECT("'"&INDEX(Списки!$AG$2:$AG$17,MATCH(TRUE,COUNTIF(INDIRECT("'"&Списки!$AG$2:$AG$17 &"'!A1:A300000"),D13&K13)>0,0))&"'!A:h"),7,0))=0,"",VLOOKUP(D13&K13,INDIRECT("'"&INDEX(Списки!$AG$2:$AG$17,MATCH(TRUE,COUNTIF(INDIRECT("'"&Списки!$AG$2:$AG$17 &"'!A1:A300000"),D13&K13)>0,0))&"'!A:h"),7,0))),"")}
D14: =IF(C8="","",CONCATENATE(C8," ",D8,"-",E8," ",G5,"-",G8,"-",I8)) -> Труба СК/НПС-К 3000-0,1-10000 | E14: Целая труба | F14: =IF(E14=Списки!AI3,"Справочно","") | G14: =IFERROR(I14*INDEX('Вес трубы, ПЭ трубы'!E:G,MATCH(CONCATENATE(G5&";"&F7&";"&I8),'Вес трубы, ПЭ трубы'!E:E,),3),"") -> 11157.3 | I14: =I5/1000 -> 11.5 | J14: =IF(H14="",I14,H14) -> 11.5 | K14: м | L14: 1 | M14: {=IFERROR(IF(L14<>"","",IF((VLOOKUP(D14&K14,INDIRECT("'"&INDEX(Списки!$AG$2:$AG$17,MATCH(TRUE,COUNTIF(INDIRECT("'"&Списки!$AG$2:$AG$17 &"'!A1:A300000"),D14&K14)>0,0))&"'!A:h"),7,0))=0,"",VLOOKUP(D14&K14,INDIRECT("'"&INDEX(Списки!$AG$2:$AG$17,MATCH(TRUE,COUNTIF(INDIRECT("'"&Списки!$AG$2:$AG$17 &"'!A1:A300000"),D14&K14)>0,0))&"'!A:h"),7,0))),"")} | N14: =IFERROR(IF(L14="",M14*J14,J14*L14),"") -> 11.5 | O14: заполнить стоимость трубы,
C15: Собственное производство | D15: Придание изделию товарного вида | F15: {=IF(C15="","",IF(OR(C15=Списки!$AG$15:$AG$17),"нет","да"))} -> нет | I15: =G5/1300*J14 -> 26.538462 | J15: =ROUNDUP(IF($E$14=Списки!$AI$2,IF(H15="",I15,H15),0),1) -> 26.6 | K15: чел. ч | M15: =IFERROR(IF(L15<>"","",VLOOKUP(C15&'Калькулятор КНС'!D15&'Калькулятор КНС'!K15,НН!A:J,10,)),"") -> 1207.8 | N15: =IFERROR(IF(L15="",M15*J15,J15*L15),"") -> 32127.48
C16: Собственное производство | D16: =IF(C8="","",CONCATENATE(C8," ",D8,"-",E8," ",G5,"-",G8,"-",I8)) -> Труба СК/НПС-К 3000-0,1-10000 | F16: нет | G16: =IFERROR(I16*INDEX('Вес трубы, ПЭ трубы'!E:G,MATCH(CONCATENATE(#REF!&";"&F8&";"&#REF!),'Вес трубы, ПЭ трубы'!E:E,),3),"") | H16: 7 | J16: =IF($E$14=Списки!$AI$2,0,IF(H16="",I16,H16)) -> 0 | K16: м | M16: =IFERROR(IF(L16<>"","",VLOOKUP(C16&'Калькулятор КНС'!D16&'Калькулятор КНС'!K16,НН!A:J,10,)),"") | N16: =IFERROR(J16*L16,0) -> 0
C17: Собственное производство | D17: Придание изделию товарного вида | F17: {=IF(C17="","",IF(OR(C17=Списки!$AG$15:$AG$17),"нет","да"))} -> нет | I17: =$G$5/1300*J16 -> 0 | J17: =ROUNDUP(IF(H17="",I17,H17),1) -> 0 | K17: чел. ч | M17: =IFERROR(IF(L17<>"","",VLOOKUP(C17&'Калькулятор КНС'!D17&'Калькулятор КНС'!K17,НН!A:J,10,)),"") -> 1207.8 | N17: =IFERROR(IF(L17="",M17*J17,J17*L17),"") -> 0
C18: Собственное производство | D18: =IF(C8="","",CONCATENATE(C8," ",D8,"-",E8," ",G5,"-",G8,"-",I8)) -> Труба СК/НПС-К 3000-0,1-10000 | F18: нет | H18: 5.5 | J18: =IF($E$14=Списки!$AI$2,0,IF(H18="",I18,H18)) -> 0 | K18: м | M18: =IFERROR(IF(L18<>"","",VLOOKUP(C18&'Калькулятор КНС'!D18&'Калькулятор КНС'!K18,НН!A:J,10,)),"") | N18: =IFERROR(J18*L18,0) -> 0
C19: Собственное производство | D19: Придание изделию товарного вида | F19: {=IF(C19="","",IF(OR(C19=Списки!$AG$15:$AG$17),"нет","да"))} -> нет | I19: =$G$5/1300*J18 -> 0 | J19: =ROUNDUP(IF(H19="",I19,H19),1) -> 0 | K19: чел. ч | M19: =IFERROR(IF(L19<>"","",VLOOKUP(C19&'Калькулятор КНС'!D19&'Калькулятор КНС'!K19,НН!A:J,10,)),"") -> 1207.8 | N19: =IFERROR(IF(L19="",M19*J19,J19*L19),"") -> 0
C20: Собственное производство | D20: Ламинирование частей корпуса | F20: нет | I20: =VLOOKUP(IF(G5="",G5,G5),'Для расчетов'!J36:S143,10,) -> 112 | J20: =IF($E$14=Списки!$AI$2,0,IF(H20="",I20,H20)) -> 0 | K20: кг | M20: =IFERROR(IF(L20<>"","",VLOOKUP(C20&'Калькулятор КНС'!D20&'Калькулятор КНС'!K20,НН!A:J,10,)),"") -> 310.2 | N20: =IFERROR(IF(L20="",M20*J20,J20*L20),0) -> 0
C21: ФОТ | D21: ФОТ | F21: нет | I21: =IF(COUNTIF(D20,"*мех*")=1,0.28,IF(COUNTIF(D20,"*ламин*")=1,1)) -> 1 | J21: =IF($E$14=Списки!$AI$2,0,IF(H21="",I21,H21)) -> 0 | K21: чел. ч | M21: =IFERROR(IF(L21<>"","",VLOOKUP(C21&'Калькулятор КНС'!D21&'Калькулятор КНС'!K21,НН!A:J,10,)),"") -> 1207.8 | N21: =IFERROR(IF(L21="",M21*J21,J21*L21),0) -> 0
C22: Собственное производство | D22: =IF(C50="да","Механическое формованное дно","Механическая формовка плоского днища") -> Механическое формованное дно | F22: {=IF(C22="","",IF(OR(C22=Списки!$AG$15:$AG$17),"нет","да"))} -> нет | I22: =((PI()*(($G$5+300)/(1000*2))^2)*0.01*1850)+(((G5/1000)^2*PI()*0.008*1850)/4) -> 262.84528 | J22: =IF(H22="",I22,H22) -> 262.84528 | K22: кг | M22: =IFERROR(IF(L22<>"","",VLOOKUP(C22&'Калькулятор КНС'!D22&'Калькулятор КНС'!K22,НН!A:J,10,)),"") -> 214.4 | N22: =IFERROR(IF(L22="",M22*J22,J22*L22),"") -> 56354.027 | O22: дно фальшпола+второе дно - новая конструкция
C23: ФОТ | D23: ФОТ | F23: {=IF(C23="","",IF(OR(C23=Списки!$AG$15:$AG$17),"нет","да"))} -> нет | I23: =IF(COUNTIF(D22,"*мех*")=1,0.28,IF(COUNTIF(D22,"*ламин*")=1,0.56,1)) -> 0.28 | J23: =ROUNDUP(IF(H23="",IFERROR(J22*I23,""),H23),1) -> 73.6 | K23: чел. ч | M23: =IFERROR(IF(L23<>"","",VLOOKUP(C23&'Калькулятор КНС'!D23&'Калькулятор КНС'!K23,НН!A:J,10,)),"") -> 1207.8 | N23: =IFERROR(IF(L23="",M23*J23,J23*L23),"") -> 88894.08
C24: Собственное производство | D24: =IF(C50="да","Ламинирование дна к фальшполу","Ламинирование плоского днища") -> Ламинирование дна к фальшполу | F24: {=IF(C24="","",IF(OR(C24=Списки!$AG$15:$AG$17),"нет","да"))} -> нет | I24: =IF(H24="",IFERROR(IF(H22="",J22,H22)*3/10,""),"") -> 78.853583 | J24: =IF(H24="",I24,H24) -> 78.853583 | K24: кг | M24: =IFERROR(IF(L24<>"","",VLOOKUP(C24&'Калькулятор КНС'!D24&'Калькулятор КНС'!K24,НН!A:J,10,)),"") -> 310.2 | N24: =IFERROR(IF(L24="",M24*J24,J24*L24),"") -> 24460.381
C25: ФОТ | D25: ФОТ | F25: {=IF(C25="","",IF(OR(C25=Списки!$AG$15:$AG$17),"нет","да"))} -> нет | I25: =IF(COUNTIF(D24,"*мех*")=1,0.28,IF(COUNTIF(D24,"*ламин*")=1,0.56,1)) -> 0.56 | J25: =ROUNDUP(IF(H25="",IFERROR(J24*I25,""),H25),1) -> 44.2 | K25: чел. ч | M25: =IFERROR(IF(L25<>"","",VLOOKUP(C25&'Калькулятор КНС'!D25&'Калькулятор КНС'!K25,НН!A:J,10,)),"") -> 1207.8 | N25: =IFERROR(IF(L25="",M25*J25,J25*L25),"") -> 53384.76
D26: Входящий патрубок | M26: {=IFERROR(IF(L26<>"","",IF((VLOOKUP(D26&K26,INDIRECT("'"&INDEX(Списки!$AG$2:$AG$17,MATCH(TRUE,COUNTIF(INDIRECT("'"&Списки!$AG$2:$AG$17 &"'!A1:A300000"),D26&K26)>0,0))&"'!A:h"),7,0))=0,"",VLOOKUP(D26&K26,INDIRECT("'"&INDEX(Списки!$AG$2:$AG$17,MATCH(TRUE,COUNTIF(INDIRECT("'"&Списки!$AG$2:$AG$17 &"'!A1:A300000"),D26&K26)>0,0))&"'!A:h"),7,0))),"")}
C27: Собственное производство | D27: =IF(ОЛ_НАСОСНАЯ_СТАНЦИЯ!E40="Труба стеклокомпозитная","Муфта-2 СК/НПС-К "&J$5&"-1",IF(ОЛ_НАСОСНАЯ_СТАНЦИЯ!E40=Списки!L$8,IF(J$5>=300,"Труба СК/НПС-К "&K$8&"-0,1-2500","Ручная формовка патрубка"),IF(J$5>=200,"Труба СК/НПС-К "&_xlfn.CEILING.MATH(IF(J$8="",K$8,J$8),50)&"-0,1-2500","Ручная формовка патрубка"))) -> Труба СК/НПС-К 500-0,1-2500 | E27: =IF(ОЛ_НАСОСНАЯ_СТАНЦИЯ!E40="Труба стеклокомпозитная","Муфта-2 СК/НПС-К "&J$5&"-1","Стеклокомпозитная гильза Ø"&K$8) -> Стеклокомпозитная гильза Ø500 | F27: {=IF(C27="","",IF(OR(C27=Списки!$AG$15:$AG$17),"нет","да"))} -> нет | J27: =IFERROR(IF(SEARCH("*гильза*",E27)=1,0.5*$K$5),VLOOKUP(IF(J8="",K8,J8),'Для расчетов'!$A$36:$F$60,4,)*$K$5) -> 0.5 | K27: =IFERROR(IF(SEARCH("*труба*",D27)=1,"м"),"кг") -> м | L27: =IFERROR(IF(SEARCH("м",K27)=1,"1,00"),"") -> 1,00 | M27: =IFERROR(IF(L27<>"","",VLOOKUP(C27&'Калькулятор КНС'!D27&'Калькулятор КНС'!K27,НН!A:J,10,)),"") | N27: =IFERROR(IF(L27="",M27*J27,J27*L27),0) -> 0.5 | O27: заполнить стоимость трубы, если формованный патрубок
C28: Собственное производство | D28: Придание изделию товарного вида | F28: {=IF(C28="","",IF(OR(C28=Списки!$AG$15:$AG$17),"нет","да"))} -> нет | I28: =K8/1300*J27 -> 0.19230769 | J28: =IF(COUNTIF(D27,"*труба*")=1,K8/1300*J27,0) -> 0.19230769 | K28: чел. ч | M28: =IFERROR(IF(L28<>"","",VLOOKUP(C28&'Калькулятор КНС'!D28&'Калькулятор КНС'!K28,НН!A:J,10,)),"") -> 1207.8 | N28: =IFERROR(IF(L28="",M28*J28,J28*L28),"") -> 232.26923
C29: Собственное производство | D29: Ламинирование патрубка к корпусу | F29: {=IF(C29="","",IF(OR(C29=Списки!$AG$15:$AG$17),"нет","да"))} -> нет | J29: =IFERROR(IF(SEARCH("*труба*",E27)=1,VLOOKUP(IF(J8="",K8,J8),'Для расчетов'!$A$36:$F$60,4,)*3/10*$K$5),VLOOKUP(IF(J8="",K8,J8),'Для расчетов'!$A$36:$F$60,4,)*$K$5*3/10) -> 0.57 | K29: кг | M29: =IFERROR(IF(L29<>"","",VLOOKUP(C29&'Калькулятор КНС'!D29&'Калькулятор КНС'!K29,НН!A:J,10,)),"") -> 310.2 | N29: =IFERROR(IF(L29="",M29*J29,J29*L29),"") -> 176.814
C30: ФОТ | D30: ФОТ | F30: {=IF(C30="","",IF(OR(C30=Списки!$AG$15:$AG$17),"нет","да"))} -> нет | I30: =IF(COUNTIF(D29,"*мех*")=1,0.28,IF(COUNTIF(D29,"*ламин*")=1,1)) -> 1 | J30: =ROUNDUP(IF(H30="",IFERROR(J29*I30,""),H30),1) -> 0.6 | K30: чел. ч | M30: =IFERROR(IF(L30<>"","",VLOOKUP(C30&'Калькулятор КНС'!D30&'Калькулятор КНС'!K30,НН!A:J,10,)),"") -> 1207.8 | N30: =IFERROR(IF(L30="",M30*J30,J30*L30),"") -> 724.68 | O30: ламинирование патрубка/муфты к корпуск коэффициент = 1
D32: Фланцевый патрубок для задвижки на подводящем патрубке | I32: =2*K5 -> 2 | J32: шт | M32: {=IFERROR(IF(L32<>"","",IF((VLOOKUP(D32&K32,INDIRECT("'"&INDEX(Списки!$AG$2:$AG$17,MATCH(TRUE,COUNTIF(INDIRECT("'"&Списки!$AG$2:$AG$17 &"'!A1:A300000"),D32&K32)>0,0))&"'!A:h"),7,0))=0,"",VLOOKUP(D32&K32,INDIRECT("'"&INDEX(Списки!$AG$2:$AG$17,MATCH(TRUE,COUNTIF(INDIRECT("'"&Списки!$AG$2:$AG$17 &"'!A1:A300000"),D32&K32)>0,0))&"'!A:h"),7,0))),"")}
C33: Собственное производство | D33: =IF(ОЛ_НАСОСНАЯ_СТАНЦИЯ!E39=Списки!L$8,IF(J$5>=300,"Труба СК/НПС-К "&K$8&"-0,1-2500","Ручная формовка патрубка"),IF(J$5>=200,"Труба СК/НПС-К "&_xlfn.CEILING.MATH(IF(J$8="",K$8,J$8),50)&"-0,1-2500","Ручная формовка патрубка")) -> Труба СК/НПС-К 500-0,1-2500 | E33: =IF(ОЛ_НАСОСНАЯ_СТАНЦИЯ!E46="Труба стеклокомпозитная","Муфта-2 СК/НПС-К "&J$5&"-1","Стеклокомпозитная гильза Ø"&K$8) -> Стеклокомпозитная гильза Ø500 | F33: {=IF(C33="","",IF(OR(C33=Списки!$AG$15:$AG$17),"нет","да"))} -> нет | J33: =IF(ОЛ_НАСОСНАЯ_СТАНЦИЯ!$E$47="нет",0,IF(J$5>=300,(0.3*$K$5),(PI()*J5/1000*0.005*0.3*1850))*I32) -> 0.6 | K33: =IFERROR(IF(SEARCH("*труба*",D33)=1,"м"),"кг") -> м | L33: =IFERROR(IF(SEARCH("м",K33)=1,"1.00"),"") -> 1.00 | M33: =IFERROR(IF(L33<>"","",VLOOKUP(C33&'Калькулятор КНС'!D33&'Калькулятор КНС'!K33,НН!A:J,10,)),"") | N33: =IFERROR(IF(L33="",M33*J33,J33*L33),0) -> 0 | O33: заполнить стоимость трубы, если формованный патрубок
C34: Собственное производство | D34: Придание изделию товарного вида | F34: {=IF(C34="","",IF(OR(C34=Списки!$AG$15:$AG$17),"нет","да"))} -> нет | I34: =K8/1300*J33 -> 0.23076923 | J34: =IF(ОЛ_НАСОСНАЯ_СТАНЦИЯ!$E$47="нет",0,IF(COUNTIF(D33,"*труба*")=1,K8/1300*J33,0)) -> 0.23076923 | K34: чел. ч | M34: =IFERROR(IF(L34<>"","",VLOOKUP(C34&'Калькулятор КНС'!D34&'Калькулятор КНС'!K34,НН!A:J,10,)),"") -> 1207.8 | N34: =IFERROR(IF(L34="",M34*J34,J34*L34),"") -> 278.72308
C35: Собственное производство | D35: Ручная формовка фланца для задвижки на подводящем трубопроводе | F35: {=IF(C35="","",IF(OR(C35=Списки!$AG$15:$AG$17),"нет","да"))} -> нет | I35: =VLOOKUP(IF(J8="",J5,J8),'Для расчетов'!A36:G61,7,)*I32 -> 9.2 | J35: =IF(ОЛ_НАСОСНАЯ_СТАНЦИЯ!$E$47="нет",0,IF(H35="",I35,H35)) -> 9.2 | K35: кг | M35: =IFERROR(IF(L35<>"","",VLOOKUP(C35&'Калькулятор КНС'!D35&'Калькулятор КНС'!K35,НН!A:J,10,)),"") -> 310.2 | N35: =IFERROR(IF(L35="",M35*J35,J35*L35),"") -> 2853.84
C36: ФОТ | D36: ФОТ | F36: {=IF(C36="","",IF(OR(C36=Списки!$AG$15:$AG$17),"нет","да"))} -> нет | I36: =IF(COUNTIF(D35,"*руч*")=1,1,IF(COUNTIF(D35,"*ламин*")=1,1)) -> 1 | J36: =ROUNDUP(IF(H36="",IFERROR(J35*I36,""),H36),1) -> 9.2 | K36: чел. ч | M36: =IFERROR(IF(L36<>"","",VLOOKUP(C36&'Калькулятор КНС'!D36&'Калькулятор КНС'!K36,НН!A:J,10,)),"") -> 1207.8 | N36: =IFERROR(IF(L36="",M36*J36,J36*L36),"") -> 11111.76
C37: Собственное производство | D37: Ламинирование патрубка к корпусу | F37: {=IF(C37="","",IF(OR(C37=Списки!$AG$15:$AG$17),"нет","да"))} -> нет | I37: =IF(COUNTIF(D35,"*мех*")=1,0.28,IF(COUNTIF(D35,"*ламин*")=1,0.56,1)) -> 1 | J37: =IF(ОЛ_НАСОСНАЯ_СТАНЦИЯ!$E$47="нет",0,IFERROR(IF(SEARCH("*труба*",E33)=1,VLOOKUP(IF(J8="",J5,J8),'Для расчетов'!$A$36:$F$60,4,)*3/10*$K$5),VLOOKUP(IF(J8="",J5,J8),'Для расчетов'!$A$36:$F$60,4,)*$K$5*3/10)) -> 0.33 | K37: кг | M37: =IFERROR(IF(L37<>"","",VLOOKUP(C37&'Калькулятор КНС'!D37&'Калькулятор КНС'!K37,НН!A:J,10,)),"") -> 310.2 | N37: =IFERROR(IF(L37="",M37*J37,J37*L37),"") -> 102.366
C38: ФОТ | D38: ФОТ | F38: {=IF(C38="","",IF(OR(C38=Списки!$AG$15:$AG$17),"нет","да"))} -> нет | I38: =IF(COUNTIF(D37,"*мех*")=1,0.28,IF(COUNTIF(D37,"*ламин*")=1,1)) -> 1 | J38: =ROUNDUP(IF(H38="",IFERROR(J37*I38,""),H38),1) -> 0.4 | K38: чел. ч | M38: =IFERROR(IF(L38<>"","",VLOOKUP(C38&'Калькулятор КНС'!D38&'Калькулятор КНС'!K38,НН!A:J,10,)),"") -> 1207.8 | N38: =IFERROR(IF(L38="",M38*J38,J38*L38),"") -> 483.12
D40: Выходящий патрубок | M40: {=IFERROR(IF(L40<>"","",IF((VLOOKUP(D40&K40,INDIRECT("'"&INDEX(Списки!$AG$2:$AG$17,MATCH(TRUE,COUNTIF(INDIRECT("'"&Списки!$AG$2:$AG$17 &"'!A1:A300000"),D40&K40)>0,0))&"'!A:h"),7,0))=0,"",VLOOKUP(D40&K40,INDIRECT("'"&INDEX(Списки!$AG$2:$AG$17,MATCH(TRUE,COUNTIF(INDIRECT("'"&Списки!$AG$2:$AG$17 &"'!A1:A300000"),D40&K40)>0,0))&"'!A:h"),7,0))),"")}
C41: Собственное производство | D41: =IF(ОЛ_НАСОСНАЯ_СТАНЦИЯ!E40="Труба стеклокомпозитная","Муфта-2 СК/НПС-К "&L$5&"-1",IF(ОЛ_НАСОСНАЯ_СТАНЦИЯ!E40=Списки!L$8,IF(L$5>=300,"Труба СК/НПС-К "&M$8&"-0,1-2500","Ручная формовка патрубка"),IF(L$5>=200,"Труба СК/НПС-К "&_xlfn.CEILING.MATH(IF(L$8="",M$8,L$8),50)&"-0,1-2500","Ручная формовка патрубка"))) -> Ручная формовка патрубка | E41: =IF(ОЛ_НАСОСНАЯ_СТАНЦИЯ!E46="Труба стеклокомпозитная","Муфта-2 СК/НПС-К "&L$5&"-1","Стеклокомпозитная гильза Ø"&M$8) -> Стеклокомпозитная гильза Ø250 | F41: {=IF(C41="","",IF(OR(C41=Списки!$AG$15:$AG$17),"нет","да"))} -> нет | J41: =IFERROR(IF(SEARCH("*гильза*",E41)=1,0.5*$M$5),VLOOKUP(IF(L8="",M8,L8),'Для расчетов'!$A$36:$F$60,4,)*$M$5) -> 1 | K41: =IFERROR(IF(SEARCH("*труба*",D41)=1,"м"),"кг") -> кг | L41: =IFERROR(IF(SEARCH("м",K41)=1,"1,00"),"") | M41: =IFERROR(IF(L41<>"","",VLOOKUP(C41&'Калькулятор КНС'!D41&'Калькулятор КНС'!K41,НН!A:J,10,)),"") -> 310.2 | N41: =IFERROR(IF(L41="",M41*J41,J41*L41),0) -> 310.2
C42: Собственное производство | D42: Придание изделию товарного вида | F42: {=IF(C42="","",IF(OR(C42=Списки!$AG$15:$AG$17),"нет","да"))} -> нет | I42: =M8/1300*J41 -> 0.19230769 | J42: =IF(COUNTIF(D41,"*труба*")=1,M8/1300*J41,0) -> 0 | K42: чел. ч | M42: =IFERROR(IF(L42<>"","",VLOOKUP(C42&'Калькулятор КНС'!D42&'Калькулятор КНС'!K42,НН!A:J,10,)),"") -> 1207.8 | N42: =IFERROR(IF(L42="",M42*J42,J42*L42),"") -> 0
C43: Собственное производство | D43: Ламинирование патрубка к корпусу | F43: {=IF(C43="","",IF(OR(C43=Списки!$AG$15:$AG$17),"нет","да"))} -> нет | J43: =IFERROR(IF(SEARCH("*труба*",E41)=1,VLOOKUP(IF(L8="",M8,L8),'Для расчетов'!$A$36:$F$60,4,)*3/10*$M$5),VLOOKUP(IF(L8="",M8,L8),'Для расчетов'!$A$36:$F$60,4,)*$M$5*3/10) -> 0.36 | K43: кг | M43: =IFERROR(IF(L43<>"","",VLOOKUP(C43&'Калькулятор КНС'!D43&'Калькулятор КНС'!K43,НН!A:J,10,)),"") -> 310.2 | N43: =IFERROR(IF(L43="",M43*J43,J43*L43),"") -> 111.672
C44: ФОТ | D44: ФОТ | F44: {=IF(C44="","",IF(OR(C44=Списки!$AG$15:$AG$17),"нет","да"))} -> нет | I44: =IF(COUNTIF(D43,"*мех*")=1,0.28,IF(COUNTIF(D43,"*ламин*")=1,1)) -> 1 | J44: =ROUNDUP(IF(H44="",IFERROR(J43*I44,""),H44),1) -> 0.4 | K44: чел. ч | M44: =IFERROR(IF(L44<>"","",VLOOKUP(C44&'Калькулятор КНС'!D44&'Калькулятор КНС'!K44,НН!A:J,10,)),"") -> 1207.8 | N44: =IFERROR(IF(L44="",M44*J44,J44*L44),"") -> 483.12
C46: Собственное производство | D46: Ручная формовка гильз для ввода кабелей | E46: 110 | F46: {=IF(C46="","",IF(OR(C46=Списки!$AG$15:$AG$17),"нет","да"))} -> нет | H46: =I48*3 -> 6 | I46: =IF(H46="",0.5,"") | J46: =IF(H46="",I46,H46) -> 6 | K46: кг | M46: =IFERROR(IF(L46<>"","",VLOOKUP(C46&'Калькулятор КНС'!D46&'Калькулятор КНС'!K46,НН!A:J,10,)),"") -> 310.2 | N46: =IFERROR(IF(L46="",M46*J46,J46*L46),"") -> 1861.2
C47: ФОТ | D47: ФОТ | F47: {=IF(C47="","",IF(OR(C47=Списки!$AG$15:$AG$17),"нет","да"))} -> нет | I47: =IF(COUNTIF(D46,"*мех*")=1,0.28,IF(COUNTIF(D46,"*ламин*")=1,0.56,1)) -> 1 | J47: =ROUNDUP(IF(H47="",IFERROR(J46*I47,""),H47),1) -> 6 | K47: чел. ч | M47: =IFERROR(IF(L47<>"","",VLOOKUP(C47&'Калькулятор КНС'!D47&'Калькулятор КНС'!K47,НН!A:J,10,)),"") -> 1207.8 | N47: =IFERROR(IF(L47="",M47*J47,J47*L47),"") -> 7246.8
C48: Прочие материалы | D48: Гермоввод 110 (комплектация 1) | F48: {=IF(C48="","",IF(OR(C48=Списки!$AG$15:$AG$17),"нет","да"))} -> да | I48: 2 | J48: =IF(H48="",I48,H48) -> 2 | K48: шт | M48: =IFERROR(IF(L48<>"","",VLOOKUP(C48&'Калькулятор КНС'!D48&'Калькулятор КНС'!K48,НН!A:J,10,)),"") | N48: =IFERROR(IF(L48="",M48*J48,J48*L48),"")
F49: {=IF(ISBLANK(C49),"",IF(OR(C49=Списки!$AG$15:$AG$17),"нет","да"))} | J49: =IF(ISBLANK(D49),"",IF(H49="",I49,H49)) | M49: =IFERROR(IF(L49<>"","",VLOOKUP(C49&'Калькулятор КНС'!D49&'Калькулятор КНС'!K49,НН!A:J,10,)),"") | N49: =IFERROR(IF(L49="",M49*J49,J49*L49),"")
C50: Да | D50: Фальшпол: | M50: {=IFERROR(IF(L50<>"","",IF((VLOOKUP(D50&K50,INDIRECT("'"&INDEX(Списки!$AG$2:$AG$17,MATCH(TRUE,COUNTIF(INDIRECT("'"&Списки!$AG$2:$AG$17 &"'!A1:A300000"),D50&K50)>0,0))&"'!A:h"),7,0))=0,"",VLOOKUP(D50&K50,INDIRECT("'"&INDEX(Списки!$AG$2:$AG$17,MATCH(TRUE,COUNTIF(INDIRECT("'"&Списки!$AG$2:$AG$17 &"'!A1:A300000"),D50&K50)>0,0))&"'!A:h"),7,0))),"")}
C51: Детали труб_да ПЭ ПВХ PPR | D51: Труба ПВХ Ду160 оранжевая (наружная) | E51: Отверстия для гильз под бетон 2шт | F51: {=IF(C51="","",IF(OR(C51=Списки!$AG$15:$AG$17),"нет","да"))} -> да | I51: 1 | J51: =IF(C50="НЕТ",0,I51) -> 1 | K51: м | M51: =IFERROR(IF(L51<>"","",VLOOKUP(C51&'Калькулятор КНС'!D51&'Калькулятор КНС'!K51,НН!A:J,10,)),"") -> 2901 | N51: =IFERROR(IF(L51="",M51*J51,J51*L51),"") -> 2901
C52: Собственное производство | D52: Механическая формовка деталей фальшпола | F52: {=IF(C52="","",IF($C$50="нет","-",IF(OR(C52=Списки!$AG$15:$AG$17),"нет","да")))} -> нет | H52: 70 | J52: =IF($C$50="нет",0,IF(H52="",I52,H52)) -> 70 | K52: кг | M52: =IFERROR(IF(L52<>"","",VLOOKUP(C52&'Калькулятор КНС'!D52&'Калькулятор КНС'!K52,НН!A:J,10,)),"") -> 214.4 | N52: =IFERROR(IF(L52="",M52*J52,J52*L52),"") -> 15008
C53: ФОТ | D53: ФОТ | F53: {=IF(C53="","",IF($C$50="нет","-",IF(OR(C53=Списки!$AG$15:$AG$17),"нет","да")))} -> нет | I53: =IF(COUNTIF(D52,"*мех*")=1,0.28,IF(COUNTIF(D52,"*ламин*")=1,0.56,1)) -> 0.28 | J53: =ROUNDUP(IF(H53="",IFERROR(J52*I53,""),H53),1) -> 19.6 | K53: чел. ч | M53: =IFERROR(IF(L53<>"","",VLOOKUP(C53&'Калькулятор КНС'!D53&'Калькулятор КНС'!K53,НН!A:J,10,)),"") -> 1207.8 | N53: =IFERROR(IF(L53="",M53*J53,J53*L53),"") -> 23672.88
C54: Собственное производство | D54: Ламинирование фальшпола к корпусу | F54: {=IF(C54="","",IF($C$50="нет","-",IF(OR(C54=Списки!$AG$15:$AG$17),"нет","да")))} -> нет | I54: =IF(H54="",3*J52/10,"") -> 21 | J54: =IF($C$50="нет",0,IF(H54="",I54,H54)) -> 21 | K54: кг | M54: =IFERROR(IF(L54<>"","",VLOOKUP(C54&'Калькулятор КНС'!D54&'Калькулятор КНС'!K54,НН!A:J,10,)),"") -> 310.2 | N54: =IFERROR(IF(L54="",M54*J54,J54*L54),"") -> 6514.2
C55: ФОТ | D55: ФОТ | F55: {=IF(C55="","",IF($C$50="нет","-",IF(OR(C55=Списки!$AG$15:$AG$17),"нет","да")))} -> нет | I55: =IF(COUNTIF(D54,"*мех*")=1,0.28,IF(COUNTIF(D54,"*ламин*")=1,0.56,1)) -> 0.56 | J55: =ROUNDUP(IF(H55="",IFERROR(J54*I55,""),H55),1) -> 11.8 | K55: чел. ч | M55: =IFERROR(IF(L55<>"","",VLOOKUP(C55&'Калькулятор КНС'!D55&'Калькулятор КНС'!K55,НН!A:J,10,)),"") -> 1207.8 | N55: =IFERROR(IF(L55="",M55*J55,J55*L55),"") -> 14252.04
F56: {=IF(ISBLANK(C56),"",IF($C$50="нет","-",IF(OR(C56=Списки!$AG$15:$AG$17),"нет","да")))} | J56: =IF(ISBLANK(D56),"",IF(H56="",I56,H56)) | M56: =IFERROR(IF(L56<>"","",VLOOKUP(C56&'Калькулятор КНС'!D56&'Калькулятор КНС'!K56,НН!A:J,10,)),"") | N56: =IFERROR(IF(L56="",M56*J56,J56*L56),"")
D57: Теплоизоляция: | F57: {=IF(ISBLANK(C57),"",IF(OR(C57=Списки!$AG$15:$AG$17),"нет","да"))} | M57: {=IFERROR(IF(L57<>"","",IF((VLOOKUP(D57&K57,INDIRECT("'"&INDEX(Списки!$AG$2:$AG$17,MATCH(TRUE,COUNTIF(INDIRECT("'"&Списки!$AG$2:$AG$17 &"'!A1:A300000"),D57&K57)>0,0))&"'!A:h"),7,0))=0,"",VLOOKUP(D57&K57,INDIRECT("'"&INDEX(Списки!$AG$2:$AG$17,MATCH(TRUE,COUNTIF(INDIRECT("'"&Списки!$AG$2:$AG$17 &"'!A1:A300000"),D57&K57)>0,0))&"'!A:h"),7,0))),"")} | N57: =IFERROR(IF(L57="",M57*J57,J57*L57),"")
C58: Прочие материалы | D58: Теплоизоляция - Изофом ППЭ ОР 15 1,5х40 | E58: Вертикальная изоляция корпуса | F58: {=IF(ОЛ_НАСОСНАЯ_СТАНЦИЯ!E72="","",IF(OR(ОЛ_НАСОСНАЯ_СТАНЦИЯ!E72=Списки!$AG$15:$AG$17),"нет","да"))} -> да | I58: =_xlfn.CEILING.MATH(PI()*(G5/1000)*(ОЛ_НАСОСНАЯ_СТАНЦИЯ!E73/1000),0.01) -> 18.85 | J58: =IF(ОЛ_НАСОСНАЯ_СТАНЦИЯ!$E$72="нет",0,IF(ISBLANK(D58),"",IF(H58="",I58,H58)))+((((1.5+1.5)*2)+(PI()*(650/1000)))*0.94) -> 26.409513 | K58: м² | M58: =IFERROR(IF(L58<>"","",VLOOKUP(C58&'Калькулятор КНС'!D58&'Калькулятор КНС'!K58,НН!A:J,10,)),"") -> 750 | N58: =IFERROR(IF(L58="",M58*J58,J58*L58),"") -> 19807.135
C59: Прочие материалы | D59: Теплоизоляция - Изофом ППЭ ОР 15 1,5х40 | E59: Изоляция крышки | F59: {=IF(ОЛ_НАСОСНАЯ_СТАНЦИЯ!E72="","",IF(OR(ОЛ_НАСОСНАЯ_СТАНЦИЯ!E72=Списки!$AG$15:$AG$17),"нет","да"))} -> да | I59: =PI()*($G$5/(1000*2))^2 -> 7.0685835 | J59: =IF(ОЛ_НАСОСНАЯ_СТАНЦИЯ!$E$72="нет",0,IF(ISBLANK(D59),"",IF(H59="",I59,H59))) -> 7.0685835 | K59: м² | M59: =IFERROR(IF(L59<>"","",VLOOKUP(C59&'Калькулятор КНС'!D59&'Калькулятор КНС'!K59,НН!A:J,10,)),"") -> 750 | N59: =IFERROR(IF(L59="",M59*J59,J59*L59),"") -> 5301.4376
C60: Собственное производство | D60: Защитный слой ламинации 4 мм на теплоизоляцию | F60: {=IF(ОЛ_НАСОСНАЯ_СТАНЦИЯ!E72="","",IF(OR(ОЛ_НАСОСНАЯ_СТАНЦИЯ!E72=Списки!$AG$15:$AG$17),"нет","да"))} -> да | I60: =(J58+J59)*0.005*1850 -> 309.67239 | J60: =IF(ОЛ_НАСОСНАЯ_СТАНЦИЯ!$E$72="нет",0,IF(ISBLANK(D60),"",IF(H60="",I60,H60))) -> 309.67239 | K60: кг | M60: =IFERROR(IF(L60<>"","",VLOOKUP(C60&'Калькулятор КНС'!D60&'Калькулятор КНС'!K60,НН!A:J,10,)),"") -> 310.2 | N60: =IFERROR(IF(L60="",M60*J60,J60*L60),"") -> 96060.376
C61: ФОТ | D61: ФОТ | F61: {=IF(C61="","",IF($C$50="нет","-",IF(OR(C61=Списки!$AG$15:$AG$17),"нет","да")))} -> нет | I61: =IF(COUNTIF(D60,"*мех*")=1,0.28,IF(COUNTIF(D60,"*ламин*")=1,0.56,1)) -> 0.56 | J61: =ROUNDUP(IF(H61="",IFERROR(J60*I61,""),H61),1) -> 173.5 | K61: чел. ч | M61: =IFERROR(IF(L61<>"","",VLOOKUP(C61&'Калькулятор КНС'!D61&'Калькулятор КНС'!K61,НН!A:J,10,)),"") -> 1207.8 | N61: =IFERROR(IF(L61="",M61*J61,J61*L61),"") -> 209553.3
M62: =IFERROR(IF(L62<>"","",VLOOKUP(C62&'Калькулятор КНС'!D62&'Калькулятор КНС'!K62,НН!A:J,10,)),"")
C63: Да | D63: =IF(G5<2000,"Петли монтажные по чертежу НТТ 648, в т.ч.:","Петли монтажные усиленные по чертежу НТТ 1959, в т.ч.:") -> Петли монтажные усиленные по чертежу НТТ 1959, в т.ч.: | J63: 4 | K63: шт | M63: {=IFERROR(IF(L63<>"","",IF((VLOOKUP(D63&K63,INDIRECT("'"&INDEX(Списки!$AG$2:$AG$17,MATCH(TRUE,COUNTIF(INDIRECT("'"&Списки!$AG$2:$AG$17 &"'!A1:A300000"),D63&K63)>0,0))&"'!A:h"),7,0))=0,"",VLOOKUP(D63&K63,INDIRECT("'"&INDEX(Списки!$AG$2:$AG$17,MATCH(TRUE,COUNTIF(INDIRECT("'"&Списки!$AG$2:$AG$17 &"'!A1:A300000"),D63&K63)>0,0))&"'!A:h"),7,0))),"")}
C64: =IF(D64="","","Метизы") -> Метизы | D64: =_xlfn.IFNA(IF(ОЛ_НАСОСНАЯ_СТАНЦИЯ!$E$20<2000,'Вспомогат. таблицы'!$A$14,'Вспомогат. таблицы'!$A$2),"") -> Болт М24-6ɡх100.21.Ст20 ГОСТ 7798-70 | E64: =IFERROR(IF(SEARCH("*петель*",D64)=1,IF(ОЛ_НАСОСНАЯ_СТАНЦИЯ!$E$20<2000,"Прим. - Петля простая","Прим. - Петля усиленная"),""),"") | F64: {=IF(C64="","",IF(OR(C64=Списки!$AG$15:$AG$17),"нет","да"))} -> да | G64: =IFERROR(3.56*0.14*J64,"") -> 3.9872 | I64: =IFERROR(IF(H64="",IF($G$5>=2000,VLOOKUP(D64,'Вспомогат. таблицы'!$A$2:$B$11,2,),VLOOKUP(D64,'Вспомогат. таблицы'!$A$15:$B$24,2,)),""),"") -> 2 | J64: =IF($C$63="нет",0,IF(C64="","",IFERROR(IF(H64="",I64,H64)*$J$63,""))) -> 8 | K64: =IF(C64="","","шт") -> шт | M64: =IFERROR(IF(L64<>"","",VLOOKUP(C64&'Калькулятор КНС'!D64&'Калькулятор КНС'!K64,НН!A:J,10,)),"") -> 105 | N64: =IFERROR(IF(L64="",M64*J64,J64*L64),"") -> 840
C65: Метизы | D65: =IF(ОЛ_НАСОСНАЯ_СТАНЦИЯ!$E$20<2000,'Вспомогат. таблицы'!$A$15,'Вспомогат. таблицы'!$A$3) -> Шайба 24.21.Ст20 ГОСТ 11371-78 | E65: =IFERROR(IF(SEARCH("*петель*",D65)=1,IF(ОЛ_НАСОСНАЯ_СТАНЦИЯ!$E$20<2000,"Прим. - Петля простая","Прим. - Петля усиленная"),""),"") | F65: {=IF(C65="","",IF(OR(C65=Списки!$AG$15:$AG$17),"нет","да"))} -> да | G65: =32.3*J65/1000 -> 0.2584 | I65: =IF(H65="",IF($G$5>=2000,VLOOKUP(D65,'Вспомогат. таблицы'!$A$2:$B$11,2,),VLOOKUP(D65,'Вспомогат. таблицы'!$A$15:$B$24,2,)),"") -> 2 | J65: =IF($C$63="нет",0,IF(H65="",I65,H65)*$J$63) -> 8 | K65: шт | M65: =IFERROR(IF(L65<>"","",VLOOKUP(C65&'Калькулятор КНС'!D65&'Калькулятор КНС'!K65,НН!A:J,10,)),"") -> 6 | N65: =IFERROR(IF(L65="",M65*J65,J65*L65),"") -> 48
C66: Метизы | D66: =IF(ОЛ_НАСОСНАЯ_СТАНЦИЯ!$E$20<2000,'Вспомогат. таблицы'!$A$16,'Вспомогат. таблицы'!$A$4) -> Шайба 24.30х13 Ст20 ГОСТ 6402-70 | E66: =IFERROR(IF(SEARCH("*петель*",D66)=1,IF(ОЛ_НАСОСНАЯ_СТАНЦИЯ!$E$20<2000,"Прим. - Петля простая","Прим. - Петля усиленная"),""),"") | F66: {=IF(C66="","",IF(OR(C66=Списки!$AG$15:$AG$17),"нет","да"))} -> да | I66: =IF(H66="",IF($G$5>=2000,VLOOKUP(D66,'Вспомогат. таблицы'!$A$2:$B$11,2,),VLOOKUP(D66,'Вспомогат. таблицы'!$A$15:$B$24,2,)),"") -> 2 | J66: =IF($C$63="нет",0,IF(H66="",I66,H66)*$J$63) -> 8 | K66: шт | M66: =IFERROR(IF(L66<>"","",VLOOKUP(C66&'Калькулятор КНС'!D66&'Калькулятор КНС'!K66,НН!A:J,10,)),"") -> 5.91 | N66: =IFERROR(IF(L66="",M66*J66,J66*L66),"") -> 47.28
C67: Метизы | D67: =IF(ОЛ_НАСОСНАЯ_СТАНЦИЯ!$E$20<2000,'Вспомогат. таблицы'!$A$17,'Вспомогат. таблицы'!$A$5) -> Гайка М24-7Н.Ст20 ГОСТ 5915-70 | E67: =IFERROR(IF(SEARCH("*петель*",D67)=1,IF(ОЛ_НАСОСНАЯ_СТАНЦИЯ!$E$20<2000,"Прим. - Петля простая","Прим. - Петля усиленная"),""),"") | F67: {=IF(C67="","",IF(OR(C67=Списки!$AG$15:$AG$17),"нет","да"))} -> да | G67: =27.12*J67/1000 -> 0.21696 | I67: =IF(H67="",IF($G$5>=2000,VLOOKUP(D67,'Вспомогат. таблицы'!$A$2:$B$11,2,),VLOOKUP(D67,'Вспомогат. таблицы'!$A$15:$B$24,2,)),"") -> 2 | J67: =IF($C$63="нет",0,IF(H67="",I67,H67)*$J$63) -> 8 | K67: шт | M67: =IFERROR(IF(L67<>"","",VLOOKUP(C67&'Калькулятор КНС'!D67&'Калькулятор КНС'!K67,НН!A:J,10,)),"") -> 28 | N67: =IFERROR(IF(L67="",M67*J67,J67*L67),"") -> 224
C68: Металлопрокат | D68: =IF(ОЛ_НАСОСНАЯ_СТАНЦИЯ!$E$20<2000,'Вспомогат. таблицы'!$A$18,'Вспомогат. таблицы'!$A$6) -> Лист г/к Б-ПН-О-6,0х1500х3000 ГОСТ 19903-74 // Ст3пс ГОСТ 14637-89 | E68: =IFERROR(IF(SEARCH("*петель*",D68)=1,IF(ОЛ_НАСОСНАЯ_СТАНЦИЯ!$E$20<2000,"Прим. - Петля простая","Прим. - Петля усиленная"),""),"") | F68: {=IF(C68="","",IF(OR(C68=Списки!$AG$15:$AG$17),"нет","да"))} -> да | G68: =107*J68/1000 -> 0.03424 | I68: =IF(H68="",IF($G$5>=2000,VLOOKUP(D68,'Вспомогат. таблицы'!$A$2:$B$11,2,),VLOOKUP(D68,'Вспомогат. таблицы'!$A$15:$B$24,2,)),"") -> 0.08 | J68: =IF($C$63="нет",0,IF(H68="",I68,H68)*$J$63) -> 0.32 | K68: м² | M68: =IFERROR(IF(L68<>"","",VLOOKUP(C68&'Калькулятор КНС'!D68&'Калькулятор КНС'!K68,НН!A:J,10,)),"") -> 5833.33 | N68: =IFERROR(IF(L68="",M68*J68,J68*L68),"") -> 1866.6656
C69: Металлопрокат | D69: =IF(ОЛ_НАСОСНАЯ_СТАНЦИЯ!$E$20<2000,'Вспомогат. таблицы'!$A$19,'Вспомогат. таблицы'!$A$7) -> Лист г/к Б-ПН-О-12,0х1500х3000 ГОСТ 19903-74 // Ст3пс ГОСТ 14637-89 | E69: =IFERROR(IF(SEARCH("*петель*",D69)=1,IF(ОЛ_НАСОСНАЯ_СТАНЦИЯ!$E$20<2000,"Прим. - Петля простая","Прим. - Петля усиленная"),""),"") | F69: {=IF(C69="","",IF(OR(C69=Списки!$AG$15:$AG$17),"нет","да"))} -> да | G69: =J63*0.785 -> 3.14 | I69: =IF(H69="",IF($G$5>=2000,VLOOKUP(D69,'Вспомогат. таблицы'!$A$2:$B$11,2,),VLOOKUP(D69,'Вспомогат. таблицы'!$A$15:$B$24,2,)),"") -> 0.05 | J69: =IF($C$63="нет",0,IF(H69="",I69,H69)*$J$63) -> 0.2 | K69: м² | M69: =IFERROR(IF(L69<>"","",VLOOKUP(C69&'Калькулятор КНС'!D69&'Калькулятор КНС'!K69,НН!A:J,10,)),"") -> 11222.22 | N69: =IFERROR(IF(L69="",M69*J69,J69*L69),"") -> 2244.444
C70: Металлопрокат | D70: =IF(ОЛ_НАСОСНАЯ_СТАНЦИЯ!$E$20<2000,'Вспомогат. таблицы'!$A$20,'Вспомогат. таблицы'!$A$8) -> Арматура 20-А-I Ст3пс ГОСТ 5781-82 гладкая (А240) | E70: =IFERROR(IF(SEARCH("*петель*",D70)=1,IF(ОЛ_НАСОСНАЯ_СТАНЦИЯ!$E$20<2000,"Прим. - Петля простая","Прим. - Петля усиленная"),""),"") | F70: {=IF(C70="","",IF(OR(C70=Списки!$AG$15:$AG$17),"нет","да"))} -> да | G70: =J63*2.26 -> 9.04 | I70: =IF(H70="",IF($G$5>=2000,VLOOKUP(D70,'Вспомогат. таблицы'!$A$2:$B$11,2,),VLOOKUP(D70,'Вспомогат. таблицы'!$A$15:$B$24,2,)),"") -> 0.9 | J70: =IF($C$63="нет",0,IF(H70="",I70,H70)*$J$63) -> 3.6 | K70: м | M70: =IFERROR(IF(L70<>"","",VLOOKUP(C70&'Калькулятор КНС'!D70&'Калькулятор КНС'!K70,НН!A:J,10,)),"") -> 190 | N70: =IFERROR(IF(L70="",M70*J70,J70*L70),"") -> 684
C71: Собственное производство | D71: =IF(ОЛ_НАСОСНАЯ_СТАНЦИЯ!$E$20<2000,'Вспомогат. таблицы'!$A$21,'Вспомогат. таблицы'!$A$9) -> Ламинирование петель к корпусу | E71: =IFERROR(IF(SEARCH("*петель*",D71)=1,IF(ОЛ_НАСОСНАЯ_СТАНЦИЯ!$E$20<2000,"Прим. - Петля простая","Прим. - Петля усиленная"),""),"") -> Прим. - Петля усиленная | F71: {=IF(C71="","",IF(OR(C71=Списки!$AG$15:$AG$17),"нет","да"))} -> нет | I71: =IF(H71="",IF($G$5>=2000,VLOOKUP(D71,'Вспомогат. таблицы'!$A$2:$B$11,2,),VLOOKUP(D71,'Вспомогат. таблицы'!$A$15:$B$24,2,)),"") -> 0.6 | J71: =IF($C$63="нет",0,IF(H71="",I71,H71)*$J$63) -> 2.4 | K71: кг | M71: =IFERROR(IF(L71<>"","",VLOOKUP(C71&'Калькулятор КНС'!D71&'Калькулятор КНС'!K71,НН!A:J,10,)),"") -> 310.2 | N71: =IFERROR(IF(L71="",M71*J71,J71*L71),"") -> 744.48 | O71: Ламинирование 1 простой петли = 0,4 кг, ламинирование 1 усиленной петли =0,6 кг
C72: ФОТ | D72: =IF(ОЛ_НАСОСНАЯ_СТАНЦИЯ!$E$20<2000,'Вспомогат. таблицы'!$A$22,'Вспомогат. таблицы'!$A$10) -> ФОТ | E72: =IFERROR(IF(SEARCH("*петель*",D72)=1,IF(ОЛ_НАСОСНАЯ_СТАНЦИЯ!$E$20<2000,"Прим. - Петля простая","Прим. - Петля усиленная"),""),"") | F72: {=IF(C72="","",IF(OR(C72=Списки!$AG$15:$AG$17),"нет","да"))} -> нет | I72: =IF(COUNTIF(D71,"*мех*")=1,0.28,IF(COUNTIF(D71,"*ламин*")=1,0.56,1)) -> 0.56 | J72: =IF($C$63="нет",0,ROUNDUP(IF(H72="",IFERROR(J71*I72,""),H72),1)) -> 1.4 | K72: чел. ч | M72: =IFERROR(IF(L72<>"","",VLOOKUP(C72&'Калькулятор КНС'!D72&'Калькулятор КНС'!K72,НН!A:J,10,)),"") -> 1207.8 | N72: =IFERROR(IF(L72="",M72*J72,J72*L72),"") -> 1690.92
F73: {=IF(ISBLANK(C73),"",IF(OR(C73=Списки!$AG$15:$AG$17),"нет","да"))} | J73: =IF(ISBLANK(D73),"",IF(H73="",I73,H73)) | M73: =IFERROR(IF(L73<>"","",VLOOKUP(C73&'Калькулятор КНС'!D73&'Калькулятор КНС'!K73,НН!A:J,10,)),"") | N73: =IFERROR(IF(L73="",M73*J73,J73*L73),"")
D74: Дробилка: | F74: {=IF(ISBLANK(C74),"",IF(OR(C74=Списки!$AG$15:$AG$17),"нет","да"))} | M74: {=IFERROR(IF(L74<>"","",IF((VLOOKUP(D74&K74,INDIRECT("'"&INDEX(Списки!$AG$2:$AG$17,MATCH(TRUE,COUNTIF(INDIRECT("'"&Списки!$AG$2:$AG$17 &"'!A1:A300000"),D74&K74)>0,0))&"'!A:h"),7,0))=0,"",VLOOKUP(D74&K74,INDIRECT("'"&INDEX(Списки!$AG$2:$AG$17,MATCH(TRUE,COUNTIF(INDIRECT("'"&Списки!$AG$2:$AG$17 &"'!A1:A300000"),D74&K74)>0,0))&"'!A:h"),7,0))),"")}
C75: Собственное производство | D75: Механическая формовка деталей канала под дробилку | F75: {=IF(C75="","",IF(OR(ОЛ_НАСОСНАЯ_СТАНЦИЯ!$E$46=Списки!$H$2,ОЛ_НАСОСНАЯ_СТАНЦИЯ!$E$46=Списки!$H$5),"-",IF(OR(C75=Списки!$AG$15:$AG$17),"нет","да")))} -> - | H75: 60 | J75: =IF(OR(ОЛ_НАСОСНАЯ_СТАНЦИЯ!$E$46=Списки!$H$2,ОЛ_НАСОСНАЯ_СТАНЦИЯ!$E$46=Списки!$H$5),0,IF(H75="",I75,H75)) -> 0 | K75: кг | M75: =IFERROR(IF(L75<>"","",VLOOKUP(C75&'Калькулятор КНС'!D75&'Калькулятор КНС'!K75,НН!A:J,10,)),"") -> 214.4 | N75: =IFERROR(IF(L75="",M75*J75,J75*L75),"") -> 0
C76: ФОТ | D76: ФОТ | F76: {=IF(C76="","",IF(OR(ОЛ_НАСОСНАЯ_СТАНЦИЯ!$E$46=Списки!$H$2,ОЛ_НАСОСНАЯ_СТАНЦИЯ!$E$46=Списки!$H$5),"-",IF(OR(C76=Списки!$AG$15:$AG$17),"нет","да")))} -> - | I76: =IF(COUNTIF(D75,"*мех*")=1,0.28,IF(COUNTIF(D75,"*ламин*")=1,0.56,1)) -> 0.28 | J76: =ROUNDUP(IF(H76="",IFERROR(J75*I76,""),H76),1) -> 0 | K76: чел. ч | M76: =IFERROR(IF(L76<>"","",VLOOKUP(C76&'Калькулятор КНС'!D76&'Калькулятор КНС'!K76,НН!A:J,10,)),"") -> 1207.8 | N76: =IFERROR(IF(L76="",M76*J76,J76*L76),"") -> 0
C77: Собственное производство | D77: Ламинирование деталей площадки под дробилку в сборке | F77: {=IF(C77="","",IF(OR(ОЛ_НАСОСНАЯ_СТАНЦИЯ!$E$46=Списки!$H$2,ОЛ_НАСОСНАЯ_СТАНЦИЯ!$E$46=Списки!$H$5),"-",IF(OR(C77=Списки!$AG$15:$AG$17),"нет","да")))} -> - | I77: =IF(H77="",IFERROR(IF(H75="",I75,H75)*3/10,""),"") -> 18 | J77: =IF(OR(ОЛ_НАСОСНАЯ_СТАНЦИЯ!$E$46=Списки!$H$2,ОЛ_НАСОСНАЯ_СТАНЦИЯ!$E$46=Списки!$H$5),0,IF(H77="",I77,H77)) -> 0 | K77: кг | M77: =IFERROR(IF(L77<>"","",VLOOKUP(C77&'Калькулятор КНС'!D77&'Калькулятор КНС'!K77,НН!A:J,10,)),"") -> 310.2 | N77: =IFERROR(IF(L77="",M77*J77,J77*L77),"") -> 0
C78: ФОТ | D78: ФОТ | F78: {=IF(C78="","",IF(OR(ОЛ_НАСОСНАЯ_СТАНЦИЯ!$E$46=Списки!$H$2,ОЛ_НАСОСНАЯ_СТАНЦИЯ!$E$46=Списки!$H$5),"-",IF(OR(C78=Списки!$AG$15:$AG$17),"нет","да")))} -> - | I78: =IF(COUNTIF(D77,"*мех*")=1,0.28,IF(COUNTIF(D77,"*ламин*")=1,IF(D77="Ламинирование деталей площадки под дробилку в сборке",1,0.56),1)) -> 1 | J78: =ROUNDUP(IF(H78="",IFERROR(J77*I78,""),H78),1) -> 0 | K78: чел. ч | M78: =IFERROR(IF(L78<>"","",VLOOKUP(C78&'Калькулятор КНС'!D78&'Калькулятор КНС'!K78,НН!A:J,10,)),"") -> 1207.8 | N78: =IFERROR(IF(L78="",M78*J78,J78*L78),"") -> 0 | O78: Коэффициент ламинации 1
C79: Металлопрокат | D79: Уголок 50х50х5мм 12Х18Н10Т (AISI304) ГОСТ 8509-93 | F79: {=IF(C79="","",IF(OR(ОЛ_НАСОСНАЯ_СТАНЦИЯ!$E$46=Списки!$H$2,ОЛ_НАСОСНАЯ_СТАНЦИЯ!$E$46=Списки!$H$5),"-",IF(OR(C79=Списки!$AG$15:$AG$17),"нет","да")))} -> - | I79: =IF(H79="",ROUNDUP(2*(ОЛ_НАСОСНАЯ_СТАНЦИЯ!E41/1000),),"") -> 20 | J79: =IF(OR(ОЛ_НАСОСНАЯ_СТАНЦИЯ!$E$46=Списки!$H$2,ОЛ_НАСОСНАЯ_СТАНЦИЯ!$E$46=Списки!$H$5),0,IF(ISBLANK(D79),"",IF(H79="",I79,H79))) -> 0 | K79: м | M79: =IFERROR(IF(L79<>"","",VLOOKUP(C79&'Калькулятор КНС'!D79&'Калькулятор КНС'!K79,НН!A:J,10,)),"") -> 1500 | N79: =IFERROR(IF(L79="",M79*J79,J79*L79),"") -> 0
C80: Металлопрокат | D80: Труба 60х30х2мм 12Х18Н10Т ГОСТ 8639-82 | F80: {=IF(C80="","",IF(OR(ОЛ_НАСОСНАЯ_СТАНЦИЯ!$E$46=Списки!$H$2,ОЛ_НАСОСНАЯ_СТАНЦИЯ!$E$46=Списки!$H$5),"-",IF(OR(C80=Списки!$AG$15:$AG$17),"нет","да")))} -> - | H80: 11 | I80: =IF(H80="",ROUNDUP(2*(ОЛ_НАСОСНАЯ_СТАНЦИЯ!E42/1000),),"") | J80: =IF(OR(ОЛ_НАСОСНАЯ_СТАНЦИЯ!$E$46=Списки!$H$2,ОЛ_НАСОСНАЯ_СТАНЦИЯ!$E$46=Списки!$H$5),0,IF(ISBLANK(D80),"",IF(H80="",I80,H80))) -> 0 | K80: м | L80: 2000 | M80: =IFERROR(IF(L80<>"","",VLOOKUP(C80&'Калькулятор КНС'!D80&'Калькулятор КНС'!K80,НН!A:J,10,)),"") | N80: =IFERROR(IF(L80="",M80*J80,J80*L80),"") -> 0
C81: Грузоподъем | D81: Кольцо сварное полированное АРТ 8229 А4 10Х60 | F81: {=IF(C81="","",IF(OR(ОЛ_НАСОСНАЯ_СТАНЦИЯ!$E$46=Списки!$H$2,ОЛ_НАСОСНАЯ_СТАНЦИЯ!$E$46=Списки!$H$5),"-",IF(OR(C81=Списки!$AG$15:$AG$17),"нет","да")))} -> - | I81: =I82 -> 11 | J81: =IF(OR(ОЛ_НАСОСНАЯ_СТАНЦИЯ!$E$46=Списки!$H$2,ОЛ_НАСОСНАЯ_СТАНЦИЯ!$E$46=Списки!$H$5),0,IF(ISBLANK(D81),"",IF(H81="",I81,H81))) -> 0 | K81: шт | M81: =IFERROR(IF(L81<>"","",VLOOKUP(C81&'Калькулятор КНС'!D81&'Калькулятор КНС'!K81,НН!A:J,10,)),"") -> 600 | N81: =IFERROR(IF(L81="",M81*J81,J81*L81),"") -> 0
C82: Грузоподъем | D82: Цепь короткозвенная сварная 5 мм DIN 766 А2/А4 | E82: ="Для подъема и спуска дробилки L= "&ROUNDUP((ОЛ_НАСОСНАЯ_СТАНЦИЯ!E41/1000+1),0)&" м" -> Для подъема и спуска дробилки L= 11 м | F82: {=IF(C82="","",IF(OR(ОЛ_НАСОСНАЯ_СТАНЦИЯ!$E$46=Списки!$H$2,ОЛ_НАСОСНАЯ_СТАНЦИЯ!$E$46=Списки!$H$5),"-",IF(OR(C82=Списки!$AG$15:$AG$17),"нет","да")))} -> - | I82: =IF(H82="",ROUNDUP((ОЛ_НАСОСНАЯ_СТАНЦИЯ!E41/1000+1),),"") -> 11 | J82: =IF(OR(ОЛ_НАСОСНАЯ_СТАНЦИЯ!$E$46=Списки!$H$2,ОЛ_НАСОСНАЯ_СТАНЦИЯ!$E$46=Списки!$H$5),0,IF(ISBLANK(D82),"",IF(H82="",I82,H82))) -> 0 | K82: м | M82: =IFERROR(IF(L82<>"","",VLOOKUP(C82&'Калькулятор КНС'!D82&'Калькулятор КНС'!K82,НН!A:J,10,)),"") -> 450 | N82: =IFERROR(IF(L82="",M82*J82,J82*L82),"") -> 0
C83: Грузоподъем | D83: Карабин винтовой 5 мм нерж. А4 ART 8253 | F83: {=IF(C83="","",IF(OR(ОЛ_НАСОСНАЯ_СТАНЦИЯ!$E$46=Списки!$H$2,ОЛ_НАСОСНАЯ_СТАНЦИЯ!$E$46=Списки!$H$5),"-",IF(OR(C83=Списки!$AG$15:$AG$17),"нет","да")))} -> - | I83: =IF(H83="",ROUNDUP(I82,),"") -> 11 | J83: =IF(OR(ОЛ_НАСОСНАЯ_СТАНЦИЯ!$E$46=Списки!$H$2,ОЛ_НАСОСНАЯ_СТАНЦИЯ!$E$46=Списки!$H$5),0,IF(ISBLANK(D83),"",IF(H83="",I83,H83))) -> 0 | K83: шт | M83: =IFERROR(IF(L83<>"","",VLOOKUP(C83&'Калькулятор КНС'!D83&'Калькулятор КНС'!K83,НН!A:J,10,)),"") -> 320 | N83: =IFERROR(IF(L83="",M83*J83,J83*L83),"") -> 0
M84: {=IFERROR(IF(L84<>"","",IF((VLOOKUP(D84&K84,INDIRECT("'"&INDEX(Списки!$AG$2:$AG$17,MATCH(TRUE,COUNTIF(INDIRECT("'"&Списки!$AG$2:$AG$17 &"'!A1:A300000"),D84&K84)>0,0))&"'!A:h"),7,0))=0,"",VLOOKUP(D84&K84,INDIRECT("'"&INDEX(Списки!$AG$2:$AG$17,MATCH(TRUE,COUNTIF(INDIRECT("'"&Списки!$AG$2:$AG$17 &"'!A1:A300000"),D84&K84)>0,0))&"'!A:h"),7,0))),"")}
B85: 1.2 | D85: Корпус КНС Работы (ФОТ) | M85: {=IFERROR(IF(L85<>"","",IF((VLOOKUP(D85&K85,INDIRECT("'"&INDEX(Списки!$AG$2:$AG$17,MATCH(TRUE,COUNTIF(INDIRECT("'"&Списки!$AG$2:$AG$17 &"'!A1:A300000"),D85&K85)>0,0))&"'!A:h"),7,0))=0,"",VLOOKUP(D85&K85,INDIRECT("'"&INDEX(Списки!$AG$2:$AG$17,MATCH(TRUE,COUNTIF(INDIRECT("'"&Списки!$AG$2:$AG$17 &"'!A1:A300000"),D85&K85)>0,0))&"'!A:h"),7,0))),"")}
C86: Собственное производство | D86: Предварительные работы для подготовки трубы (транспортировка, разметка осей, шлифовка) | E86: =IFERROR(IF(SEARCH("*петель*",D86)=1,IF(ОЛ_НАСОСНАЯ_СТАНЦИЯ!E20<2000,"Прим. - Петли простые","Прим. - Петли усиленные")),IFERROR(IF(SEARCH("*под гильзу вход*",D86)=1,$E$27),IFERROR(IF(SEARCH("*под гильзу напор*",D86)=1,#REF!),IFERROR(IF(SEARCH("*трубы*",D86)=1,D$14),"")))) -> Труба СК/НПС-К 3000-0,1-10000 | F86: {=IF(C86="","",IF(OR(C86=Списки!$AG$15:$AG$17),"нет","да"))} -> нет | I86: =($G$5/(200*6))*J14 -> 28.75 | J86: =ROUNDUP(IF(H86="",I86,H86),1) -> 28.8 | K86: чел. ч | M86: =IFERROR(IF(L86<>"","",VLOOKUP(C86&'Калькулятор КНС'!D86&'Калькулятор КНС'!K86,НН!A:J,10,)),"") -> 1207.8 | N86: =IFERROR(IF(L86="",M86*J86,J86*L86),"") -> 34784.64 | O86: DN/(200*6) * Lтр
C87: Собственное производство | D87: Прорезка отверстия под гильзу входящего патрубка | E87: =E27 -> Стеклокомпозитная гильза Ø500 | F87: {=IF(C87="","",IF(OR(C87=Списки!$AG$15:$AG$17),"нет","да"))} -> нет | I87: =(K8*3.14*0.5*K5)/1000 -> 0.785 | J87: =ROUNDUP(IF(H87="",I87,H87),1) -> 0.8 | K87: чел. ч | M87: =IFERROR(IF(L87<>"","",VLOOKUP(C87&'Калькулятор КНС'!D87&'Калькулятор КНС'!K87,НН!A:J,10,)),"") -> 1207.8 | N87: =IFERROR(IF(L87="",M87*J87,J87*L87),"") -> 966.24 | O87: прорезка любого отверстия: (DN* П/1000)*0,5*количество патрубков - вырезать 1 м окружности занимает 0,5 чел.ч.
C88: Собственное производство | D88: Прорезка отверстия под гильзу напорного патрубка (ов) | E88: =E41 -> Стеклокомпозитная гильза Ø250 | F88: {=IF(C88="","",IF(OR(C88=Списки!$AG$15:$AG$17),"нет","да"))} -> нет | I88: =(M8*3.14*0.5*M5)/1000 -> 0.785 | J88: =ROUNDUP(IF(H88="",I88,H88),1) -> 0.8 | K88: чел. ч | M88: =IFERROR(IF(L88<>"","",VLOOKUP(C88&'Калькулятор КНС'!D88&'Калькулятор КНС'!K88,НН!A:J,10,)),"") -> 1207.8 | N88: =IFERROR(IF(L88="",M88*J88,J88*L88),"") -> 966.24 | O88: прорезка любого отверстия: (DN* П/1000)*0,5*количество патрубков - вырезать 1 м окружности занимает 0,5 чел.ч.
C89: Собственное производство | D89: Прорезка отверстия под гильзу ввода кабелей | E89: 100 | F89: {=IF(C89="","",IF(OR(C89=Списки!$AG$15:$AG$17),"нет","да"))} -> нет | I89: =(E89*3.14*0.5)/1000 -> 0.157 | J89: =ROUNDUP(IF(H89="",I89,H89),1) -> 0.2 | K89: чел. ч | M89: =IFERROR(IF(L89<>"","",VLOOKUP(C89&'Калькулятор КНС'!D89&'Калькулятор КНС'!K89,НН!A:J,10,)),"") -> 1207.8 | N89: =IFERROR(IF(L89="",M89*J89,J89*L89),"") -> 241.56 | O89: 8 шт
C90: Собственное производство | D90: Изготовление Петель монтажных | F90: {=IF(C90="","",IF(OR(C90=Списки!$AG$15:$AG$17),"нет","да"))} -> нет | I90: =ROUNDUP(0.5*J63,) -> 2 | J90: =IF(C63="нет",0,ROUNDUP(IF(H90="",I90,H90),1)) -> 2 | K90: чел. ч | M90: =IFERROR(IF(L90<>"","",VLOOKUP(C90&'Калькулятор КНС'!D90&'Калькулятор КНС'!K90,НН!A:J,10,)),"") -> 1207.8 | N90: =IFERROR(IF(L90="",M90*J90,J90*L90),"") -> 2415.6 | O90: 0,5 чел. За 1 петлю
C91: Собственное производство | D91: Монтаж Петель монтажных | F91: {=IF(C91="","",IF(OR(C91=Списки!$AG$15:$AG$17),"нет","да"))} -> нет | I91: =ROUNDUP(0.5*J63,) -> 2 | J91: =IF(C63="нет",0,ROUNDUP(IF(H91="",I91,H91),1)) -> 2 | K91: чел. ч | M91: =IFERROR(IF(L91<>"","",VLOOKUP(C91&'Калькулятор КНС'!D91&'Калькулятор КНС'!K91,НН!A:J,10,)),"") -> 1207.8 | N91: =IFERROR(IF(L91="",M91*J91,J91*L91),"") -> 2415.6 | O91: 0,5 чел. За 1 петлю
C92: Собственное производство | D92: Монтаж теплоизоляции | F92: {=IF(C92="","",IF(OR(C92=Списки!$AG$15:$AG$17),"нет","да"))} -> нет | I92: =J58*1+J59*1 -> 33.478097 | J92: =ROUNDUP(IF(ОЛ_НАСОСНАЯ_СТАНЦИЯ!E72="нет",0,IF(H92="",I92,H92)),1) -> 33.5 | K92: чел. ч | M92: =IFERROR(IF(L92<>"","",VLOOKUP(C92&'Калькулятор КНС'!D92&'Калькулятор КНС'!K92,НН!A:J,10,)),"") -> 1207.8 | N92: =IFERROR(IF(L92="",M92*J92,J92*L92),"") -> 40461.3 | O92: 1 м2 = 1 чел.ч для вертикальной части корпуса, 1 м2 = 1 чел.ч для изоляции крышки
C93: Собственное производство | D93: Монтаж направляющих дробилки | F93: {=IF(C93="","",IF(OR(C93=Списки!$AG$15:$AG$17),"нет","да"))} -> нет | I93: 2 | J93: =ROUNDUP(IF(OR(ОЛ_НАСОСНАЯ_СТАНЦИЯ!$E$46=Списки!$H$2,ОЛ_НАСОСНАЯ_СТАНЦИЯ!$E$46=Списки!$H$5),0,IF(H93="",I93,H93)),1) -> 0 | K93: чел. ч | M93: =IFERROR(IF(L93<>"","",VLOOKUP(C93&'Калькулятор КНС'!D93&'Калькулятор КНС'!K93,НН!A:J,10,)),"") -> 1207.8 | N93: =IFERROR(IF(L93="",M93*J93,J93*L93),"") -> 0 | O93: обычно у дробилки 2 направляющие, за 2 шт. - 2 чел.ч.
D94: Последняя строка | M94: {=IFERROR(IF(L94<>"","",IF((VLOOKUP(D94&K94,INDIRECT("'"&INDEX(Списки!$AG$2:$AG$17,MATCH(TRUE,COUNTIF(INDIRECT("'"&Списки!$AG$2:$AG$17 &"'!A1:A300000"),D94&K94)>0,0))&"'!A:h"),7,0))=0,"",VLOOKUP(D94&K94,INDIRECT("'"&INDEX(Списки!$AG$2:$AG$17,MATCH(TRUE,COUNTIF(INDIRECT("'"&Списки!$AG$2:$AG$17 &"'!A1:A300000"),D94&K94)>0,0))&"'!A:h"),7,0))),"")}
E95: Итого: Корпус | G95: =SUM(G14:G94) -> 11173.977 | M95: {=IFERROR(IF(L95<>"","",IF((VLOOKUP(D95&K95,INDIRECT("'"&INDEX(Списки!$AG$2:$AG$17,MATCH(TRUE,COUNTIF(INDIRECT("'"&Списки!$AG$2:$AG$17 &"'!A1:A300000"),D95&K95)>0,0))&"'!A:h"),7,0))=0,"",VLOOKUP(D95&K95,INDIRECT("'"&INDEX(Списки!$AG$2:$AG$17,MATCH(TRUE,COUNTIF(INDIRECT("'"&Списки!$AG$2:$AG$17 &"'!A1:A300000"),D95&K95)>0,0))&"'!A:h"),7,0))),"")} | N95: =IF($E$14=Списки!$AI$3,SUM($N$16:$N$94),SUM($N$14:$N$94)) -> 764920.63
E96: в т.ч. Материалы на закупку: | M96: {=IFERROR(IF(L96<>"","",IF((VLOOKUP(D96&K96,INDIRECT("'"&INDEX(Списки!$AG$2:$AG$17,MATCH(TRUE,COUNTIF(INDIRECT("'"&Списки!$AG$2:$AG$17 &"'!A1:A300000"),D96&K96)>0,0))&"'!A:h"),7,0))=0,"",VLOOKUP(D96&K96,INDIRECT("'"&INDEX(Списки!$AG$2:$AG$17,MATCH(TRUE,COUNTIF(INDIRECT("'"&Списки!$AG$2:$AG$17 &"'!A1:A300000"),D96&K96)>0,0))&"'!A:h"),7,0))),"")} | N96: {=SUM(SUMIF($C$16:$C$94,Списки!$AG$2:$AG$14,$N$16:$N$94))} -> 33963.962
E97: в т.ч. Труба, муфта: | M97: {=IFERROR(IF(L97<>"","",IF((VLOOKUP(D97&K97,INDIRECT("'"&INDEX(Списки!$AG$2:$AG$17,MATCH(TRUE,COUNTIF(INDIRECT("'"&Списки!$AG$2:$AG$17 &"'!A1:A300000"),D97&K97)>0,0))&"'!A:h"),7,0))=0,"",VLOOKUP(D97&K97,INDIRECT("'"&INDEX(Списки!$AG$2:$AG$17,MATCH(TRUE,COUNTIF(INDIRECT("'"&Списки!$AG$2:$AG$17 &"'!A1:A300000"),D97&K97)>0,0))&"'!A:h"),7,0))),"")} | N97: =IF($E$14=Списки!$AI$3,SUMIFS(N16:N85,D16:D85,"муфта*",F16:F85,"нет")+SUMIFS(N16:N85,D16:D85,"Труба*",F16:F85,"нет"),N14+SUMIFS(N16:N85,D16:D85,"муфта*",F16:F85,"нет")+SUMIFS(N16:N85,D16:D85,"Труба*",F16:F85,"нет"))+SUMIFS(N16:N85,E16:E85,"муфта*",F16:F85,"нет") -> 12 | P97: необходимо указать стоимость трубы/муфты
E98: в т.ч. Работы участка фитингов, ФОТ: | J98: =ROUNDUP(SUMIFS($J$14:$J$94,$K$14:$K$94,Списки!$S$5)-SUMIFS($J$14:$J$94,$K$14:$K$94,Списки!$S$5,$D$14:$D$94,"*изготов*"),1) -> 433.9 | K98: чел. ч | M98: {=IFERROR(IF(L98<>"","",IF((VLOOKUP(D98&K98,INDIRECT("'"&INDEX(Списки!$AG$2:$AG$17,MATCH(TRUE,COUNTIF(INDIRECT("'"&Списки!$AG$2:$AG$17 &"'!A1:A300000"),D98&K98)>0,0))&"'!A:h"),7,0))=0,"",VLOOKUP(D98&K98,INDIRECT("'"&INDEX(Списки!$AG$2:$AG$17,MATCH(TRUE,COUNTIF(INDIRECT("'"&Списки!$AG$2:$AG$17 &"'!A1:A300000"),D98&K98)>0,0))&"'!A:h"),7,0))),"")} | N98: =SUMIF($K$14:$K$94,Списки!$S$5,$N$14:$N$94)-SUMIFS($N$14:$N$94,$K$14:$K$94,Списки!$S$5,$D$14:$D$94,"*изготов*") -> 523971.51
E99: в т.ч. Работы участка РМУ, ФОТ: | J99: =ROUNDUP(SUMIFS($J$14:$J$94,$K$14:$K$94,Списки!$S$5,$D$14:$D$94,"*изготов*"),1) -> 2 | K99: чел. ч | N99: =SUMIFS($N$14:$N$94,$K$14:$K$94,Списки!$S$5,$D$14:$D$94,"*изготов*") -> 2415.6
E100: в т.ч. Формовка: | J100: =SUMIFS($J$14:$J$94,$K$14:$K$94,Списки!$S$4) -> 762.23125 | K100: кг | M100: {=IF(D100="ФОТ",I100*#REF!,IFERROR(IF(L100<>"","",IF((VLOOKUP(D100&K100,INDIRECT("'"&INDEX(Списки!$AG$2:$AG$17,MATCH(TRUE,COUNTIF(INDIRECT("'"&Списки!$AG$2:$AG$17 &"'!A1:A300000"),D100&K100)>0,0))&"'!A:h"),7,0))=0,"",VLOOKUP(D100&K100,INDIRECT("'"&INDEX(Списки!$AG$2:$AG$17,MATCH(TRUE,COUNTIF(INDIRECT("'"&Списки!$AG$2:$AG$17 &"'!A1:A300000"),D100&K100)>0,0))&"'!A:h"),7,0))),""))} | N100: =SUMIF($K$16:$K$94,Списки!$S$4,$N$16:$N$94) -> 204557.56
D101: Корзина Материалы: | F101: {=IF(ISBLANK(C101),"",IF(OR(C101=Списки!$AG$15:$AG$17),"нет","да"))} | M101: {=IF(D101="ФОТ",I101*#REF!,IFERROR(IF(L101<>"","",IF((VLOOKUP(D101&K101,INDIRECT("'"&INDEX(Списки!$AG$2:$AG$17,MATCH(TRUE,COUNTIF(INDIRECT("'"&Списки!$AG$2:$AG$17 &"'!A1:A300000"),D101&K101)>0,0))&"'!A:h"),7,0))=0,"",VLOOKUP(D101&K101,INDIRECT("'"&INDEX(Списки!$AG$2:$AG$17,MATCH(TRUE,COUNTIF(INDIRECT("'"&Списки!$AG$2:$AG$17 &"'!A1:A300000"),D101&K101)>0,0))&"'!A:h"),7,0))),""))}
D102: Количество корзин | J102: 1 | K102: шт | M102: {=IFERROR(IF(L102<>"","",IF((VLOOKUP(D102&K102,INDIRECT("'"&INDEX(Списки!$AG$2:$AG$17,MATCH(TRUE,COUNTIF(INDIRECT("'"&Списки!$AG$2:$AG$17 &"'!A1:A300000"),D102&K102)>0,0))&"'!A:h"),7,0))=0,"",VLOOKUP(D102&K102,INDIRECT("'"&INDEX(Списки!$AG$2:$AG$17,MATCH(TRUE,COUNTIF(INDIRECT("'"&Списки!$AG$2:$AG$17 &"'!A1:A300000"),D102&K102)>0,0))&"'!A:h"),7,0))),"")}
C103: Металлопрокат | D103: Уголок 20х20х1,5мм 08Х18Н10Т(AISI304) ГОСТ 8509-93 | F103: {=IF(C103="","",IF(OR(C103=Списки!$AG$15:$AG$17),"нет","да"))} -> да | G103: =0.68*J103 -> 6.8 | I103: 10 | J103: =IF(OR(ОЛ_НАСОСНАЯ_СТАНЦИЯ!$E$46=Списки!$H$3,ОЛ_НАСОСНАЯ_СТАНЦИЯ!$E$46=Списки!$H$5),0,IF(H103="",I103,H103))*J102 -> 10 | K103: м | M103: =IFERROR(IF(L103<>"","",VLOOKUP(C103&'Калькулятор КНС'!D103&'Калькулятор КНС'!K103,НН!A:J,10,)),"") -> 850 | N103: =IFERROR(IF(L103="",M103*J103,J103*L103),"") -> 8500
C104: Металлопрокат | D104: Лист нержавеющий перфорированный 1х1000х2000мм Qg 10.0-12.0 марка 10х18н10 | F104: {=IF(C104="","",IF(OR(C104=Списки!$AG$15:$AG$17),"нет","да"))} -> да | I104: =IF(H104="",2,"") -> 2 | J104: =IF(OR(ОЛ_НАСОСНАЯ_СТАНЦИЯ!$E$46=Списки!$H$3,ОЛ_НАСОСНАЯ_СТАНЦИЯ!$E$46=Списки!$H$5),0,IF(H104="",I104,H104))*J102 -> 2 | K104: м² | M104: =IFERROR(IF(L104<>"","",VLOOKUP(C104&'Калькулятор КНС'!D104&'Калькулятор КНС'!K104,НН!A:J,10,)),"") -> 8750 | N104: =IFERROR(IF(L104="",M104*J104,J104*L104),"") -> 17500
C105: Металлопрокат | D105: Труба 45х3,0 ГОСТ 9941-81 ст 12Х18Н10Т (AISI 321) (бесшовная холоднодеформированная) ГОСТ 9941-81 | E105: =IFERROR(IF(SEARCH("*направляющ*",D105)=1,"2 шт. длиной "&IF(I105="",#REF!,I105)&"м"),"") | F105: {=IF(C105="","",IF(OR(C105=Списки!$AG$15:$AG$17),"нет","да"))} -> да | G105: =3.11*J105 -> 62.2 | I105: =IF(ОЛ_НАСОСНАЯ_СТАНЦИЯ!$E$46=Списки!$H$2,IF(H105="",ROUNDUP(2*(ОЛ_НАСОСНАЯ_СТАНЦИЯ!E41/1000),),"")) -> 20 | J105: =IF(OR(ОЛ_НАСОСНАЯ_СТАНЦИЯ!$E$46=Списки!$H$3,ОЛ_НАСОСНАЯ_СТАНЦИЯ!$E$46=Списки!$H$5),0,IF(H105="",I105,H105))*J102 -> 20 | K105: м | M105: =IFERROR(IF(L105<>"","",VLOOKUP(C105&'Калькулятор КНС'!D105&'Калькулятор КНС'!K105,НН!A:J,10,)),"") -> 3900 | N105: =IFERROR(IF(L105="",M105*J105,J105*L105),"") -> 78000
...

Sheet Заявка
B1: ОБЩЕСТВО С ОГРАНИЧЕННОЙ ОТВЕТСТВЕННОСТЬЮ «НОВЫЕ ТРУБНЫЕ ТЕХНОЛОГИИ» 141320, Московская область, г.о. Сергиево-Посадский, д. Коврово, д. 50, помещ. 2 E-mail: info@ntt.su, тел/факс: +7(499) 949-14-04
B3: Дата составления: | C3: 21 июля 2020 год | F3: Составил: | G3: Изюмова И.В.
A5: Заявка на приобретение изм.1 (для ДЗЛ) Для комплектации КНС 3000х8800 по заявке №627/1-з необходимо приобрести:
A6: № | B6: Категория | C6: Наименование | D6: ЕИ | E6: Кол-во | F6: Бюджет. цена, руб/ед. | G6: Бюджет. ст-ть, руб | H6: Дата закупки | I6: Отметка об исполнении
I7: Кол-во | J7: Дата
A9: =IF(C9="","",A8+1) | B9: =IFERROR(INDEX('Калькулятор КНС'!C:D,MATCH(C9,'Калькулятор КНС'!D:D,),1),"") | C9: {=IFERROR(INDEX('[5]Список для заявки'!$A$2:$A$400,SMALL(IF('[5]Список для заявки'!$A$2:$A$400<>"",ROW('[5]Список для заявки'!$A$2:$A$400)-1),ROW('[5]Список для заявки'!A1))),"")} | D9: =IFERROR(VLOOKUP(C9,'Калькулятор КНС'!D:K,8,),"") | E9: =IFERROR(VLOOKUP(C9,'Калькулятор КНС'!D:K,7,),"") | F9: =IFERROR(IF(VLOOKUP(C9,'Калькулятор КНС'!D:N,9,)="",VLOOKUP(C9,'Калькулятор КНС'!D:N,10,),VLOOKUP(C9,'Калькулятор КНС'!D:N,9,)),"") | G9: =IFERROR(VLOOKUP(C9,'Калькулятор КНС'!D:N,11,),"")
A10: =IF(C10="","",A9+1) | B10: =IFERROR(INDEX('Калькулятор КНС'!C:D,MATCH(C10,'Калькулятор КНС'!D:D,),1),"") | C10: {=IFERROR(INDEX(#REF!,SMALL(IF(#REF!<>"",ROW(#REF!)-1),ROW(#REF!))),"")} | D10: =IFERROR(VLOOKUP(C10,'Калькулятор КНС'!D:K,8,),"") | E10: =IFERROR(VLOOKUP(C10,'Калькулятор КНС'!D:K,7,),"") | F10: =IFERROR(IF(VLOOKUP(C10,'Калькулятор КНС'!D:N,9,)="",VLOOKUP(C10,'Калькулятор КНС'!D:N,10,),VLOOKUP(C10,'Калькулятор КНС'!D:N,9,)),"") | G10: =IFERROR(VLOOKUP(C10,'Калькулятор КНС'!D:N,11,),"")
A11: =IF(C11="","",A10+1) | B11: =IFERROR(INDEX('Калькулятор КНС'!C:D,MATCH(C11,'Калькулятор КНС'!D:D,),1),"") | C11: {=IFERROR(INDEX(#REF!,SMALL(IF(#REF!<>"",ROW(#REF!)-1),ROW(#REF!))),"")} | D11: =IFERROR(VLOOKUP(C11,'Калькулятор КНС'!D:K,8,),"") | E11: =IFERROR(VLOOKUP(C11,'Калькулятор КНС'!D:K,7,),"") | F11: =IFERROR(IF(VLOOKUP(C11,'Калькулятор КНС'!D:N,9,)="",VLOOKUP(C11,'Калькулятор КНС'!D:N,10,),VLOOKUP(C11,'Калькулятор КНС'!D:N,9,)),"") | G11: =IFERROR(VLOOKUP(C11,'Калькулятор КНС'!D:N,11,),"")
A12: =IF(C12="","",A11+1) | B12: =IFERROR(INDEX('Калькулятор КНС'!C:D,MATCH(C12,'Калькулятор КНС'!D:D,),1),"") | C12: {=IFERROR(INDEX(#REF!,SMALL(IF(#REF!<>"",ROW(#REF!)-1),ROW(#REF!))),"")} | D12: =IFERROR(VLOOKUP(C12,'Калькулятор КНС'!D:K,8,),"") | E12: =IFERROR(VLOOKUP(C12,'Калькулятор КНС'!D:K,7,),"") | F12: =IFERROR(IF(VLOOKUP(C12,'Калькулятор КНС'!D:N,9,)="",VLOOKUP(C12,'Калькулятор КНС'!D:N,10,),VLOOKUP(C12,'Калькулятор КНС'!D:N,9,)),"") | G12: =IFERROR(VLOOKUP(C12,'Калькулятор КНС'!D:N,11,),"")
A13: =IF(C13="","",A12+1) | B13: =IFERROR(INDEX('Калькулятор КНС'!C:D,MATCH(C13,'Калькулятор КНС'!D:D,),1),"") | C13: {=IFERROR(INDEX(#REF!,SMALL(IF(#REF!<>"",ROW(#REF!)-1),ROW(#REF!))),"")} | D13: =IFERROR(VLOOKUP(C13,'Калькулятор КНС'!D:K,8,),"") | E13: =IFERROR(VLOOKUP(C13,'Калькулятор КНС'!D:K,7,),"") | F13: =IFERROR(IF(VLOOKUP(C13,'Калькулятор КНС'!D:N,9,)="",VLOOKUP(C13,'Калькулятор КНС'!D:N,10,),VLOOKUP(C13,'Калькулятор КНС'!D:N,9,)),"") | G13: =IFERROR(VLOOKUP(C13,'Калькулятор КНС'!D:N,11,),"")
A14: =IF(C14="","",A13+1) | B14: =IFERROR(INDEX('Калькулятор КНС'!C:D,MATCH(C14,'Калькулятор КНС'!D:D,),1),"") | C14: {=IFERROR(INDEX(#REF!,SMALL(IF(#REF!<>"",ROW(#REF!)-1),ROW(#REF!))),"")} | D14: =IFERROR(VLOOKUP(C14,'Калькулятор КНС'!D:K,8,),"") | E14: =IFERROR(VLOOKUP(C14,'Калькулятор КНС'!D:K,7,),"") | F14: =IFERROR(IF(VLOOKUP(C14,'Калькулятор КНС'!D:N,9,)="",VLOOKUP(C14,'Калькулятор КНС'!D:N,10,),VLOOKUP(C14,'Калькулятор КНС'!D:N,9,)),"") | G14: =IFERROR(VLOOKUP(C14,'Калькулятор КНС'!D:N,11,),"")
A15: =IF(C15="","",A14+1) | B15: =IFERROR(INDEX('Калькулятор КНС'!C:D,MATCH(C15,'Калькулятор КНС'!D:D,),1),"") | C15: {=IFERROR(INDEX(#REF!,SMALL(IF(#REF!<>"",ROW(#REF!)-1),ROW(#REF!))),"")} | D15: =IFERROR(VLOOKUP(C15,'Калькулятор КНС'!D:K,8,),"") | E15: =IFERROR(VLOOKUP(C15,'Калькулятор КНС'!D:K,7,),"") | F15: =IFERROR(IF(VLOOKUP(C15,'Калькулятор КНС'!D:N,9,)="",VLOOKUP(C15,'Калькулятор КНС'!D:N,10,),VLOOKUP(C15,'Калькулятор КНС'!D:N,9,)),"") | G15: =IFERROR(VLOOKUP(C15,'Калькулятор КНС'!D:N,11,),"")
A16: =IF(C16="","",A15+1) | B16: =IFERROR(INDEX('Калькулятор КНС'!C:D,MATCH(C16,'Калькулятор КНС'!D:D,),1),"") | C16: {=IFERROR(INDEX(#REF!,SMALL(IF(#REF!<>"",ROW(#REF!)-1),ROW(#REF!))),"")} | D16: =IFERROR(VLOOKUP(C16,'Калькулятор КНС'!D:K,8,),"") | E16: =IFERROR(VLOOKUP(C16,'Калькулятор КНС'!D:K,7,),"") | F16: =IFERROR(IF(VLOOKUP(C16,'Калькулятор КНС'!D:N,9,)="",VLOOKUP(C16,'Калькулятор КНС'!D:N,10,),VLOOKUP(C16,'Калькулятор КНС'!D:N,9,)),"") | G16: =IFERROR(VLOOKUP(C16,'Калькулятор КНС'!D:N,11,),"")
A17: =IF(C17="","",A16+1) | B17: =IFERROR(INDEX('Калькулятор КНС'!C:D,MATCH(C17,'Калькулятор КНС'!D:D,),1),"") | C17: {=IFERROR(INDEX(#REF!,SMALL(IF(#REF!<>"",ROW(#REF!)-1),ROW(#REF!))),"")} | D17: =IFERROR(VLOOKUP(C17,'Калькулятор КНС'!D:K,8,),"") | E17: =IFERROR(VLOOKUP(C17,'Калькулятор КНС'!D:K,7,),"") | F17: =IFERROR(IF(VLOOKUP(C17,'Калькулятор КНС'!D:N,9,)="",VLOOKUP(C17,'Калькулятор КНС'!D:N,10,),VLOOKUP(C17,'Калькулятор КНС'!D:N,9,)),"") | G17: =IFERROR(VLOOKUP(C17,'Калькулятор КНС'!D:N,11,),"")
A18: =IF(C18="","",A17+1) | B18: =IFERROR(INDEX('Калькулятор КНС'!C:D,MATCH(C18,'Калькулятор КНС'!D:D,),1),"") | C18: {=IFERROR(INDEX(#REF!,SMALL(IF(#REF!<>"",ROW(#REF!)-1),ROW(#REF!))),"")} | D18: =IFERROR(VLOOKUP(C18,'Калькулятор КНС'!D:K,8,),"") | E18: =IFERROR(VLOOKUP(C18,'Калькулятор КНС'!D:K,7,),"") | F18: =IFERROR(IF(VLOOKUP(C18,'Калькулятор КНС'!D:N,9,)="",VLOOKUP(C18,'Калькулятор КНС'!D:N,10,),VLOOKUP(C18,'Калькулятор КНС'!D:N,9,)),"") | G18: =IFERROR(VLOOKUP(C18,'Калькулятор КНС'!D:N,11,),"")
A19: =IF(C19="","",A18+1) | B19: =IFERROR(INDEX('Калькулятор КНС'!C:D,MATCH(C19,'Калькулятор КНС'!D:D,),1),"") | C19: {=IFERROR(INDEX(#REF!,SMALL(IF(#REF!<>"",ROW(#REF!)-1),ROW(#REF!))),"")} | D19: =IFERROR(VLOOKUP(C19,'Калькулятор КНС'!D:K,8,),"") | E19: =IFERROR(VLOOKUP(C19,'Калькулятор КНС'!D:K,7,),"") | F19: =IFERROR(IF(VLOOKUP(C19,'Калькулятор КНС'!D:N,9,)="",VLOOKUP(C19,'Калькулятор КНС'!D:N,10,),VLOOKUP(C19,'Калькулятор КНС'!D:N,9,)),"") | G19: =IFERROR(VLOOKUP(C19,'Калькулятор КНС'!D:N,11,),"")
A20: =IF(C20="","",A19+1) | B20: =IFERROR(INDEX('Калькулятор КНС'!C:D,MATCH(C20,'Калькулятор КНС'!D:D,),1),"") | C20: {=IFERROR(INDEX(#REF!,SMALL(IF(#REF!<>"",ROW(#REF!)-1),ROW(#REF!))),"")} | D20: =IFERROR(VLOOKUP(C20,'Калькулятор КНС'!D:K,8,),"") | E20: =IFERROR(VLOOKUP(C20,'Калькулятор КНС'!D:K,7,),"") | F20: =IFERROR(IF(VLOOKUP(C20,'Калькулятор КНС'!D:N,9,)="",VLOOKUP(C20,'Калькулятор КНС'!D:N,10,),VLOOKUP(C20,'Калькулятор КНС'!D:N,9,)),"") | G20: =IFERROR(VLOOKUP(C20,'Калькулятор КНС'!D:N,11,),"")
A21: =IF(C21="","",A20+1) | B21: =IFERROR(INDEX('Калькулятор КНС'!C:D,MATCH(C21,'Калькулятор КНС'!D:D,),1),"") | C21: {=IFERROR(INDEX(#REF!,SMALL(IF(#REF!<>"",ROW(#REF!)-1),ROW(#REF!))),"")} | D21: =IFERROR(VLOOKUP(C21,'Калькулятор КНС'!D:K,8,),"") | E21: =IFERROR(VLOOKUP(C21,'Калькулятор КНС'!D:K,7,),"") | F21: =IFERROR(IF(VLOOKUP(C21,'Калькулятор КНС'!D:N,9,)="",VLOOKUP(C21,'Калькулятор КНС'!D:N,10,),VLOOKUP(C21,'Калькулятор КНС'!D:N,9,)),"") | G21: =IFERROR(VLOOKUP(C21,'Калькулятор КНС'!D:N,11,),"")
... A136: =IF(C136="","",A135+1) | B136: =IFERROR(INDEX('Калькулятор КНС'!C:D,MATCH(C136,'Калькулятор КНС'!D:D,),1),"") | C136: {=IFERROR(INDEX(#REF!,SMALL(IF(#REF!<>"",ROW(#REF!)-1),ROW(#REF!))),"")} | D136: =IFERROR(VLOOKUP(C136,'Калькулятор КНС'!D:K,8,),"") | E136: =IFERROR(VLOOKUP(C136,'Калькулятор КНС'!D:K,7,),"") | F136: =IFERROR(IF(VLOOKUP(C136,'Калькулятор КНС'!D:N,9,)="",VLOOKUP(C136,'Калькулятор КНС'!D:N,10,),VLOOKUP(C136,'Калькулятор КНС'!D:N,9,)),"") | G136: =IFERROR(VLOOKUP(C136,'Калькулятор КНС'!D:N,11,),"")
C138: Итого: | F138: =SUM(F9:F136) -> 0 | G138: =SUM(G9:G136) -> 0
C140: Эксперт Конструкторско-технологического отдела Департамента инжиниринга | I140: Изюмова И.В.
C142: Директор департамента инжиниринга | I142: Буханцов Ю.В.
C144: Директор производства | I144: Никифоров Д.Н.
C146: Директор Департамента по закупкам и логистике | I146: Марченкова Н.В.

Sheet Вспомогат. таблицы
A1: Для усиленной петли | B1: кол-во, шт
A2: Болт М24-6ɡх100.21.Ст20 ГОСТ 7798-70 | B2: =8/4 -> 2
A3: Шайба 24.21.Ст20 ГОСТ 11371-78 | B3: =8/4 -> 2
A4: Шайба 24.30х13 Ст20 ГОСТ 6402-70 | B4: =8/4 -> 2
A5: Гайка М24-7Н.Ст20 ГОСТ 5915-70 | B5: =8/4 -> 2
A6: Лист г/к Б-ПН-О-6,0х1500х3000 ГОСТ 19903-74 // Ст3пс ГОСТ 14637-89 | B6: =(2*2*0.03+0.2)/4 -> 0.08
A7: Лист г/к Б-ПН-О-12,0х1500х3000 ГОСТ 19903-74 // Ст3пс ГОСТ 14637-89 | B7: =(2*0.1)/4 -> 0.05
A8: Арматура 20-А-I Ст3пс ГОСТ 5781-82 гладкая (А240) | B8: =(2*1.8)/4 -> 0.9
A9: Ламинирование петель к корпусу | B9: 0.6
A10: ФОТ
A13: Для простой петли
A14: #N/A
A15: Болт М12-6gх50.58.12Х18Н10Т ГОСТ 7798-70 (DIN 931, DIN 933) | B15: 2
A16: Гайка M12-7H.5.016.Ст20 ГОСТ 5915-70 | B16: 2
A17: Шайба 12.65Г.029.Ст20 ГОСТ 6402-70 | B17: 2
A18: Лист г/к Б-ПН-О-3,0х1500х3000 ГОСТ 19903-74 // Ст3пс ГОСТ 16523-97 | B18: 0.004
A19: Лист г/к Б-ПН-О-6,0х1500х3000 ГОСТ 19903-74 // Ст3пс ГОСТ 14637-89 | B19: 0.006
A20: Арматура 10-А-I Ст3пс ГОСТ 5781-82 гладкая (А240) | B20: 0.4
A21: Ламинирование петель к корпусу | B21: 0.4
A22: ФОТ

Sheet Цветовая библиотека
C2: 12
C3: 119
C4: 110
C6: 89
C7: 89
C8: 89
C10: 90
C11: 68
C12: 89
C14: 244
C15: 240
C16: 235

Sheet Гидравл. расчет
D1: Приложение 1
A2: Гидравлический расчет (работа на 1 нитку)
A3: Q | C3: м3/сут | F3: производительность КНС
A4: Q | B4: =D4/1000 -> 0.02236 | C4: м3/с | D4: =ОЛ_НАСОСНАЯ_СТАНЦИЯ!E51/3.6 -> 22.36 | E4: л/с
A5: Нпл.земл | B5: 162.1 | C5: м | F5: отметка планировки земли в месте установки
A6: Hввод | B6: 152.19 | C6: м | F6: отметка подводящего трубопровода на вводе в КНС
A7: Нвывод | B7: 159.8 | C7: м | F7: отметка напорного трубопровода на выводе из КНС
A8: Нмин. ур.воды | B8: 151.34 | C8: м | D8: =ОЛ_НАСОСНАЯ_СТАНЦИЯ!N48 -> 0.76 | F8: отметка минимального уровня воды в КНС
A9: Hдикт. точка | B9: 159.84 | C9: м | F9: диктующая точка точка
A10: d | B10: =0.159-(2*0.0045)-0.001 -> 0.149 | C10: м | F10: внутренний диаметр напорного трубопровода в КНС
A11: l | B11: 10 | C11: м | F11: длина напорного трубопровода в КНС
A12: D | B12: =0.16-(2*0.0095) -> 0.141 | C12: м | F12: внутренний диаметр напорного трубопровода вне КНС
A13: L | B13: 7.6 | C13: м | F13: длина напорного трубопровода вне КНС
A15: Требуемый напор
A16: Hрасч = Hгеод + ∑ Hпот + Hизл
A17: Геометрический напор | F17: Скорости потоков в трубопроводах
A18: Hгеом | B18: =B9-B8 -> 8.5 | C18: м | F18: Vкнс | G18: =4*B4/(PI()*(B10^2)) -> 1.2823583 | H18: м/с | I18: скорость течения жидкости в напорном трубопроводе КНС
A19: Свободный напор на излив | F19: V | G19: =4*B4/(PI()*(B12^2)) -> 1.4320022 | H19: м/с | I19: скорость течения жидкости в напорном трубопроводе вне КНС
A20: Hизл | B20: 1 | C20: м
A22: При перекачке стоков по полиэтиленовым трубам ПЭ100+ SDR17 Ø160х9,5 мм потери напора на 1 м длины - 1000i= 14,309 (https://vik.by/instruments/shevelev-online)
A23: ∑ Hпот = ∆h + hпот + hнс
A24: ∆h – потери по длине
A25: ∆h= 1000i*к*L | B25: =0.109 -> 0.109 | C25: м
A26: Потери на трение в напорном трубопроводе при скорости > 1,2 м/с
A27: hнс | B27: 3 | C27: м
A28: hпот | B28: =B25*0.15 -> 0.01635 | C28: м
A29: ∑ Hпот | B29: =B25+B27+B28 -> 3.12535 | C29: м
A31: Требуемый напор
A32: Hтр | B32: =B18+B29+B20 -> 12.62535 | C32: м
A33: Сопротивление системы
A34: S | B34: =(B32-B18)/(D4^2) -> 0.0082512017 | C34: с2*м/л2
A35: График системы
A36: Q, л/с | B36: H,м | C36: Hполн, м | D36: Qв1, л/с | E36: Qв2, л/с | G36: Нг
A37: 0 | B37: =$B$34*(A37^2) -> 0 | C37: =B37+$B$18 -> 8.5 | D37: =A37 -> 0 | E37: =A37*2 -> 0 | G37: =$B$18 -> 8.5
A38: =ROUNDUP($A$46*0.3,) -> 9 | B38: =$B$34*(A38^2) -> 0.66834734 | C38: =B38+$B$18 -> 9.1683473 | D38: =A38 -> 9 | E38: =A38*2 -> 18 | G38: =$B$18 -> 8.5
A39: =ROUNDUP($A$46*0.4,) -> 11 | B39: =$B$34*(A39^2) -> 0.9983954 | C39: =B39+$B$18 -> 9.4983954 | D39: =A39 -> 11 | E39: =A39*2 -> 22 | G39: =$B$18 -> 8.5
A40: =ROUNDUP($A$46*0.5,) -> 14 | B40: =$B$34*(A40^2) -> 1.6172355 | C40: =B40+$B$18 -> 10.117236 | D40: =A40 -> 14 | E40: =A40*2 -> 28 | G40: =$B$18 -> 8.5
A41: =ROUNDUP($A$46*0.6,) -> 17 | B41: =$B$34*(A41^2) -> 2.3845973 | C41: =B41+$B$18 -> 10.884597 | D41: =A41 -> 17 | E41: =A41*2 -> 34 | G41: =$B$18 -> 8.5
A42: =ROUNDUP($A$46*0.7,) -> 19 | B42: =$B$34*(A42^2) -> 2.9786838 | C42: =B42+$B$18 -> 11.478684 | D42: =A42 -> 19 | E42: =A42*2 -> 38 | G42: =$B$18 -> 8.5
A43: =ROUNDUP($A$46*0.8,) -> 22 | B43: =$B$34*(A43^2) -> 3.9935816 | C43: =B43+$B$18 -> 12.493582 | D43: =A43 -> 22 | E43: =A43*2 -> 44 | G43: =$B$18 -> 8.5
A44: =D4 -> 22.36 | B44: =$B$34*(A44^2) -> 4.12535 | C44: =B44+$B$18 -> 12.62535 | D44: =A44 -> 22.36 | E44: =A44*2 -> 44.72 | G44: =$B$18 -> 8.5
A45: =ROUNDUP($A$46*(1-0.1),) -> 25 | B45: =$B$34*(A45^2) -> 5.157001 | C45: =B45+$B$18 -> 13.657001 | D45: =A45 -> 25 | E45: =A45*2 -> 50 | G45: =$B$18 -> 8.5
A46: =ROUNDUP(D4*1.2,) -> 27 | B46: =$B$34*(A46^2) -> 6.015126 | C46: =B46+$B$18 -> 14.515126 | D46: =A46 -> 27 | E46: =A46*2 -> 54 | G46: =$B$18 -> 8.5
A49: График насоса
A50: Q, л/с | B50: H,м | C50: Qн1,л/с | D50: Qн2,л/с
A51: =0/3.6 -> 0 | B51: 22.5 | C51: =A51 -> 0 | D51: =C51*2 -> 0
A52: =A63/3.6 -> 2.7777778 | B52: 20.5 | C52: =A52 -> 2.7777778 | D52: =C52*2 -> 5.5555556
A53: =A64/3.6 -> 5.5555556 | B53: 18.5 | C53: =A53 -> 5.5555556 | D53: =C53*2 -> 11.111111
A54: =A65/3.6 -> 8.3333333 | B54: 15.2 | C54: =A54 -> 8.3333333 | D54: =C54*2 -> 16.666667
A55: =A66/3.6 -> 8.5222222 | B55: 14.89 | C55: =A55 -> 8.5222222 | D55: =C55*2 -> 17.044444
A56: =A67/3.6 -> 11.111111 | B56: 9 | C56: =A56 -> 11.111111 | D56: =C56*2 -> 22.222222
A57: =A68/3.6 -> 13.888889 | B57: 8.5 | C57: =A57 -> 13.888889 | D57: =C57*2 -> 27.777778
A58: =A69/3.6 -> 16.666667 | B58: 6 | C58: =A58 -> 16.666667 | D58: =C58*2 -> 33.333333
A62: 0
A63: 10
A64: 20
A65: 30
A66: 30.68
A67: 40
A68: 50
A69: 60

Sheet Для расчетов
A1: к содержанию
A2: Dу | C2: 1000 | D2: 1000-b | E2: 1200 | F2: 1200-b | G2: 1400 | H2: 1400-b | I2: 1500 | J2: 1500-b | K2: 1600 | L2: 1600-b | M2: 1800 | N2: 1800-b | O2: 1900 | P2: 1900-b | Q2: 2000 | R2: 2000-b | S2: 2200 | T2: 2200-b | U2: 2400 | V2: 2400-b | W2: 2500 | X2: 2500-b | Y2: 2600 | Z2: 2600-b | AA2: 2700 | AB2: 2700-b | AC2: 3000 | AD2: 3000-b
C3: (Dн1192) | E3: (Dн1390) | G3: (Dн 1588) | I3: (Dн 1639) | K3: (Dн 1786) | M3: (Dн 1984) | O3: (Dн 2047) | Q3: (Dн 2183) | S3: (Dн 2381) | U3: (Dн 2578) | W3: (Dн 2578) | Y3: (Dн 2658) | AA3: (Dн 2758) | AC3: (Dн 3064)
A4: L(м) | C4: кг | D4: мм | E4: кг | F4: мм | G4: кг | H4: мм | I4: кг | J4: мм | K4: кг | L4: мм | M4: кг | N4: мм | O4: кг | P4: мм | Q4: кг | R4: мм | S4: кг | T4: мм | U4: кг | V4: мм | W4: кг | X4: мм | Y4: кг | Z4: мм | AA4: кг | AB4: мм | AC4: кг | AD4: мм
A5: До 3м | B5: 3000 | C5: 18 | D5: 9 | E5: 28 | F5: 10 | G5: 41 | H5: 11 | I5: 46 | J5: 12 | K5: 59 | L5: 13 | M5: 80 | N5: 14 | O5: 92 | P5: 15 | Q5: 106 | R5: 15 | S5: 138 | T5: 17 | U5: 174 | V5: 18 | W5: 180 | X5: 19 | Y5: 198 | Z5: 19 | AA5: 221 | AB5: 20 | AC5: 300 | AD5: 22
A6: До3,5 | B6: 3500 | C6: 19 | D6: 9 | E6: 30 | F6: 11 | G6: 44 | H6: 12 | I6: 50 | J6: 13 | K6: 63 | L6: 14 | M6: 86 | N6: 15 | O6: 110 | P6: 16 | Q6: 113 | R6: 16 | S6: 147 | T6: 18 | U6: 186 | V6: 19 | W6: 193 | X6: 20 | Y6: 212 | Z6: 21 | AA6: 236 | AB6: 21 | AC6: 327 | AD6: 24
A7: До 4 м | B7: 4000 | C7: 20 | D7: 10 | E7: 31 | F7: 11 | G7: 47 | H7: 13 | I7: 53 | J7: 14 | K7: 66 | L7: 14 | M7: 90 | N7: 16 | O7: 104 | P7: 17 | Q7: 120 | R7: 17 | S7: 156 | T7: 19 | U7: 197 | V7: 20 | W7: 205 | X7: 21 | Y7: 226 | Z7: 22 | AA7: 251 | AB7: 23 | AC7: 341 | AD7: 25
A8: До 4,5 | B8: 4500 | C8: 21 | D8: 10 | E8: 33 | F8: 12 | G8: 49 | H8: 13 | I8: 55 | J8: 14 | K8: 70 | L8: 15 | M8: 95 | N8: 17 | O8: 110 | P8: 18 | Q8: 127 | R8: 18 | S8: 164 | T8: 20 | U8: 209 | V8: 22 | W8: 216 | X8: 22 | Y8: 238 | Z8: 23 | AA8: 265 | AB8: 24 | AC8: 361 | AD8: 27
A9: До 5 м | B9: 5000 | C9: 22 | D9: 11 | E9: 34 | F9: 12 | G9: 51 | H9: 14 | I9: 58 | J9: 15 | K9: 73 | L9: 16 | M9: 100 | N9: 18 | O9: 116 | P9: 19 | Q9: 133 | R9: 19 | S9: 172 | T9: 21 | U9: 218 | V9: 23 | W9: 227 | X9: 24 | Y9: 249 | Z9: 24 | AA9: 278 | AB9: 25 | AC9: 379 | AD9: 28
A10: До 5,5 | B10: 5500 | C10: 23 | D10: 11 | E10: 36 | F10: 13 | G10: 53 | H10: 15 | I10: 60 | J10: 16 | K10: 76 | L10: 16 | M10: 104 | N10: 18 | O10: 118 | P10: 19 | Q10: 138 | R10: 20 | S10: 180 | T10: 22 | U10: 228 | V10: 24 | W10: 237 | X10: 25 | Y10: 261 | Z10: 25 | AA10: 291 | AB10: 26 | AC10: 396 | AD10: 29
A11: До 6 м | B11: 6000 | C11: 24 | D11: 11 | E11: 37 | F11: 13 | G11: 56 | H11: 15 | I11: 63 | J11: 16 | K11: 79 | L11: 17 | M11: 108 | N11: 19 | O11: 122 | P11: 20 | Q11: 144 | R11: 21 | S11: 187 | T11: 23 | U11: 238 | V11: 25 | W11: 246 | X11: 26 | Y11: 272 | Z11: 27 | AA11: 303 | AB11: 27 | AC11: 412 | AD11: 30
A12: До 6,5 | B12: 6500 | C12: 25 | D12: 12 | E12: 39 | F12: 14 | G12: 57 | H12: 16 | I12: 65 | J12: 17 | K12: 82 | L12: 18 | M12: 112 | N12: 20 | O12: 128 | P12: 21 | Q12: 149 | R12: 22 | S12: 194 | T12: 24 | U12: 246 | V12: 26 | W12: 256 | X12: 27 | Y12: 282 | Z12: 28 | AA12: 315 | AB12: 29 | AC12: 428 | AD12: 31
A13: До 7 м | B13: 7000 | C13: 26 | D13: 12 | E13: 40 | F13: 14 | G13: 60 | H13: 16 | I13: 68 | J13: 17 | K13: 85 | L13: 18 | M13: 117 | N13: 21 | O13: 134 | P13: 22 | Q13: 155 | R13: 22 | S13: 201 | T13: 24 | U13: 255 | V13: 26 | W13: 266 | X13: 28 | Y13: 291 | Z13: 28 | AA13: 337 | AB13: 31 | AC13: 447 | AD13: 33
A14: До 12 | B14: 12000 | C14: 28 | D14: 13 | E14: 45 | F14: 16 | G14: 68 | H14: 19 | I14: 78 | J14: 20 | K14: 99 | L14: 21 | M14: 136 | N14: 24 | O14: 159 | P14: 26 | Q14: 184 | R14: 27 | S14: 241 | T14: 29 | U14: 307 | V14: 32 | W14: 321 | X14: 33 | Y14: 355 | Z14: 35 | AA14: 398 | AB14: 36 | AC14: 546 | AD14: 40
A18: Формовка эллиптических днищ
A20: Dн | C20: 1000 | D20: 1000-b | E20: 1200 | F20: 1200-b | G20: 1400 | H20: 1400-b | I20: 1500 | J20: 1500-b | K20: 1600 | L20: 1600-b | M20: 1800 | N20: 1800-b | O20: 1900 | P20: 1900-b | Q20: 2000 | R20: 2000-b | S20: 2200 | T20: 2200-b | U20: 2400 | V20: 2400-b | W20: 2500 | X20: 2500-b | Y20: 2600 | Z20: 2600-b | AA20: 2700 | AB20: 2700-b | AC20: 3000 | AD20: 3000-b
A21: L(м) | C21: (Dн1192) | E21: (Dн1390) | G21: (Dн 1588) | I21: (Dн 1639) | K21: (Dн 1786) | M21: (Dн 1984) | O21: (Dн 2047) | Q21: (Dн 2183) | S21: (Dн 2381) | U21: (Dн 2578) | W21: (Dн 2578) | Y21: (Dн 2658) | AA21: (Dн 2758) | AC21: (Dн 3064)
A22: До 3м | B22: 3000 | C22: 20 | D22: 7 | E22: 25 | F22: 8 | G22: 32 | H22: 9 | I22: 46 | J22: 10 | K22: 54 | L22: 10 | M22: 80 | N22: 11 | O22: 94 | P22: 12 | Q22: 107 | R22: 13 | S22: 140 | T22: 14 | U22: 175 | V22: 15 | W22: 197 | X22: 15 | Y22: 227 | Z22: 16 | AA22: 243 | AB22: 16 | AC22: 311 | AD22: 18
A23: До 3,5 | B23: 3500 | C23: 22 | D23: 8 | E23: 26 | F23: 9 | G23: 34 | H23: 10 | I23: 49 | J23: 11 | K23: 58 | L23: 11 | M23: 86 | N23: 12 | O23: 102 | P23: 13 | Q23: 114 | R23: 13 | S23: 149 | T23: 14 | U23: 187 | V23: 16 | W23: 210 | X23: 16 | Y23: 243 | Z23: 17 | AA23: 260 | AB23: 17 | AC23: 333 | AD23: 19
A24: До 4 м | B24: 4000 | C24: 23 | D24: 8 | E24: 28 | F24: 9 | G24: 36 | H24: 11 | I24: 52 | J24: 11 | K24: 61 | L24: 12 | M24: 91 | N24: 13 | O24: 105 | P24: 13 | Q24: 121 | R24: 14 | S24: 158 | T24: 15 | U24: 199 | V24: 17 | W24: 223 | X24: 17 | Y24: 258 | Z24: 18 | AA24: 276 | AB24: 18 | AC24: 353 | AD24: 20
A25: До 4,5 | B25: 4500 | C25: 24 | D25: 8 | E25: 29 | F25: 10 | G25: 37 | H25: 11 | I25: 55 | J25: 12 | K25: 64 | L25: 12 | M25: 95 | N25: 14 | O25: 110 | P25: 14 | Q25: 127 | R25: 15 | S25: 166 | T25: 16 | U25: 209 | V25: 17 | W25: 235 | X25: 18 | Y25: 272 | Z25: 19 | AA25: 291 | AB25: 19 | AC25: 373 | AD25: 21
A26: До 5 м | B26: 5000 | C26: 25 | D26: 9 | E26: 30 | F26: 10 | G26: 39 | H26: 12 | I26: 57 | J26: 12 | K26: 67 | L26: 13 | M26: 100 | N26: 14 | O26: 118 | P26: 15 | Q26: 133 | R26: 16 | S26: 174 | T26: 17 | U26: 219 | V26: 18 | W26: 246 | X26: 19 | Y26: 285 | Z26: 20 | AA26: 305 | AB26: 20 | AC26: 391 | AD26: 22
A27: До 5,5 | B27: 5500 | C27: 26 | D27: 9 | E27: 32 | F27: 11 | G27: 41 | H27: 12 | I27: 60 | J27: 13 | K27: 70 | L27: 13 | M27: 104 | N27: 15 | O27: 126 | P27: 16 | Q27: 139 | R27: 16 | S27: 182 | T27: 18 | U27: 229 | V27: 19 | W27: 257 | X27: 20 | Y27: 297 | Z27: 21 | AA27: 318 | AB27: 21 | AC27: 408 | AD27: 23
A28: До 6м | B28: 6000 | C28: 26 | D28: 9 | E28: 33 | F28: 11 | G28: 42 | H28: 12 | I28: 62 | J28: 13 | K28: 72 | L28: 14 | M28: 108 | N28: 15 | O28: 130 | P28: 16 | Q28: 144 | R28: 17 | S28: 189 | T28: 18 | U28: 238 | V28: 20 | W28: 267 | X28: 21 | Y28: 309 | Z28: 21 | AA28: 331 | AB28: 22 | AC28: 425 | AD28: 24
A29: До 6,5 | B29: 6500 | C29: 27 | D29: 10 | E29: 34 | F29: 11 | G29: 44 | H29: 13 | I29: 64 | J29: 14 | K29: 75 | L29: 14 | M29: 112 | N29: 16 | O29: 134 | P29: 17 | Q29: 149 | R29: 17 | S29: 196 | T29: 19 | U29: 247 | V29: 21 | W29: 277 | X29: 21 | Y29: 321 | Z29: 22 | AA29: 343 | AB29: 23 | AC29: 441 | AD29: 25
A30: До 7 м | B30: 7000 | C30: 28 | D30: 10 | E30: 35 | F30: 12 | G30: 45 | H30: 13 | I30: 66 | J30: 14 | K30: 77 | L30: 15 | M30: 115 | N30: 16 | O30: 140 | P30: 17 | Q30: 154 | R30: 18 | S30: 202 | T30: 20 | U30: 255 | V30: 21 | W30: 287 | X30: 22 | Y30: 332 | Z30: 23 | AA30: 355 | AB30: 24 | AC30: 456 | AD30: 26
A31: До 12 | B31: 12000 | C31: 35 | D31: 13 | E31: 44 | F31: 15 | G31: 57 | H31: 17 | I31: 84 | J31: 18 | K31: 98 | L31: 19 | M31: 147 | N31: 21 | O31: 173 | P31: 22 | Q31: 196 | R31: 23 | S31: 259 | T31: 25 | U31: 327 | V31: 27 | W31: 368 | X31: 28 | Y31: 425 | Z31: 29 | AA31: 455 | AB31: 30 | AC31: 586 | AD31: 34
A34: Формовка простых патрубков
A36: Диаметр номинальный | B36: Диаметр наружный | C36: Минимальная длина патрубка | D36: Мф общая, кг | E36: Н1, мм | F36: S1, мм | G36: Мф фланца, кг | H36: Болтовое соединение для фланца | I36: Количество отверстий | J36: Dу | K36: Наружный диаметр трубы - D, мм. | L36: Внутреннее давление PN, атм. | M36: сцепка | N36: H, мм. | O36: S, мм. | P36: X, мм. | Q36: Y, мм. | R36: Мс - масса формованных слоев на стыке* кг. | S36: Мс - масса формованных слоев на стыке* кг. | V36: Количество башмаков/анкеров
A37: 50 | D37: 0.5 | G37: 0.4 | H37: М16х80 | I37: 4 | J37: 1000 | K37: 1025.1 | L37: 4 | M37: =J37&L37/10 -> 10000,4 | N37: 103 | O37: 4.5 | P37: 52 | Q37: 2 | R37: 6.4 | S37: =R37 -> 6.4 | W37: Глубина корпуса, м
A38: 65 | D38: 0.5 | G38: 0.5 | H38: М16х80 | I38: 4 | V38: Дн, м | W38: 3 | X38: 4 | Y38: 5 | Z38: 6 | AA38: 7 | AB38: 8 | AC38: 9 | AD38: 10 | AE38: 11 | AF38: 12 | AG38: 13 | AH38: 14 | AI38: 15 | AJ38: 16 | AK38: 17
A39: 80 | D39: 0.55 | G39: 0.6 | H39: М16х80 | I39: 4 | V39: 1.2 | W39: 3 | X39: 3 | Y39: 3 | Z39: 3 | AA39: =(AA38*1000*9.8*(3.14*V39^2)/4)/27500 -> 2.8198342 | AB39: =(AB38*1000*9.8*(3.14*V39^2)/4)/27500 -> 3.2226676 | AC39: =(AC38*1000*9.8*(3.14*V39^2)/4)/27500 -> 3.6255011 | AD39: =(AD38*1000*9.8*(3.14*V39^2)/4)/27500 -> 4.0283345 | AE39: =(AE38*1000*9.8*(3.14*V39^2)/4)/27500 -> 4.431168 | AF39: =(AF38*1000*9.8*(3.14*V39^2)/4)/27500 -> 4.8340015 | AG39: =(AG38*1000*9.8*(3.14*V39^2)/4)/27500 -> 5.2368349 | AH39: =(AH38*1000*9.8*(3.14*V39^2)/4)/27500 -> 5.6396684 | AI39: =(AI38*1000*9.8*(3.14*V39^2)/4)/27500 -> 6.0425018 | AJ39: =(AJ38*1000*9.8*(3.14*V39^2)/4)/27500 -> 6.4453353 | AK39: =(AK38*1000*9.8*(3.14*V39^2)/4)/27500 -> 6.8481687
A40: 100 | D40: 0.6 | G40: 0.9 | H40: М16х80 | I40: 8 | J40: 1000 | L40: 6 | M40: =J40&L40/10 -> 10000,6 | N40: 154 | O40: 6.5 | P40: 77 | R40: 12 | V40: 1.3 | W40: 3 | X40: 3 | Y40: 3 | Z40: =(Z38*1000*9.8*(3.14*V40^2)/4)/27500 -> 2.8366189 | AA40: =(AA38*1000*9.8*(3.14*V40^2)/4)/27500 -> 3.3093887 | AB40: =(AB38*1000*9.8*(3.14*V40^2)/4)/27500 -> 3.7821585 | AC40: =(AC38*1000*9.8*(3.14*V40^2)/4)/27500 -> 4.2549284 | AD40: =(AD38*1000*9.8*(3.14*V40^2)/4)/27500 -> 4.7276982 | AE40: =(AE38*1000*9.8*(3.14*V40^2)/4)/27500 -> 5.200468 | AF40: =(AF38*1000*9.8*(3.14*V40^2)/4)/27500 -> 5.6732378 | AG40: =(AG38*1000*9.8*(3.14*V40^2)/4)/27500 -> 6.1460076 | AH40: =(AH38*1000*9.8*(3.14*V40^2)/4)/27500 -> 6.6187775 | AI40: =(AI38*1000*9.8*(3.14*V40^2)/4)/27500 -> 7.0915473 | AJ40: =(AJ38*1000*9.8*(3.14*V40^2)/4)/27500 -> 7.5643171 | AK40: =(AK38*1000*9.8*(3.14*V40^2)/4)/27500 -> 8.0370869
A41: 150 | D41: 0.6 | G41: 1.4 | H41: М20х90 | I41: 8 | J41: 1000 | L41: 10 | M41: =J41&L41/10 -> 10001 | N41: 257 | O41: 10.5 | P41: 129 | R41: 28.5 | V41: 1.4 | W41: 3 | X41: 3 | Y41: =(Y38*1000*9.8*(3.14*V41^2)/4)/27500 -> 2.7415055 | Z41: =(Z38*1000*9.8*(3.14*V41^2)/4)/27500 -> 3.2898065 | AA41: =(AA38*1000*9.8*(3.14*V41^2)/4)/27500 -> 3.8381076 | AB41: =(AB38*1000*9.8*(3.14*V41^2)/4)/27500 -> 4.3864087 | AC41: =(AC38*1000*9.8*(3.14*$V41^2)/4)/27500 -> 4.9347098 | AD41: =(AD38*1000*9.8*(3.14*$V41^2)/4)/27500 -> 5.4830109 | AE41: =(AE38*1000*9.8*(3.14*$V41^2)/4)/27500 -> 6.031312 | AF41: =(AF38*1000*9.8*(3.14*$V41^2)/4)/27500 -> 6.5796131 | AG41: =(AG38*1000*9.8*(3.14*$V41^2)/4)/27500 -> 7.1279142 | AH41: =(AH38*1000*9.8*(3.14*$V41^2)/4)/27500 -> 7.6762153 | AI41: =(AI38*1000*9.8*(3.14*$V41^2)/4)/27500 -> 8.2245164 | AJ41: =(AJ38*1000*9.8*(3.14*$V41^2)/4)/27500 -> 8.7728175 | AK41: =(AK38*1000*9.8*(3.14*$V41^2)/4)/27500 -> 9.3211185
A42: 200 | D42: 0.6 | G42: 1.8 | H42: М20х90 | I42: 12 | J42: 1000 | L42: 16 | M42: =J42&L42/10 -> 10001,6 | N42: 411 | O42: 16.5 | P42: 206 | R42: 71.3 | V42: 1.5 | W42: 3 | X42: =(X38*1000*9.8*(3.14*V42^2)/4)/27500 -> 2.5177091 | Y42: =(Y38*1000*9.8*(3.14*V42^2)/4)/27500 -> 3.1471364 | Z42: =(Z38*1000*9.8*(3.14*V42^2)/4)/27500 -> 3.7765636 | AA42: =(AA38*1000*9.8*(3.14*V42^2)/4)/27500 -> 4.4059909 | AB42: =(AB38*1000*9.8*(3.14*V42^2)/4)/27500 -> 5.0354182 | AC42: =(AC38*1000*9.8*(3.14*$V42^2)/4)/27500 -> 5.6648455 | AD42: =(AD38*1000*9.8*(3.14*$V42^2)/4)/27500 -> 6.2942727 | AE42: =(AE38*1000*9.8*(3.14*$V42^2)/4)/27500 -> 6.9237 | AF42: =(AF38*1000*9.8*(3.14*$V42^2)/4)/27500 -> 7.5531273 | AG42: =(AG38*1000*9.8*(3.14*$V42^2)/4)/27500 -> 8.1825545 | AH42: =(AH38*1000*9.8*(3.14*$V42^2)/4)/27500 -> 8.8119818 | AI42: =(AI38*1000*9.8*(3.14*$V42^2)/4)/27500 -> 9.4414091 | AJ42: =(AJ38*1000*9.8*(3.14*$V42^2)/4)/27500 -> 10.070836 | AK42: =(AK38*1000*9.8*(3.14*$V42^2)/4)/27500 -> 10.700264
A43: 250 | D43: 0.6 | G43: 2.3 | H43: М24х100 | I43: 12 | J43: 1000 | L43: 20 | M43: =J43&L43/10 -> 10002 | N43: 513 | O43: 20.5 | P43: 257 | R43: 103.5 | V43: 1.6 | W43: 3 | X43: =(X38*1000*9.8*(3.14*V43^2)/4)/27500 -> 2.8645935 | Y43: =(Y38*1000*9.8*(3.14*V43^2)/4)/27500 -> 3.5807418 | Z43: =(Z38*1000*9.8*(3.14*V43^2)/4)/27500 -> 4.2968902 | AA43: =(AA38*1000*9.8*(3.14*V43^2)/4)/27500 -> 5.0130385 | AB43: =(AB38*1000*9.8*(3.14*V43^2)/4)/27500 -> 5.7291869 | AC43: =(AC38*1000*9.8*(3.14*$V43^2)/4)/27500 -> 6.4453353 | AD43: =(AD38*1000*9.8*(3.14*$V43^2)/4)/27500 -> 7.1614836 | AE43: =(AE38*1000*9.8*(3.14*$V43^2)/4)/27500 -> 7.877632 | AF43: =(AF38*1000*9.8*(3.14*$V43^2)/4)/27500 -> 8.5937804 | AG43: =(AG38*1000*9.8*(3.14*$V43^2)/4)/27500 -> 9.3099287 | AH43: =(AH38*1000*9.8*(3.14*$V43^2)/4)/27500 -> 10.026077 | AI43: =(AI38*1000*9.8*(3.14*$V43^2)/4)/27500 -> 10.742225 | AJ43: =(AJ38*1000*9.8*(3.14*$V43^2)/4)/27500 -> 11.458374 | AK43: =(AK38*1000*9.8*(3.14*$V43^2)/4)/27500 -> 12.174522
A44: 300 | B44: 314.6 | C44: 375 | D44: 0.6 | E44: 78 | F44: 5.7 | G44: 3.1 | H44: М24х100 | I44: 12 | J44: 1100 | K44: 1126.5 | L44: 4 | M44: =J44&L44/10 -> 11000,4 | N44: 113 | O44: 4.5 | P44: 57 | R44: 7 | S44: =R44 -> 7 | V44: 1.7 | W44: 3 | X44: =(X38*1000*9.8*(3.14*V44^2)/4)/27500 -> 3.2338575 | Y44: =(Y38*1000*9.8*(3.14*V44^2)/4)/27500 -> 4.0423218 | Z44: =(Z38*1000*9.8*(3.14*V44^2)/4)/27500 -> 4.8507862 | AA44: =(AA38*1000*9.8*(3.14*V44^2)/4)/27500 -> 5.6592505 | AB44: =(AB38*1000*9.8*(3.14*V44^2)/4)/27500 -> 6.4677149 | AC44: =(AC38*1000*9.8*(3.14*$V44^2)/4)/27500 -> 7.2761793 | AD44: =(AD38*1000*9.8*(3.14*$V44^2)/4)/27500 -> 8.0846436 | AE44: =(AE38*1000*9.8*(3.14*$V44^2)/4)/27500 -> 8.893108 | AF44: =(AF38*1000*9.8*(3.14*$V44^2)/4)/27500 -> 9.7015724 | AG44: =(AG38*1000*9.8*(3.14*$V44^2)/4)/27500 -> 10.510037 | AH44: =(AH38*1000*9.8*(3.14*$V44^2)/4)/27500 -> 11.318501 | AI44: =(AI38*1000*9.8*(3.14*$V44^2)/4)/27500 -> 12.126965 | AJ44: =(AJ38*1000*9.8*(3.14*$V44^2)/4)/27500 -> 12.93543 | AK44: =(AK38*1000*9.8*(3.14*$V44^2)/4)/27500 -> 13.743894
A45: 350 | B45: 366.6 | C45: 390 | D45: 0.9 | E45: 90 | F45: 5.7 | G45: 3.6 | H45: М24х100 | I45: 16 | J45: 1100 | L45: 6 | M45: =J45&L45/10 -> 11000,6 | N45: 170 | O45: 7 | P45: 85 | R45: 14.8 | V45: 1.8 | W45: =(W38*1000*9.8*(3.14*V45^2)/4)/27500 -> 2.7191258 | X45: =(X38*1000*9.8*(3.14*V45^2)/4)/27500 -> 3.6255011 | Y45: =(Y38*1000*9.8*(3.14*V45^2)/4)/27500 -> 4.5318764 | Z45: =(Z38*1000*9.8*(3.14*V45^2)/4)/27500 -> 5.4382516 | AA45: =(AA38*1000*9.8*(3.14*V45^2)/4)/27500 -> 6.3446269 | AB45: =(AB38*1000*9.8*(3.14*V45^2)/4)/27500 -> 7.2510022 | AC45: =(AC38*1000*9.8*(3.14*$V45^2)/4)/27500 -> 8.1573775 | AD45: =(AD38*1000*9.8*(3.14*$V45^2)/4)/27500 -> 9.0637527 | AE45: =(AE38*1000*9.8*(3.14*$V45^2)/4)/27500 -> 9.970128 | AF45: =(AF38*1000*9.8*(3.14*$V45^2)/4)/27500 -> 10.876503 | AG45: =(AG38*1000*9.8*(3.14*$V45^2)/4)/27500 -> 11.782879 | AH45: =(AH38*1000*9.8*(3.14*$V45^2)/4)/27500 -> 12.689254 | AI45: =(AI38*1000*9.8*(3.14*$V45^2)/4)/27500 -> 13.595629 | AJ45: =(AJ38*1000*9.8*(3.14*$V45^2)/4)/27500 -> 14.502004 | AK45: =(AK38*1000*9.8*(3.14*$V45^2)/4)/27500 -> 15.40838
A46: 400 | B46: 413.1 | C46: 406 | D46: 1.1 | E46: 101 | F46: 6.8 | G46: 4.6 | H46: М24х100 | I46: 16 | J46: 1100 | L46: 10 | M46: =J46&L46/10 -> 11001 | N46: 282 | O46: 11.5 | P46: 141 | R46: 37.6 | V46: 1.9 | W46: =(W38*1000*9.8*(3.14*V46^2)/4)/27500 -> 3.0296433 | X46: =(X38*1000*9.8*(3.14*V46^2)/4)/27500 -> 4.0395244 | Y46: =(Y38*1000*9.8*(3.14*V46^2)/4)/27500 -> 5.0494055 | Z46: =(Z38*1000*9.8*(3.14*V46^2)/4)/27500 -> 6.0592865 | AA46: =(AA38*1000*9.8*(3.14*V46^2)/4)/27500 -> 7.0691676 | AB46: =(AB38*1000*9.8*(3.14*V46^2)/4)/27500 -> 8.0790487 | AC46: =(AC38*1000*9.8*(3.14*$V46^2)/4)/27500 -> 9.0889298 | AD46: =(AD38*1000*9.8*(3.14*$V46^2)/4)/27500 -> 10.098811 | AE46: =(AE38*1000*9.8*(3.14*$V46^2)/4)/27500 -> 11.108692 | AF46: =(AF38*1000*9.8*(3.14*$V46^2)/4)/27500 -> 12.118573 | AG46: =(AG38*1000*9.8*(3.14*$V46^2)/4)/27500 -> 13.128454 | AH46: =(AH38*1000*9.8*(3.14*$V46^2)/4)/27500 -> 14.138335 | AI46: =(AI38*1000*9.8*(3.14*$V46^2)/4)/27500 -> 15.148216 | AJ46: =(AJ38*1000*9.8*(3.14*$V46^2)/4)/27500 -> 16.158097 | AK46: =(AK38*1000*9.8*(3.14*$V46^2)/4)/27500 -> 17.167979
A47: 450 | B47: 464.1 | C47: 433 | D47: 1.3 | E47: 113 | F47: 6.8 | G47: 5.3 | H47: М24х100 | I47: 20 | J47: 1100 | L47: 16 | M47: =J47&L47/10 -> 11001,6 | N47: 450 | O47: 18 | P47: 225 | R47: 87.3 | V47: 2 | W47: =(W38*1000*9.8*(3.14*V47^2)/4)/27500 -> 3.3569455 | X47: =(X38*1000*9.8*(3.14*V47^2)/4)/27500 -> 4.4759273 | Y47: =(Y38*1000*9.8*(3.14*V47^2)/4)/27500 -> 5.5949091 | Z47: =(Z38*1000*9.8*(3.14*V47^2)/4)/27500 -> 6.7138909 | AA47: =(AA38*1000*9.8*(3.14*V47^2)/4)/27500 -> 7.8328727 | AB47: =(AB38*1000*9.8*(3.14*V47^2)/4)/27500 -> 8.9518545 | AC47: =(AC38*1000*9.8*(3.14*$V47^2)/4)/27500 -> 10.070836 | AD47: =(AD38*1000*9.8*(3.14*V47^2)/4)/27500 -> 11.189818 | AE47: =(AE38*1000*9.8*(3.14*V47^2)/4)/27500 -> 12.3088 | AF47: =(AF38*1000*9.8*(3.14*V47^2)/4)/27500 -> 13.427782 | AG47: =(AG38*1000*9.8*(3.14*V47^2)/4)/27500 -> 14.546764 | AH47: =(AH38*1000*9.8*(3.14*V47^2)/4)/27500 -> 15.665745 | AI47: =(AI38*1000*9.8*(3.14*V47^2)/4)/27500 -> 16.784727 | AJ47: =(AJ38*1000*9.8*(3.14*V47^2)/4)/27500 -> 17.903709 | AK47: =(AK38*1000*9.8*(3.14*V47^2)/4)/27500 -> 19.022691
